Workbook
Name ESTIMATEUR: 'SOMM. T.OFF'!$A$69:$A$72
Name ESTIMATEUR: 'SOMM. T.OFF'!$A$69:$A$72

Sheet ESTIMÉ
A1: PROJET | H1: Estimé no. | K1: Page : 1 de 2 | L1: PROJET | M1: =IF(B1="","",B1) | R1: Estimé no. | T1: =IF(I1="","",I1) | V1: Page: 2 de 2
H2: Date fermeture | L2: CONDUITS RECTANGULAIRES | X2: Calcul Sismique
A3: Adresse | H3: Plans | L3: FABRICATION | P3: SUSPENSION | R3: INSTALLATION
A4: INGÉNIEUR | H4: Section devis | L4: TYPES | M4: LBS | N4: PIEDS | O4: COÛT | P4: QTÉ | Q4: COÛT | R4: GENRE | S4: Pi | T4: Pi/J | U4: HRES | V4: COÛT
A5: ARCHITECTE | L5: BASSE PRESSION | M5: =IF('SOMM. T.OFF'!B14="","",'SOMM. T.OFF'!B14) -> 0 | N5: =IF('SOMM. T.OFF'!C14="","",'SOMM. T.OFF'!C14) -> 0 | O5: =IF(M5="",0,M5*DONNÉES!C16) -> 0 | Q5: =IF(P5="",N5*DONNÉES!D16,P5*DONNÉES!E16) -> 0 | R5: SM (Salle mé) | S5: =IF('SOMM. T.OFF'!F14="",0,'SOMM. T.OFF'!F14) -> 0 | T5: =IF(S5=0,0,"") -> 0 | U5: =IF(S5=0,0,S5/T5*8) -> 0 | V5: =IF(T5="","",U5*DONNÉES!$E$12) -> 0 | X5: Équipement | Y5: Qté | Z5: Prix | AA5: Total
A6: PROPRIÉTAIRE | H6: Addenda | L6: MOYENNE PRESSION | M6: =IF('SOMM. T.OFF'!B15="","",'SOMM. T.OFF'!B15) -> 0 | N6: =IF('SOMM. T.OFF'!C15="","",'SOMM. T.OFF'!C15) -> 0 | O6: =IF(M6="",0,M6*DONNÉES!C17) -> 0 | Q6: =IF(P6="",N6*DONNÉES!D17,P6*DONNÉES!E17) -> 0 | R6: HA (30" et -) | S6: =IF('SOMM. T.OFF'!F15="",0,'SOMM. T.OFF'!F15) -> 0 | T6: =IF(S6=0,0,"") -> 0 | U6: =IF(S6=0,0,S6/T6*8) -> 0 | V6: =IF(T6="","",U6*DONNÉES!$E$12) -> 0 | X6: Rapport (nbr visite) | Y6: 1 | Z6: 750 | AA6: =Z6*Y6 -> 750
A7: ESTIMATEUR | H7: Échéancier | L7: HAUTE PRESSION | M7: =IF('SOMM. T.OFF'!B16="","",'SOMM. T.OFF'!B16) -> 0 | N7: =IF('SOMM. T.OFF'!C16="","",'SOMM. T.OFF'!C16) -> 0 | O7: =IF(M7="",0,M7*DONNÉES!C18) -> 0 | Q7: =IF(P7="",N7*DONNÉES!D18,P7*DONNÉES!E18) -> 0 | R7: RI (Riser/SP) | S7: =IF('SOMM. T.OFF'!F16="",0,'SOMM. T.OFF'!F16) -> 0 | T7: =IF(S7=0,0,"") -> 0 | U7: =IF(S7=0,0,S7/T7*8) -> 0 | V7: =IF(T7="","",U7*DONNÉES!$E$12) -> 0 | X7: Centrales d'air | Z7: 500 | AA7: =Z7*Y7 -> 0
A8: ÉQUIPEMENTS | L8: 16 GA | M8: =IF('SOMM. T.OFF'!B17="","",'SOMM. T.OFF'!B17) -> 0 | N8: =IF('SOMM. T.OFF'!C17="","",'SOMM. T.OFF'!C17) -> 0 | O8: =IF(M8="",0,M8*DONNÉES!C19) -> 0 | Q8: =IF(P8="",N8*DONNÉES!D19,P8*DONNÉES!E19) -> 0 | R8: 16 (16ga/SS) | S8: =IF('SOMM. T.OFF'!F18="",0,'SOMM. T.OFF'!F18) -> 0 | T8: =IF(S8=0,0,"") -> 0 | U8: =IF(S8=0,0,S8/T8*8) -> 0 | V8: =IF(T8="","",U8*DONNÉES!$E$12) -> 0 | X8: Unité au toit | Z8: 250 | AA8: =Z8*Y8 -> 0
A9: DESCRIPTION | C9: TAG | D9: SPECS | E9: DEVIS | F9: QTÉ | G9: HRES | H9: ACCESSOIRES | I9: COÛT INSTAL. | J9: MAT'L ESTIMÉ | K9: MAT'L RÉEL | L9: ALUMINIUM | M9: =IF('SOMM. T.OFF'!B18="","",'SOMM. T.OFF'!B18) -> 0 | N9: =IF('SOMM. T.OFF'!C18="","",'SOMM. T.OFF'!C18) -> 0 | O9: =IF(M9="",0,M9*DONNÉES!C20) -> 0 | Q9: =IF(P9="",N9*DONNÉES!D20,P9*DONNÉES!E20) -> 0 | R9: AL (Alumi) | S9: =IF('SOMM. T.OFF'!F19="",0,'SOMM. T.OFF'!F19) -> 0 | T9: =IF(S9=0,0,"") -> 0 | U9: =IF(S9=0,0,S9/T9*8) -> 0 | V9: =IF(T9="","",U9*DONNÉES!$E$12) -> 0 | X9: Centrale au toit | Z9: 500 | AA9: =Z9*Y9 -> 0
A10: UNITÉ DE CLIM. | H10: =IF(F10=0,0,"") -> 0 | I10: =IF(G10=0,0,G10*DONNÉES!$E$12) -> 0 | J10: =IF(E10=0,0,"") -> 0 | K10: =IF(E10=0,0,"") -> 0 | L10: ACIER INOXYDABLE | M10: =IF('SOMM. T.OFF'!B19="","",'SOMM. T.OFF'!B19) -> 0 | N10: =IF('SOMM. T.OFF'!C19="","",'SOMM. T.OFF'!C19) -> 0 | O10: =IF(M10="",0,M10*DONNÉES!C21) -> 0 | Q10: =IF(P10="",N10*DONNÉES!D21,P10*DONNÉES!E21) -> 0 | R10: RE (31" et +) | S10: =IF('SOMM. T.OFF'!F17="",0,'SOMM. T.OFF'!F17) -> 0 | T10: 0 | U10: =IF(S10=0,0,S10/T10*8) -> 0 | V10: =IF(T10="","",U10*DONNÉES!$E$12) -> 0 | X10: Condenseur | Z10: 80 | AA10: =Z10*Y10 -> 0
A11: BASE DE TOIT | H11: =IF(F11=0,0,"") -> 0 | I11: =IF(G11=0,0,G11*DONNÉES!$E$12) -> 0 | J11: =IF(E11=0,0,"") -> 0 | K11: =IF(E11=0,0,"") -> 0 | M11: =IF('SOMM. T.OFF'!B20="","",'SOMM. T.OFF'!B20) -> 0 | N11: =IF('SOMM. T.OFF'!C20="","",'SOMM. T.OFF'!C20) -> 0 | O11: =IF(M11="",0,M11*DONNÉES!C22) -> 0 | Q11: =IF(P11="",N11*DONNÉES!D22,P11*DONNÉES!E22) -> 0 | S11: =IF('SOMM. T.OFF'!F20="","",'SOMM. T.OFF'!F20) -> 0 | T11: =IF(S11=0,0,"") -> 0 | U11: =IF(S11=0,0,S11/T11*8) -> 0 | V11: =IF(T11="","",U11*DONNÉES!$E$12) -> 0 | X11: Thermopompe (intérieur) | Z11: 80 | AA11: =Z11*Y11 -> 0
A12: UNITÉ DE COND. | H12: =IF(F12=0,0,"") -> 0 | I12: =IF(G12=0,0,G12*DONNÉES!$E$12) -> 0 | J12: =IF(E12=0,0,"") -> 0 | K12: =IF(E12=0,0,"") -> 0 | L12: SOUDURE (atelier) | M12: HEURES--> | O12: =N12*DONNÉES!E26 -> 0 | R12: Soudure | V12: =U12*DONNÉES!$E$25 -> 0 | X12: Fancoil | Z12: 80 | AA12: =Z12*Y12 -> 0
A13: ÉVAPORATEUR | H13: =IF(F13=0,0,"") -> 0 | I13: =IF(G13=0,0,G13*DONNÉES!$E$12) -> 0 | J13: =IF(E13=0,0,"") -> 0 | K13: =IF(E13=0,0,"") -> 0 | L13: SOUS-TOTAL | M13: =SUM(M5:M11) -> 0 | N13: =SUM(N5:N11) -> 0 | O13: =SUM(O5:O12) -> 0 | Q13: =SUM(Q5:Q11) -> 0 | U13: =SUM(U5:U11) -> 0 | V13: =SUM(V5:V12) -> 0 | X13: Buse d'humidificateur | Z13: 50 | AA13: =Z13*Y13 -> 0
A14: UNITÉ DE VENTI. INT. | H14: =IF(F14=0,0,"") -> 0 | I14: =IF(G14=0,0,G14*DONNÉES!$E$12) -> 0 | J14: =IF(E14=0,0,"") -> 0 | K14: =IF(E14=0,0,"") -> 0 | X14: Boites | Z14: 25 | AA14: =Z14*Y14 -> 0
A15: UNITÉ DE RÉCUP. | H15: =IF(F15=0,0,"") -> 0 | I15: =IF(G15=0,0,G15*DONNÉES!$E$12) -> 0 | J15: =IF(E15=0,0,"") -> 0 | K15: =IF(E15=0,0,"") -> 0 | L15: CONDUITS SPIRALS | X15: Diffuseurs | Z15: 3 | AA15: =Z15*Y15 -> 0
A16: BASE DE TOIT | H16: =IF(F16=0,0,"") -> 0 | I16: =IF(G16=0,0,G16*DONNÉES!$E$12) -> 0 | J16: =IF(E16=0,0,"") -> 0 | K16: =IF(E16=0,0,"") -> 0 | L16: CONDUITS | N16: JOINTS | P16: SUSPENSION | R16: INSTALLATION | X16: Ventilateur toit | Z16: 15 | AA16: =Z16*Y16 -> 0
A17: UNITÉ D'AIR NEUF | H17: =IF(F17=0,0,"") -> 0 | I17: =IF(G17=0,0,G17*DONNÉES!$E$12) -> 0 | J17: =IF(E17=0,0,"") -> 0 | K17: =IF(E17=0,0,"") -> 0 | L17: TYPES | M17: PIEDS | N17: QTÉ | O17: COÛT | P17: QTÉ | Q17: COÛT | R17: GENRE | S17: Pi | T17: Pi/J | U17: HRES | V17: COÛT | X17: Ventilateur cabinet | Z17: 80 | AA17: =Z17*Y17 -> 0
A18: BASE DE TOIT | H18: =IF(F18=0,0,"") -> 0 | I18: =IF(G18=0,0,G18*DONNÉES!$E$12) -> 0 | J18: =IF(E18=0,0,"") -> 0 | K18: =IF(E18=0,0,"") -> 0 | L18: BASSE PRESSION | O18: =N18*DONNÉES!E34 -> 0 | Q18: =M18*DONNÉES!E47 -> 0 | R18: 16" et - | S18: =SPIRALE!T23 -> 0 | T18: =IF(S18=0,1,"??") -> 1 | U18: =IF(S18="","",S18/T18*8) -> 0 | V18: =IF(T18="",0,U18*DONNÉES!$E$12) -> 0 | X18: Gros ventilateur | Z18: 150 | AA18: =Z18*Y18 -> 0
A19: UNITÉ DE DÉHUMID. | H19: =IF(F19=0,0,"") -> 0 | I19: =IF(G19=0,0,G19*DONNÉES!$E$12) -> 0 | J19: =IF(E19=0,0,"") -> 0 | K19: =IF(E19=0,0,"") -> 0 | L19: MOYENNE PRESSION | O19: =N19*DONNÉES!E35 -> 0 | Q19: =IF(P19="",M19*DONNÉES!E33,P19*DONNÉES!E32) -> 0 | R19: 18" et + | S19: =SPIRALE!T24 -> 0 | T19: =IF(S19=0,1,"??") -> 1 | U19: =IF(S19="","",S19/T19*8) -> 0 | V19: =IF(T19="",0,U19*DONNÉES!$E$12) -> 0 | X19: Ventilateur strobic | Z19: 350 | AA19: =Z19*Y19 -> 0
A20: BASE DE TOIT | H20: =IF(F20=0,0,"") -> 0 | I20: =IF(G20=0,0,G20*DONNÉES!$E$12) -> 0 | J20: =IF(E20=0,0,"") -> 0 | K20: =IF(E20=0,0,"") -> 0 | L20: HAUTE PRESSION | O20: =N20*DONNÉES!E36 -> 0 | Q20: =IF(P20="",M20*DONNÉES!E33,P20*DONNÉES!E32) -> 0 | U20: =IF(S20="","",S20/T20*8) | V20: =IF(T20="",0,U20*DONNÉES!$E$12) -> 0 | X20: Section filtre | Z20: 50 | AA20: =Z20*Y20 -> 0
A21: VENTILATEUR CABINET | H21: =IF(F21=0,0,"") -> 0 | I21: =IF(G21=0,0,G21*DONNÉES!$E$12) -> 0 | J21: =IF(E21=0,0,"") -> 0 | K21: =IF(E21=0,0,"") -> 0 | O21: =N21*DONNÉES!E37 -> 0 | Q21: =IF(P21="",M21*DONNÉES!E33,P21*DONNÉES!E32) -> 0 | U21: =IF(S21="","",S21/T21*8) | V21: =IF(T21="",0,U21*DONNÉES!$E$12) -> 0 | X21: Silencieux | Z21: 50 | AA21: =Z21*Y21 -> 0
A22: VENTILATEUR DE TOIT | H22: =IF(F22=0,0,"") -> 0 | I22: =IF(G22=0,0,G22*DONNÉES!$E$12) -> 0 | J22: =IF(E22=0,0,"") -> 0 | K22: =IF(E22=0,0,"") -> 0 | M22: SOUS-TOTAL | O22: =SUM(O18:O21) -> 0 | Q22: =SUM(Q18:Q21) -> 0 | R22: SOUDURE | S22: HEURES---> | V22: =U22*DONNÉES!E25 -> 0 | X22: Conduits 6 pi.ca. et + (au 20') | Z22: 300 | AA22: =Z22*Y22 -> 0
A23: BASE DE TOIT | H23: =IF(F23=0,0,"") -> 0 | I23: =IF(G23=0,0,G23*DONNÉES!$E$12) -> 0 | J23: =IF(E23=0,0,"") -> 0 | K23: =IF(E23=0,0,"") -> 0 | M23: COÛT CONDUITS & FITTINGS | P23: =SPIRALE!$F$6 -> 0 | R23: SOUS-TOTAL | U23: =SUM(U15:U22) -> 0 | V23: =SUM(V15:V22) -> 0 | X23: Autres Équipements | Z23: 500 | AA23: =Z23*Y23 -> 0
A24: VENTILATEUR TOILETTE | H24: =IF(F24=0,0,"") -> 0 | I24: =IF(G24=0,0,G24*DONNÉES!$E$12) -> 0 | J24: =IF(E24=0,0,"") -> 0 | K24: =IF(E24=0,0,"") -> 0
A25: HUMIDIFICATEUR | H25: =IF(F25=0,0,"") -> 0 | I25: =IF(G25=0,0,G25*DONNÉES!$E$12) -> 0 | J25: =IF(E25=0,0,"") -> 0 | K25: =IF(E25=0,0,"") -> 0
A26: SERPENTINS ÉLECTRIQUES | H26: =IF(F26=0,0,"") -> 0 | I26: =IF(G26=0,0,G26*DONNÉES!$E$12) -> 0 | J26: =IF(E26=0,0,"") -> 0 | K26: =IF(E26=0,0,"") -> 0
A27: SERPENTINS | H27: =IF(F27=0,0,"") -> 0 | I27: =IF(G27=0,0,G27*DONNÉES!$E$12) -> 0 | J27: =IF(E27=0,0,"") -> 0 | K27: =IF(E27=0,0,"") -> 0
A28: HOTTE COMMERCIALE | H28: =IF(F28=0,0,"") -> 0 | I28: =IF(G28=0,0,G28*DONNÉES!$E$12) -> 0 | J28: =IF(E28=0,0,"") -> 0 | K28: =IF(E28=0,0,"") -> 0
A29: HOTTE RÉSIDENTIELLE | H29: =IF(F29=0,0,"") -> 0 | I29: =IF(G29=0,0,G29*DONNÉES!$E$12) -> 0 | J29: =IF(E29=0,0,"") -> 0 | K29: =IF(E29=0,0,"") -> 0
A30: BOÎTES | H30: =IF(F30=0,0,"") -> 0 | I30: =IF(G30=0,0,G30*DONNÉES!$E$12) -> 0 | J30: =IF(E30=0,0,"") -> 0 | K30: =IF(E30=0,0,"") -> 0 | X30: Autres Équipements | Z30: 250 | AA30: =Z30*Y30 -> 0
A31: GRILLES ET DIFFUSEURS | H31: 0 | I31: =IF(G31=0,0,G31*DONNÉES!$E$12) -> 0 | J31: =IF(E31=0,0,"") -> 0 | K31: =IF(E31=0,0,"") -> 0 | L31: ISOLANT ACOUSTIQUE | P31: ACCESSOIRES - CONDUITS | X31: Autres Équipements | Z31: 100 | AA31: =Z31*Y31 -> 0
A32: PLENUMS | H32: 0 | I32: =IF(G32=0,0,G32*DONNÉES!$E$12) -> 0 | J32: =IF(E32=0,0,"") -> 0 | K32: =IF(E32=0,0,"") -> 0 | L32: TYPE | N32: PI. CAR. | O32: COUT | P32: DESCRIPTION | U32: QTE | V32: COUT | X32: Autres Équipements | Z32: 50 | AA32: =Z32*Y32 -> 0
A33: PERSIENNES | H33: =IF(F33=0,0,"") -> 0 | I33: =IF(G33=0,0,G33*DONNÉES!$E$12) -> 0 | J33: =IF(E33=0,0,"") -> 0 | K33: =IF(E33=0,0,"") -> 0 | L33: 1/2" FLEXIBLE | N33: =IF('SOMM. T.OFF'!D32="","",'SOMM. T.OFF'!D32) -> 0 | O33: =N33*DONNÉES!E27 -> 0 | P33: CANEVAS (pi) | R33: 4"-4"-4" ST | U33: =IF('SOMM. T.OFF'!H49=0,0,'SOMM. T.OFF'!H49) -> 0 | V33: =U33*DONNÉES!I12 -> 0 | AA33: =Z33*Y33 -> 0
A34: CABANONS | H34: =IF(F34=0,0,"") -> 0 | I34: =IF(G34=0,0,G34*DONNÉES!$E$12) -> 0 | J34: =IF(E34=0,0,"") -> 0 | K34: =IF(E34=0,0,"") -> 0 | L34: 1" FLEXIBLE | N34: =IF('SOMM. T.OFF'!D33="","",'SOMM. T.OFF'!D33) -> 0 | O34: =N34*DONNÉES!E28 -> 0 | R34: 4''-4''-4'' XL | U34: =IF('SOMM. T.OFF'!H50=0,0,'SOMM. T.OFF'!H50) -> 0 | V34: =U34*DONNÉES!I13 -> 0 | AA34: =Z34*Y34 -> 0
A35: SORTIES MURALES | H35: =IF(F35=0,0,"") -> 0 | I35: =IF(G35=0,0,G35*DONNÉES!$E$12) -> 0 | J35: =IF(E35=0,0,"") -> 0 | K35: =IF(E35=0,0,"") -> 0 | L35: 1" RIGIDE | N35: =IF('SOMM. T.OFF'!D34="","",'SOMM. T.OFF'!D34) -> 0 | O35: =N35*DONNÉES!E29 -> 0 | P35: GRILLAGE (pi.car.) | R35: SANS CADRE | U35: =IF('SOMM. T.OFF'!F58="",0,'SOMM. T.OFF'!F58) -> 0 | V35: =U35*DONNÉES!I14 -> 0 | AA35: =Z35*Y35 -> 0
A36: VOLETS COUPE-FEU | F36: =IF('SOMM. T.OFF'!E52=0,0,'SOMM. T.OFF'!E52) -> 0 | H36: 0 | I36: =IF(G36=0,0,G36*DONNÉES!$E$12) -> 0 | J36: =IF(E36=0,0,"") -> 0 | K36: =IF(E36=0,0,"") -> 0 | L36: 2" | N36: =IF('SOMM. T.OFF'!D35="","",'SOMM. T.OFF'!D35) -> 0 | O36: =N36*DONNÉES!E30 -> 0 | R36: AVEC CADRE | U36: =IF('SOMM. T.OFF'!F59="",0,'SOMM. T.OFF'!F59) -> 0 | V36: =U36*DONNÉES!I15 -> 0 | AA36: =Z36*Y36 -> 0
A37: VOLETS COUPE-FEU/FUMÉE | F37: ='SOMM. T.OFF'!E62 -> 0 | H37: 0 | I37: =IF(G37=0,0,G37*DONNÉES!$E$12) -> 0 | J37: =IF(E37=0,0,"") -> 0 | K37: =IF(E37=0,0,"") -> 0 | M37: SOUS-TOTAL | O37: =SUM(O33:O36) -> 0 | P37: VOLETS MANUELS TUYAUX CHAUFFAGE (unitaire) | U37: =IF('SOMM. T.OFF'!E51=0,0,'SOMM. T.OFF'!E51) -> 0 | V37: =U37*DONNÉES!I16 -> 0 | Y37: GRAND TOTAL | AA37: =SUM(AA6:AA36) -> 750
A38: VOLETS MOTORISÉS | F38: =IF(AND('SOMM. T.OFF'!E53,'SOMM. T.OFF'!E54,0),0,'SOMM. T.OFF'!E53+'SOMM. T.OFF'!E54) -> 0 | H38: 0 | I38: =IF(G38=0,0,G38*DONNÉES!$E$12) -> 0 | J38: =IF(E38=0,0,('SOMM. T.OFF'!F53*DONNÉES!I34)+('SOMM. T.OFF'!F54*DONNÉES!I35)) -> 0 | K38: =IF(E38=0,0,"") -> 0 | P38: SIDE TAKE-OFF C/A SPLITTER (unitaire) | U38: =IF('SOMM. T.OFF'!E60=0,0,'SOMM. T.OFF'!E60) -> 0 | V38: =U38*DONNÉES!I17 -> 0
A39: ACTUATEUR | H39: 0 | I39: =IF(G39=0,0,G39*DONNÉES!$E$12) -> 0 | J39: =IF(E39=0,0,"") -> 0 | K39: =IF(E39=0,0,"") -> 0 | L39: MAIN D'OEUVRE - DIVERS | P39: T. VANES (pi.car.) | R39: SIMPLE | U39: =IF('SOMM. T.OFF'!F47=0,0,'SOMM. T.OFF'!F47) -> 0 | V39: =U39*DONNÉES!I18 -> 0 | X39: Calul Dessins
A40: FILTRES | H40: =IF(F40=0,0,"") -> 0 | I40: =IF(G40=0,0,G40*DONNÉES!$E$12) -> 0 | J40: =IF(E40=0,0,"") -> 0 | K40: =IF(E40=0,0,"") -> 0 | L40: DESCRIPTION | N40: HRES | O40: COUT | R40: DOUBLE | U40: =IF('SOMM. T.OFF'!F48=0,0,'SOMM. T.OFF'!F48) -> 0 | V40: =U40*DONNÉES!I19 -> 0
A41: SILENCIEUX | H41: =IF(F41=0,0,"") -> 0 | I41: =IF(G41=0,0,G41*DONNÉES!$E$12) -> 0 | J41: =IF(E41=0,0,"") -> 0 | K41: =IF(E41=0,0,"") -> 0 | L41: SLEEVAGE | O41: =IF(N41=0,0,N41*DONNÉES!E41) -> 0 | P41: VOLETS MANUELS | R41: SANS CADRE (unitaire) | U41: =IF('SOMM. T.OFF'!E56=0,0,'SOMM. T.OFF'!E56) -> 0 | V41: =U41*DONNÉES!I20 -> 0
A42: TRAPPES D'ACCÈS ARCHITECTURALES | E42: =IF(INFOSPROJET!D64="","",INFOSPROJET!D64) | H42: 0 | I42: =IF(G42=0,0,G42*DONNÉES!$E$12) -> 0 | J42: =IF(E42="",0,"") -> 0 | K42: =J42 -> 0 | L42: ÉTANCHÉITÉ | O42: =IF(N42=0,0,N42*DONNÉES!E42) -> 0 | R42: AVEC CADRE (pi.car.) | U42: =IF('SOMM. T.OFF'!F57=0,0,'SOMM. T.OFF'!F57) -> 0 | V42: =U42*DONNÉES!I21 -> 0 | X42: CALCUL LBS | Y42: "X" | Z42: Lbs rectangle | AA42: Lbs autre approx* | AB42: Lbs/heure | AC42: Heures
A43: DÉMARREURS | H43: 0 | I43: =IF(G43=0,0,G43*DONNÉES!$E$12) -> 0 | J43: =IF(E43=0,0,"") -> 0 | K43: =IF(E43=0,0,"") -> 0 | L43: IDENTIFICATION | O43: =IF(N43=0,0,N43*DONNÉES!E43) -> 0 | P43: VOLETS GRAVITÉ (pi.car.) | U43: =IF('SOMM. T.OFF'!F55=0,0,'SOMM. T.OFF'!F55) -> 0 | V43: =U43*DONNÉES!I22 -> 0 | X43: REVIT / STANDARD | Y43: X | Z43: =M13 -> 0 | AA43: =AA47*3.4 -> 0 | AB43: 62.5 | AC43: =IF(Y43="x",($Z$43+$AA$43)/AB43,0) -> 0
A44: BARRES ANTI-VOLEURS | F44: =IF('SOMM. T.OFF'!F61=0,0,'SOMM. T.OFF'!F61) -> 0 | H44: =IF(F44=0,0,F44*DONNÉES!I28) -> 0 | I44: =IF(G44=0,0,G44*DONNÉES!$E$12) -> 0 | J44: 0 | K44: 0 | L44: MANUTENTION - NETTOYAGE | O44: =IF(N44=0,0,N44*DONNÉES!E44) -> 0 | P44: VOLETS COUPE-FEU (pi.lin.) | U44: =IF('SOMM. T.OFF'!F52=0,0,'SOMM. T.OFF'!F52) -> 0 | V44: =U44*DONNÉES!I23 -> 0 | X44: REVIT + INTÉGRATION | AB44: 31.25 | AC44: =IF(Y44="x",($Z$43+$AA$43)/AB44,0) -> 0
A45: CONDUITS FLEXIBLES ET SEMI RIGIDE | E45: =IF(INFOSPROJET!D31="","",INFOSPROJET!D31) | F45: ='ROND ET FLEX'!A10+'ROND ET FLEX'!Y7 -> 0 | H45: ='ROND ET FLEX'!B10+'ROND ET FLEX'!Y6 -> 0 | I45: =IF(G45=0,0,G45*DONNÉES!$E$12) -> 0 | J45: 0 | K45: 0 | L45: DÉMOLITION | O45: =IF(N45=0,0,N45*DONNÉES!E12) -> 0 | P45: P. ACCÈS DUCT | R45: P. NON-ISOLÉE | U45: 0 | V45: =U45*DONNÉES!I24 -> 0 | X45: REVIT + BIM + MAQUETTE (PILOTER) | AB45: 15.625 | AC45: =IF(Y45="x",($Z$43+$AA$43)/AB45,0) -> 0
A46: CONDUITS RONDS (chauffage) | F46: ='ROND ET FLEX'!A3 -> 0 | H46: ='ROND ET FLEX'!B3 -> 0 | I46: =IF(G46=0,0,G46*DONNÉES!$E$12) -> 0 | J46: 0 | K46: 0 | L46: SOUS-TOTAL | N46: =SUM(N41/2,N42/2,N43/2,N44,N45) -> 0 | O46: =SUM(O41:O45) -> 0 | R46: P. ISOLÉE | U46: 0 | V46: =U46*DONNÉES!I25 -> 0 | X46: CALCUL PIEDS | Z46: Pieds rectangle | AA46: Pied rond | AB46: Pied/heure
A47: CONDUIT SCELLÉ (LEED)(4,60$ au 56po) | E47: =IF(INFOSPROJET!D23="","X",INFOSPROJET!D23) -> X | H47: =N13*12/56*4.6 -> 0 | I47: =IF(G47=0,0,G47*DONNÉES!$E$12) -> 0 | J47: 0 | K47: 0 | R47: G. NON-ISOLÉE (RARE) | U47: 0 | V47: =U47*DONNÉES!I26 -> 0 | X47: REVIT / STANDARD | Z47: =N13 -> 0 | AA47: =SUM(S18:S21)+F46 -> 0 | AB47: 40 | AC47: =IF(Y47="x",($Z$43+$AA$43)/AB47,0) -> 0
A48: TRAV. HORS NORM. (SOIR)(25%)(NUIT:100%) | H48: 0 | I48: =IF(E48=0,0,IF(E48="SOIR",SUM(G55,G81,U13,U23,N46)*DONNÉES!$E$12*0.25,SUM(G55,G81,U13,U23,N46)*DONNÉES!$E$12*1)) -> 0 | J48: 0 | K48: 0 | L48: DIVERS & ORGANISATION CHANTIER | R48: G. ISOLÉE (RARE) | U48: 0 | V48: =U48*DONNÉES!I27 -> 0 | X48: REVIT + INTÉGRATION | AB48: 20 | AC48: =IF(Y48="x",($Z$43+$AA$43)/AB48,0) -> 0
A49: MANCHONS TRAVERSÉ DE MUR ÉTANCHE | E49: =IF(INFOSPROJET!D43="","",INFOSPROJET!D43) | F49: =IF(E49="","0","?") -> 0 | H49: =F49*60 -> 0 | I49: =IF(G49=0,0,G49*DONNÉES!$E$12) -> 0 | J49: 0 | K49: 0 | L49: MISE EN MARCHE VENTILATEURS (QTÉ) | O49: =IF(N49=0,0,N49*DONNÉES!E39) -> 0 | P49: MATÉRIEL D'ÉTANCHÉITÉ | V49: 0 | X49: REVIT + BIM + MAQUETTE (PILOTER) | AB49: 10 | AC49: =IF(Y49="x",($Z$43+$AA$43)/AB49,0) -> 0
H50: =IF(F50=0,0,"") -> 0 | I50: =IF(G50=0,0,G50*DONNÉES!$E$12) -> 0 | J50: =IF(E50=0,0,"") -> 0 | K50: =IF(E50=0,0,"") -> 0 | L50: GARANTIE | O50: =IF(N50=0,0,N50*DONNÉES!E40) -> 0 | V50: 0 | X50: Nombre de X(pour calcul) | Y50: =IF(Y43="",0,1)+IF(Y44="",0,1)+IF(Y45="",0,1)+IF(Y47="",0,1)+IF(Y48="",0,1)+IF(Y49="",0,1) -> 1 | AB50: Moyenne reportée | AC50: =(AC43+AC44+AC45+AC48+AC47+AC49)/Y50 -> 0
H51: =IF(F51=0,0,"") -> 0 | I51: =IF(G51=0,0,G51*DONNÉES!$E$12) -> 0 | J51: =IF(E51=0,0,"") -> 0 | K51: =IF(E51=0,0,"") -> 0 | L51: TRANSPORT MATÉRIEL | O51: 0 | V51: 0
H52: =IF(F52=0,0,"") -> 0 | I52: =IF(G52=0,0,G52*DONNÉES!$E$12) -> 0 | J52: =IF(E52=0,0,"") -> 0 | K52: =IF(E52=0,0,"") -> 0 | L52: VOYAG. & PENSION DE MTL KM | O52: =IF(N52>65,IF(N52>90,IF(N52>119,$Q$74*2/8*DONNÉES!B53,$Q$74*2/8*DONNÉES!B52),$Q$74*2/8*DONNÉES!B51),0) -> 0 | S52: SOUS-TOTAL | V52: =SUM(V33:V51) -> 0
H53: =IF(F53=0,0,"") -> 0 | I53: =IF(G53=0,0,G53*DONNÉES!$E$12) -> 0 | J53: =IF(E53=0,0,"") -> 0 | K53: =IF(E53=0,0,"") -> 0 | L53: DIRECTEUR DE PROJET | N53: =(Z43+AA43)/62.5*0.2 -> 0 | O53: =IF(N53=0,0,N53*DONNÉES!E45) -> 0 | X53: * Calcul basé sur 8po (rond, spiral) 3.4lbs/pied
H54: =IF(F54=0,0,"") -> 0 | I54: =IF(G54=0,0,G54*DONNÉES!$E$12) -> 0 | J54: =IF(E54=0,0,"") -> 0 | K54: =IF(E54=0,0,"") -> 0 | L54: DESSINS - FAB. | N54: =AC50 -> 0 | O54: =IF(N54=0,0,N54*DONNÉES!E45) -> 0 | P54: ACCESSOIRES - DIVERS
B55: SOUS-TOTAL | G55: =SUM(G10:G54) -> 0 | H55: =IF(COUNTBLANK(H10:H54)=0,SUM(H10:H44,H47:H54),"???") -> 0 | I55: =IF(COUNTBLANK(I10:I54)=0,SUM(I10:I54),"???") -> 0 | J55: =IF(COUNTBLANK($J$10:$J$54)=0,SUM($J$10:$J$54),"???") -> 0 | K55: =IF(COUNTBLANK($K$10:$K$54)=0,SUM($K$10:$K$54),"???") -> 0 | L55: CONTREMAÎTRE AU CHANTIER | O55: =(Z43+AA43)/62.5*0.2*DONNÉES!E45 -> 0 | P55: PLAQUES D'IDENTIFICATION | V55: 0
L56: STATIONNEMENT | M56: REQUIS (X) | O56: =IF(N56=0,0,Q74/8*25) -> 0 | V56: 0 | X56: Calcul Contrôle VJR
A57: SOUS-CONTRATS | L57: MANUELS ENTRETIEN & TEL QUE CONSTRUIT | O57: 0 | V57: 0
A58: DESCRIPTION | E58: DEVIS | G58: HRES | H58: ACCESSOIRES | I58: COÛT INSTAL. | J58: COÛT ESTIMÉ | K58: COÛT RÉEL | L58: ROULOTTE | O58: 0 | V58: 0
A59: CONTRÔLE FOURNITURE | E59: =IF(INFOSPROJET!D10="","",INFOSPROJET!D10) | H59: 0 | I59: =IF(G59=0,0,G59*DONNÉES!$E$12) -> 0 | J59: =IF(E59="",0,IF(INFOSPROJET!G10="X","GÉNÉRAL","")) -> 0 | K59: =IF(E59="",0,IF(INFOSPROJET!G10="X","GÉNÉRAL","")) -> 0 | L59: LOCATION D'ÉQUIPEMENTS | O59: 0 | V59: 0 | X59: Équipement | Y59: Qté | Z59: Prix | AA59: Total
A60: CONTRÔLE INSTALLATION | H60: 0 | I60: =IF(G60=0,0,G60*DONNÉES!$E$12) -> 0 | J60: =IF(E59="",0,IF(INFOSPROJET!G10="X","GÉNÉRAL","")) -> 0 | K60: =IF(E59="",0,IF(INFOSPROJET!G10="X","GÉNÉRAL","")) -> 0 | L60: CONTENEUR | O60: 0 | V60: 0 | X60: ÉCHANGEUR D'AIR | Z60: 100 | AA60: =Z60*Y60 -> 0
A61: CONTRÔLE DE LOGEMENT PAR VJR (voir calul ci-à-droite) | E61: =IF(AA70=0,"","X") | H61: 0 | I61: =IF(G61=0,0,G61*DONNÉES!$E$12) -> 0 | J61: =IF(E61="",0,"") -> 0 | K61: =IF(E61="",0,"") -> 0 | L61: PERMIS | O61: 0 | V61: 0 | X61: MINUTERIE | Z61: 50 | AA61: =Z61*Y61 -> 0
A62: ISOLATION THERMIQUE | E62: =IF(INFOSPROJET!D11="","",INFOSPROJET!D11) | H62: 0 | I62: =IF(G62=0,0,G62*DONNÉES!$E$12) -> 0 | J62: =IF(E62="",0,IF(INFOSPROJET!G11="X","GÉNÉRAL","")) -> 0 | K62: =IF(E62="",0,IF(INFOSPROJET!G11="X","GÉNÉRAL","")) -> 0 | M62: SOUS-TOTAL | O62: =SUM(O49:O61) -> 0 | S62: SOUS-TOTAL | V62: =SUM(V55:V61) -> 0 | X62: HUMIDISTAT | Z62: 50 | AA62: =Z62*Y62 -> 0
A63: BALANCEMENT | E63: =IF(INFOSPROJET!D12="","",INFOSPROJET!D12) | H63: 0 | I63: =IF(G63=0,0,G63*DONNÉES!$E$12) -> 0 | J63: =IF(E63="",0,IF(INFOSPROJET!G12="X","GÉNÉRAL","")) -> 0 | K63: =IF(E63="",0,IF(INFOSPROJET!G12="X","GÉNÉRAL","")) -> 0 | X63: RELAIS (PLINTHE/CHAUFF) | Z63: 50 | AA63: =Z63*Y63 -> 0
A64: LECTURES PRÉLIMINAIRES | H64: 0 | I64: =IF(G64=0,0,G64*DONNÉES!$E$12) -> 0 | J64: =IF(E63="",0,IF(INFOSPROJET!G12="X","GÉNÉRAL","")) -> 0 | K64: =IF(E63="",0,IF(INFOSPROJET!G12="X","GÉNÉRAL","")) -> 0 | AA64: =Z64*Y64 -> 0
A65: GRUE | H65: 0 | I65: =IF(G65=0,0,G65*DONNÉES!$E$12) -> 0 | J65: =IF(E65="",0,"") -> 0 | K65: =IF(E65="",0,"") -> 0 | AA65: =Z65*Y65 -> 0
A66: RÉFRIGÉRATION | E66: =IF(INFOSPROJET!D16="","",INFOSPROJET!D16) | H66: 0 | I66: =IF(G66=0,0,G66*DONNÉES!$E$12) -> 0 | J66: =IF(E66="",0,"") -> 0 | K66: =IF(E66="",0,"") -> 0 | L66: BILAN DE LA SOUMISSION | AA66: =Z66*Y66 -> 0
A67: ARMAFLEX | E67: =IF(INFOSPROJET!D17="","",INFOSPROJET!D17) | H67: 0 | I67: =IF(G67=0,0,G67*DONNÉES!$E$12) -> 0 | J67: =IF(E67="",0,"") -> 0 | K67: =IF(E67="",0,"") -> 0 | L67: NOTES | O67: DESCRIPTION | R67: COÛT ESTIMÉ | U67: COÛT RÉEL | AA67: =Z67*Y67 -> 0
A68: RECOUVREMENT DE REF. | E68: =IF(INFOSPROJET!D17="","",INFOSPROJET!D17) | H68: 0 | I68: =IF(G68=0,0,G68*DONNÉES!$E$12) -> 0 | J68: =IF(E68="",0,"") -> 0 | K68: =IF(E68="",0,"") -> 0 | O68: ÉQUIPEMENTS | R68: =IF(COUNTBLANK(J10:J54)=0,SUM(J10:J54),"???") -> 0 | U68: =IF(COUNTBLANK(K10:K54)=0,SUM(K10:K54),"???") -> 0 | AA68: =Z68*Y68 -> 0
A69: MISE EN MARCHE PAR CLL (VENTILATEURS VOIR DIVERS) | E69: =IF(INFOSPROJET!D15="","",INFOSPROJET!D15) | H69: 0 | I69: =IF(G69=0,0,G69*DONNÉES!$E$12) -> 0 | J69: =IF(E69="",0,"") -> 0 | K69: =IF(E69="",0,"") -> 0 | O69: SOUS-CONTRATS | R69: =IF(COUNTBLANK(J59:J80)=0,SUM(J59:J80),"???") -> 750 | U69: =IF(COUNTBLANK(K59:K80)=0,SUM(K59:K80),"???") -> 750 | AA69: =Z69*Y69 -> 0
A70: ESSAIS & TESTS | E70: =IF(INFOSPROJET!D14="","",INFOSPROJET!D14) | H70: 0 | I70: =IF(G70=0,0,G70*DONNÉES!$E$12) -> 0 | J70: =IF(E70="",0,"") -> 0 | K70: =IF(E70="",0,"") -> 0 | O70: CONDUITS + ACC. & ISOL. ACOUS. | R70: =SUM(O13,O37,V52) -> 0 | U70: =SUM(O13,O37,V52) -> 0 | Y70: GRAND TOTAL | AA70: =SUM(AA60:AA69) -> 0
A71: OUVERTURES | E71: =IF(INFOSPROJET!D63="","",INFOSPROJET!D63) | H71: 0 | I71: =IF(G71=0,0,G71*DONNÉES!$E$12) -> 0 | J71: =IF(E71="",0,"") -> 0 | K71: =IF(E71="",0,"") -> 0 | O71: CONDUITS SPIRALS | R71: =IF(P23=0,0,P23) -> 0 | U71: =IF(P23=0,0,P23) -> 0
A72: NETTOYAGE CONDUITS | E72: =IF(INFOSPROJET!D13="","",INFOSPROJET!D13) | H72: 0 | I72: =IF(G72=0,0,G72*DONNÉES!$E$12) -> 0 | J72: =IF(E72="",0,"") -> 0 | K72: =IF(E72="",0,"") -> 0 | O72: TUYAU CHAUF. & CONDUITS FLEX. | R72: =SUM(H45,H46) -> 0 | U72: =SUM(H45,H46) -> 0
A73: ANALYSE VIBRATION | H73: 0 | I73: =IF(G73=0,0,G73*DONNÉES!$E$12) -> 0 | J73: =IF(E73="",0,"") -> 0 | K73: =IF(E73="",0,"") -> 0 | O73: ACCESSOIRES DIVERS & SUSPENSION | R73: =IF(OR(H55="???",H81="???",Q13="???",O22="???",Q22="???",V62="???"),"???",SUM(H55,H81,Q13,O22,Q22,V62)) -> 0 | U73: =IF(OR(H55="???",H81="???",Q13="???",O22="???",Q22="???",V62="???"),"???",SUM(H55,H81,Q13,O22,Q22,V62)) -> 0
A74: PARASISMIQUE (voir calul ci-à-droite) | E74: =IF(INFOSPROJET!D18="","X",INFOSPROJET!D18) -> X | H74: 0 | I74: =IF(G74=0,0,G74*DONNÉES!$E$12) -> 0 | J74: =AA37 -> 750 | K74: =J74 -> 750 | O74: INSTALLATION (Hx2ho) | Q74: =SUM(G55,G81,U13,U23,N46) -> 0 | R74: =SUM(I55,I81,V13,V23,O46) -> 0 | U74: =SUM(I55,I81,V13,V23,O46) -> 0
A75: CHEMINÉE | H75: 0 | I75: =IF(G75=0,0,G75*DONNÉES!$E$12) -> 0 | J75: =IF(E75=0,0,"") -> 0 | K75: =IF(E75=0,0,"") -> 0 | O75: DIVERS & ORGANISATION CHANTIER | R75: =SUM(O49:O61) -> 0 | U75: =SUM(O49:O61) -> 0 | X75: CALCUL PROFIT ST VS RESTE
A76: STRUCTURE | H76: 0 | I76: =IF(G76=0,0,G76*DONNÉES!$E$12) -> 0 | J76: =IF(E76=0,0,"") -> 0 | K76: =IF(E76=0,0,"") -> 0 | L76: PRIX DE LA SOUMISSION | N76: REQUIS | O76: SOUS-TOTAL "A" | R76: =IF(COUNT(R68:T75)=8,SUM(R68:T75),"???") -> 750 | U76: =IF(COUNT(U68:V75)=8,SUM(U68:V75),"???") -> 750 | X76: COST SOUS-TRAITANTS | AA76: MARGE ST
A77: PLOMBERIE | H77: 0 | I77: =IF(G77=0,0,G77*DONNÉES!$E$12) -> 0 | J77: =IF(E77=0,0,"") -> 0 | K77: =IF(E77=0,0,"") -> 0 | L77: 0 | O77: BSDQ | R77: =IF(N77="",0,IF((R76*1.1)<100000,R76*1.1*(3/8*0.01),(((R76*1.1)-99000)*0.001*1.1)+375)) -> 0 | U77: =IF(N77="",0,IF((U76*1.1)<100000,U76*1.1*3/8*0.01,(((U76*1.1)-99000)*0.001*1.1)+375)) -> 0 | X77: SOUS-TRAITANTS AVEC PROFIT | Z77: =Z76/AA77 -> 0 | AA77: 0.68
A78: GAZ NATUREL | H78: 0 | I78: =IF(G78=0,0,G78*DONNÉES!$E$12) -> 0 | J78: =IF(E78=0,0,"") -> 0 | K78: =IF(E78=0,0,"") -> 0 | O78: CAUTIONNEMENT SOUMISSION | R78: =IF(N78="",0,IF((R76+R77)<180000,200,((R76/1000)))) -> 0 | U78: =IF(N78="",0,IF((U76+U77)<180000,200,((U76/1000)))) -> 0 | X78: RESTANT DU COUTANT | Z78: =U80-Z76 -> 750 | AA78: MARGE RESTANT
A79: ÉLECTRICITÉ | H79: 0 | I79: =IF(G79=0,0,G79*DONNÉES!$E$12) -> 0 | J79: =IF(E79=0,0,"") -> 0 | K79: =IF(E79=0,0,"") -> 0 | L79: =PRODUCT(L77,5%) -> 0 | M79: <---TPS | O79: CAUTIONNEMENT EXÉCUTION | R79: =IF(N79="",0,IF((R76+R77+R78)<32000,300,(R76*8.5/1000))) -> 0 | U79: =IF(N79="",0,IF((U76+U77+U78)<32000,300,(U76*8.5/1000))) -> 0 | X79: RESTANT AVEC PROFIT | Z79: =Z78/AA79 -> 961.53846 | AA79: 0.78
A80: TOITURE | H80: 0 | I80: =IF(G80=0,0,G80*DONNÉES!$E$12) -> 0 | J80: =IF(E80=0,0,"") -> 0 | K80: =IF(E80=0,0,"") -> 0 | L80: =PRODUCT(L77,9.975%) -> 0 | M80: <---TVQ | O80: SOUS-TOTAL "B" | R80: =IF(COUNT(R76:T79)=4,SUM(R76:T79),"???") -> 750 | U80: =IF(COUNT(U76:V79)=4,SUM(U76:V79),"???") -> 750 | X80: TOTAL | Z80: =Z79+Z77 -> 961.53846
B81: SOUS-TOTAL | G81: =SUM(G59:G80) -> 0 | H81: =IF(COUNTBLANK(H59:H80)=0,SUM(H59:H80),"???") -> 0 | I81: =IF(COUNTBLANK(I59:I80)=0,SUM(I59:I80),"???") -> 0 | J81: =IF(COUNTBLANK($J$59:$J$80)=0,SUM($J$59:$J$80),"???") -> 750 | K81: =IF(COUNTBLANK($K$59:$K$80)=0,SUM($K$59:$K$80),"???") -> 750 | L81: =SUM(L77:L80) -> 0 | M81: <-TOTAL | O81: ADMIN. - PROFIT % | R81: =+R82-R80 -> -750 | U81: =+U82-U80 -> -750 | X81: CALCUL DU PROFIT SUR TOTAL | Z81: =U80/Z80 -> 0.78
N82: TOTAL | R82: =IF(N81="",0,(R80/Q81)) -> 0 | U82: =IF(N81="",0,U80/Q81) -> 0

Sheet TAKE OFF
A1: PROJET : | C1: =IF(ESTIMÉ!B1="","",ESTIMÉ!B1) | L1: SYSTÈME :
A3: CODES - ACCESOIRES | L3: CALIBRE DE TÔLE
A4: 1/2" ACOUSTIQUE | C4: 1 | D4: V. MAN. TUYAUX CHAUFFAGE | I4: 9 | L4: METRIQUE | N4: M | O4: ANGLAIS
A5: 1" ACOUST. FLEX. | C5: 2 | D5: VCF - MANCHONS - UNITAIRE | I5: 10 | L5: 0 | M5: 305 | N5: 26 | O5: 0 | P5: 12
A6: 1" ACOUST. RIG. | C6: 21 | D6: VCF - COUPE-FUMÉE | I6: 100 | L6: 310 | M6: 750 | N6: 24 | O6: 13 | P6: 30
A7: 2" ACOUSTIQUE | C7: 3 | D7: V. MOTORISÉ | I7: 11 | L7: 755 | M7: 1500 | N7: 22 | O7: 31 | P7: 59
A8: 1" THERMIQUE | C8: 4 | D8: V. MOTORISÉ ISOLÉ | I8: 111 | L8: 1505 | M8: 2100 | N8: 20 | O8: 60 | P8: 82
A9: 2" THERMIQUE | C9: 5 | D9: V. GRAVITÉ | I9: 12 | L9: 2105 | M9: &plus | N9: 18 | O9: 83 | P9: &plus
A10: ACIER 16 GA | C10: 6 | D10: V. MANUEL 30" ET - UNITAIRE | I10: 13 | L10: TYPE & INSTALLATION
A11: ALUMINIUM | C11: 61 | D11: V. MANUEL CADRE 31" ET + | I11: 131 | L11: B. PRESSION | M11: BP | N11: SALLE MÉC | P11: SM
A12: T. VANES SIMPLE | C12: 7 | D12: GRILLAGE 30" ET - | I12: 14 | L12: M. PRESSION | M12: MP | N12: 30" ET - | P12: HA
A13: T. VANES DOUBLE | C13: 71 | D13: GRILLAGE CADRE 31" ET + | I13: 141 | L13: H. PRESSION | M13: HP | N13: RISER | P13: RI
A14: CANEVAS 3"-3"-3" | C14: 8 | D14: STO C/A SPLIT UNITAIRE | I14: 15 | L14: 16 GA (noir) | M14: N | N14: 16GA/SS | P14: 16
A15: CANEVAS 3"-6"-3" | C15: 81 | D15: BARRES ANTI-VOL. | I15: 16 | L15: ALUMINIUM | M15: AL | N15: ALUMINIUM | P15: AL
L16: INOX | M16: SS | N16: 31" ET + | P16: RE
A18: LARG. | B18: HAUT. | C18: LONG. | D18: MÉTAL | K18: GA | L18: TÔLE | M18: ISOL. ACOUSTIQUE | O18: ISOL. THERMIQUE | Q18: DIM. AGRAN. | R18: T. VANES SIMPLE | T18: T. VANES DOUBLE | V18: CANEVAS 3-3-3 | X18: CANEVAS 3-6-3 | Z18: SPLITTERS | AA18: VCF-MANCHONS | AC18: VCFF | AE18: V. MOTORISÉ | AG18: V. MOT. ISOLÉ | AI18: V. GRAVITÉ | AK18: V. MAN. SIMPLE | AL18: V. MANUEL CADRE | AN18: GRILLAGE | AP18: GRILLAGE CADRE | AR18: BOTTINES | AS18: BARRES ANTI-VOLEUR | AU18: ALUMINIUM | AW18: TÔLE
D19: CODE | E19: TYPE | F19: INST | G19: ACCESSOIRES | L19: LBS | M19: ÉPAIS. | N19: PI.CAR. | O19: ÉPAIS. | P19: PI.CAR. | Q19: ISOLANT | R19: QTÉ | S19: PI. CAR. | T19: QTÉ | U19: PI. CAR. | V19: QTÉ | W19: PI. LIN. | X19: QTÉ | Y19: PI. LIN. | Z19: QTÉ | AA19: QTÉ | AB19: PI. LIN. | AC19: QTÉ | AD19: PI. LIN. | AE19: QTÉ | AF19: PI. CAR. | AG19: QTÉ | AH19: PI. CAR. | AI19: QTÉ | AJ19: PI. CAR. | AK19: QTÉ | AL19: QTÉ | AM19: PI. CAR. | AN19: QTÉ | AO19: PI. CAR. | AP19: QTÉ | AQ19: PI. CAR. | AR19: QTÉ | AS19: QTÉ | AT19: PI. CAR. | AU19: PI | AV19: LBS | AW19: PI | AX19: LBS
A20: 200 | B20: 200 | C20: 2 | F20: HA | G20: 21 | H20: 21 | I20: 21 | J20: 10 | K20: =IF($N$4="M",IF(A20="","",IF(D20=6,16,IF(A20<=$M$5,26,IF(A20<=$M$6,24,IF(A20<=$M$7,22,IF(A20<=$M$8,20,18)))))),IF(A20="","",IF(D20=6,16,IF(A20<=$P$5,26,IF(A20<=$P$6,24,IF(A20<=$P$7,22,IF(A20<=$P$8,20,18))))))) | L20: =IF($N$4="M",IF(A20="","",IF(K20=26,(A20+B20+Q20)*C20*0.02739,IF(K20=24,(A20+B20+Q20)*C20*0.02739,IF(K20=22,(A20+B20+Q20)*C20*0.0333,IF(K20=20,(A20+B20+Q20)*C20*0.0393,IF(K20=18,(A20+B20+Q20)*C20*0.0511,IF(K20=16,(A20+B20+Q20)*C20*0.0628))))))),IF(A20="","",IF(K20=26,(A20+B20+Q20)*C20*0.211,IF(K20=24,(A20+B20+Q20)*C20*0.211,IF(K20=22,(A20+B20+Q20)*C20*0.258,IF(K20=20,(A20+B20+Q20)*C20*0.304,IF(K20=18,(A20+B20+Q20)*C20*0.395,IF(K20=16,(A20+B20+Q20)*C20*0.487)))))))) | M20: =IF(D20=1,0.5,IF(D20=2,"1 F",IF(D20=21,"1 R",IF(D20=3,2,"")))) | N20: =IF(M20="","",IF($N$4="M",(A20+B20+Q20)*C20*0.022,(A20+B20+Q20)*C20*0.17)) | O20: =IF(D20=4,1,IF(D20=5,2,"")) | P20: =IF(O20="","",IF($N$4="M",IF(O20=1,(A20+B20+Q20)*C20*0.022*1.1,(A20+B20+Q20)*C20*0.022*1.15),IF(O20=1,(A20+B20+Q20)*C20*0.17*1.1,(A20+B20+Q20)*C20*0.17*1.15))) | Q20: =IF($N$4="M",IF(A20="","",IF(D20=1,50,IF(D20=2,100,IF(D20=21,100,IF(D20=3,200,0))))),IF(A20="","",IF(D20=1,2,IF(D20=2,4,IF(D20=21,4,IF(D20=3,8,0)))))) | R20: =COUNTIF(G20:J20,7) -> 0 | S20: =IF(A20="","",IF($N$4="M",A20*B20*0.000011111*R20*1.5,A20*B20/144*R20*1.5)) | T20: =COUNTIF(G20:J20,71) -> 0 | U20: =IF(A20="","",IF($N$4="M",A20*B20*0.000011111*T20*1.5,A20*B20/144*T20*1.5)) | V20: =COUNTIF(G20:J20,8) -> 0 | W20: =IF(A20="","",IF($N$4="M",(A20+B20)*2*0.0032808*V20,(A20+B20)*2*V20/12)) | X20: =COUNTIF(G20:J20,81) -> 0 | Y20: =IF(A20="","",IF($N$4="M",(A20+B20)*2*0.0032808*X20,(A20+B20)*2*X20/12)) | Z20: =COUNTIF(G20:J20,9) -> 0 | AA20: =COUNTIF(G20:J20,10) -> 0 | AB20: =IF(A20="","",IF($N$4="M",(A20+B20)*2*0.0032808*AA20,(A20+B20)*2*AA20/12)) | AC20: =COUNTIF(G20:J20,100) -> 0 | AE20: =COUNTIF(G20:J20,11) -> 0 | AF20: =IF(A20="","",IF($N$4="M",A20*B20*0.000011111*AE20,A20*B20/144*AE20)) | AG20: =COUNTIF(G20:J20,111) -> 0 | AH20: =IF(A20="","",IF($N$4="M",A20*B20*0.000011111*AG20,A20*B20/144*AG20)) | AI20: =COUNTIF(G20:J20,12) -> 0 | AJ20: =IF(A20="","",IF($N$4="M",A20*B20*0.000011111*AI20,A20*B20/144*AI20)) | AK20: =COUNTIF(G20:J20,13) -> 0 | AL20: =COUNTIF(G20:J20,131) -> 0 | AM20: =IF(A20="","",IF($N$4="M",A20*B20*0.000011111*AL20,A20*B20/144*AL20)) | AN20: =COUNTIF(G20:J20,14) -> 0 | AO20: =IF(A20="","",IF($N$4="M",A20*B20*0.000011111*AN20,A20*B20/144*AN20)) | AP20: =COUNTIF(G20:J20,141) -> 0 | AQ20: =IF(A20="","",IF($N$4="M",A20*B20*0.000011111*AP20,A20*B20/144*AP20)) | AR20: =COUNTIF(G20:J20,15) -> 0 | AS20: =COUNTIF(G20:J20,16) -> 0 | AT20: =IF(A20="","",IF($N$4="M",A20*B20*0.000011111*AS20,A20*B20/144*AS20)) | AU20: =IF(D20=61,C20,0) -> 0 | AV20: =IF(D20=61,L20,0) -> 0 | AW20: =IF(A20="","",(C20-AU20)) | AX20: =IF(A20="","",(L20-AV20))
A21: 200 | B21: 200 | C21: 0 | F21: HA | G21: 10 | H21: 14 | I21: 14 | J21: 14 | K21: =IF($N$4="M",IF(A21="","",IF(D21=6,16,IF(A21<=$M$5,26,IF(A21<=$M$6,24,IF(A21<=$M$7,22,IF(A21<=$M$8,20,18)))))),IF(A21="","",IF(D21=6,16,IF(A21<=$P$5,26,IF(A21<=$P$6,24,IF(A21<=$P$7,22,IF(A21<=$P$8,20,18))))))) | L21: =IF($N$4="M",IF(A21="","",IF(K21=26,(A21+B21+Q21)*C21*0.02739,IF(K21=24,(A21+B21+Q21)*C21*0.02739,IF(K21=22,(A21+B21+Q21)*C21*0.0333,IF(K21=20,(A21+B21+Q21)*C21*0.0393,IF(K21=18,(A21+B21+Q21)*C21*0.0511,IF(K21=16,(A21+B21+Q21)*C21*0.0628))))))),IF(A21="","",IF(K21=26,(A21+B21+Q21)*C21*0.211,IF(K21=24,(A21+B21+Q21)*C21*0.211,IF(K21=22,(A21+B21+Q21)*C21*0.258,IF(K21=20,(A21+B21+Q21)*C21*0.304,IF(K21=18,(A21+B21+Q21)*C21*0.395,IF(K21=16,(A21+B21+Q21)*C21*0.487)))))))) | M21: =IF(D21=1,0.5,IF(D21=2,"1 F",IF(D21=21,"1 R",IF(D21=3,2,"")))) | N21: =IF(M21="","",IF($N$4="M",(A21+B21+Q21)*C21*0.022,(A21+B21+Q21)*C21*0.17)) | O21: =IF(D21=4,1,IF(D21=5,2,"")) | P21: =IF(O21="","",IF($N$4="M",IF(O21=1,(A21+B21+Q21)*C21*0.022*1.1,(A21+B21+Q21)*C21*0.022*1.15),IF(O21=1,(A21+B21+Q21)*C21*0.17*1.1,(A21+B21+Q21)*C21*0.17*1.15))) | Q21: =IF($N$4="M",IF(A21="","",IF(D21=1,50,IF(D21=2,100,IF(D21=21,100,IF(D21=3,200,0))))),IF(A21="","",IF(D21=1,2,IF(D21=2,4,IF(D21=21,4,IF(D21=3,8,0)))))) | R21: =COUNTIF(G21:J21,7) -> 0 | S21: =IF(A21="","",IF($N$4="M",A21*B21*0.000011111*R21*1.5,A21*B21/144*R21*1.5)) | T21: =COUNTIF(G21:J21,71) -> 0 | U21: =IF(A21="","",IF($N$4="M",A21*B21*0.000011111*T21*1.5,A21*B21/144*T21*1.5)) | V21: =COUNTIF(G21:J21,8) -> 0 | W21: =IF(A21="","",IF($N$4="M",(A21+B21)*2*0.0032808*V21,(A21+B21)*2*V21/12)) | X21: =COUNTIF(G21:J21,81) -> 0 | Y21: =IF(A21="","",IF($N$4="M",(A21+B21)*2*0.0032808*X21,(A21+B21)*2*X21/12)) | Z21: =COUNTIF(G21:J21,9) -> 0 | AA21: =COUNTIF(G21:J21,10) -> 0 | AB21: =IF(A21="","",IF($N$4="M",(A21+B21)*2*0.0032808*AA21,(A21+B21)*2*AA21/12)) | AC21: =COUNTIF(G21:J21,100) -> 0 | AE21: =COUNTIF(G21:J21,11) -> 0 | AF21: =IF(A21="","",IF($N$4="M",A21*B21*0.000011111*AE21,A21*B21/144*AE21)) | AG21: =COUNTIF(G21:J21,111) -> 0 | AH21: =IF(A21="","",IF($N$4="M",A21*B21*0.000011111*AG21,A21*B21/144*AG21)) | AI21: =COUNTIF(G21:J21,12) -> 0 | AJ21: =IF(A21="","",IF($N$4="M",A21*B21*0.000011111*AI21,A21*B21/144*AI21)) | AK21: =COUNTIF(G21:J21,13) -> 0 | AL21: =COUNTIF(G21:J21,131) -> 0 | AM21: =IF(A21="","",IF($N$4="M",A21*B21*0.000011111*AL21,A21*B21/144*AL21)) | AN21: =COUNTIF(G21:J21,14) -> 0 | AO21: =IF(A21="","",IF($N$4="M",A21*B21*0.000011111*AN21,A21*B21/144*AN21)) | AP21: =COUNTIF(G21:J21,141) -> 0 | AQ21: =IF(A21="","",IF($N$4="M",A21*B21*0.000011111*AP21,A21*B21/144*AP21)) | AR21: =COUNTIF(G21:J21,15) -> 0 | AS21: =COUNTIF(G21:J21,16) -> 0 | AT21: =IF(A21="","",IF($N$4="M",A21*B21*0.000011111*AS21,A21*B21/144*AS21)) | AU21: =IF(D21=61,C21,0) -> 0 | AV21: =IF(D21=61,L21,0) -> 0 | AW21: =IF(A21="","",(C21-AU21)) | AX21: =IF(A21="","",(L21-AV21))
A22: 200 | B22: 200 | C22: 0 | F22: HA | G22: 14 | K22: =IF($N$4="M",IF(A22="","",IF(D22=6,16,IF(A22<=$M$5,26,IF(A22<=$M$6,24,IF(A22<=$M$7,22,IF(A22<=$M$8,20,18)))))),IF(A22="","",IF(D22=6,16,IF(A22<=$P$5,26,IF(A22<=$P$6,24,IF(A22<=$P$7,22,IF(A22<=$P$8,20,18))))))) | L22: =IF($N$4="M",IF(A22="","",IF(K22=26,(A22+B22+Q22)*C22*0.02739,IF(K22=24,(A22+B22+Q22)*C22*0.02739,IF(K22=22,(A22+B22+Q22)*C22*0.0333,IF(K22=20,(A22+B22+Q22)*C22*0.0393,IF(K22=18,(A22+B22+Q22)*C22*0.0511,IF(K22=16,(A22+B22+Q22)*C22*0.0628))))))),IF(A22="","",IF(K22=26,(A22+B22+Q22)*C22*0.211,IF(K22=24,(A22+B22+Q22)*C22*0.211,IF(K22=22,(A22+B22+Q22)*C22*0.258,IF(K22=20,(A22+B22+Q22)*C22*0.304,IF(K22=18,(A22+B22+Q22)*C22*0.395,IF(K22=16,(A22+B22+Q22)*C22*0.487)))))))) | M22: =IF(D22=1,0.5,IF(D22=2,"1 F",IF(D22=21,"1 R",IF(D22=3,2,"")))) | N22: =IF(M22="","",IF($N$4="M",(A22+B22+Q22)*C22*0.022,(A22+B22+Q22)*C22*0.17)) | O22: =IF(D22=4,1,IF(D22=5,2,"")) | P22: =IF(O22="","",IF($N$4="M",IF(O22=1,(A22+B22+Q22)*C22*0.022*1.1,(A22+B22+Q22)*C22*0.022*1.15),IF(O22=1,(A22+B22+Q22)*C22*0.17*1.1,(A22+B22+Q22)*C22*0.17*1.15))) | Q22: =IF($N$4="M",IF(A22="","",IF(D22=1,50,IF(D22=2,100,IF(D22=21,100,IF(D22=3,200,0))))),IF(A22="","",IF(D22=1,2,IF(D22=2,4,IF(D22=21,4,IF(D22=3,8,0)))))) | R22: =COUNTIF(G22:J22,7) -> 0 | S22: =IF(A22="","",IF($N$4="M",A22*B22*0.000011111*R22*1.5,A22*B22/144*R22*1.5)) | T22: =COUNTIF(G22:J22,71) -> 0 | U22: =IF(A22="","",IF($N$4="M",A22*B22*0.000011111*T22*1.5,A22*B22/144*T22*1.5)) | V22: =COUNTIF(G22:J22,8) -> 0 | W22: =IF(A22="","",IF($N$4="M",(A22+B22)*2*0.0032808*V22,(A22+B22)*2*V22/12)) | X22: =COUNTIF(G22:J22,81) -> 0 | Y22: =IF(A22="","",IF($N$4="M",(A22+B22)*2*0.0032808*X22,(A22+B22)*2*X22/12)) | Z22: =COUNTIF(G22:J22,9) -> 0 | AA22: =COUNTIF(G22:J22,10) -> 0 | AB22: =IF(A22="","",IF($N$4="M",(A22+B22)*2*0.0032808*AA22,(A22+B22)*2*AA22/12)) | AC22: =COUNTIF(G22:J22,100) -> 0 | AE22: =COUNTIF(G22:J22,11) -> 0 | AF22: =IF(A22="","",IF($N$4="M",A22*B22*0.000011111*AE22,A22*B22/144*AE22)) | AG22: =COUNTIF(G22:J22,111) -> 0 | AH22: =IF(A22="","",IF($N$4="M",A22*B22*0.000011111*AG22,A22*B22/144*AG22)) | AI22: =COUNTIF(G22:J22,12) -> 0 | AJ22: =IF(A22="","",IF($N$4="M",A22*B22*0.000011111*AI22,A22*B22/144*AI22)) | AK22: =COUNTIF(G22:J22,13) -> 0 | AL22: =COUNTIF(G22:J22,131) -> 0 | AM22: =IF(A22="","",IF($N$4="M",A22*B22*0.000011111*AL22,A22*B22/144*AL22)) | AN22: =COUNTIF(G22:J22,14) -> 0 | AO22: =IF(A22="","",IF($N$4="M",A22*B22*0.000011111*AN22,A22*B22/144*AN22)) | AP22: =COUNTIF(G22:J22,141) -> 0 | AQ22: =IF(A22="","",IF($N$4="M",A22*B22*0.000011111*AP22,A22*B22/144*AP22)) | AR22: =COUNTIF(G22:J22,15) -> 0 | AS22: =COUNTIF(G22:J22,16) -> 0 | AT22: =IF(A22="","",IF($N$4="M",A22*B22*0.000011111*AS22,A22*B22/144*AS22)) | AU22: =IF(D22=61,C22,0) -> 0 | AV22: =IF(D22=61,L22,0) -> 0 | AW22: =IF(A22="","",(C22-AU22)) | AX22: =IF(A22="","",(L22-AV22))
A23: 250 | B23: 250 | C23: 13.1 | F23: HA | G23: 21 | H23: 21 | I23: 21 | J23: 21 | K23: =IF($N$4="M",IF(A23="","",IF(D23=6,16,IF(A23<=$M$5,26,IF(A23<=$M$6,24,IF(A23<=$M$7,22,IF(A23<=$M$8,20,18)))))),IF(A23="","",IF(D23=6,16,IF(A23<=$P$5,26,IF(A23<=$P$6,24,IF(A23<=$P$7,22,IF(A23<=$P$8,20,18))))))) | L23: =IF($N$4="M",IF(A23="","",IF(K23=26,(A23+B23+Q23)*C23*0.02739,IF(K23=24,(A23+B23+Q23)*C23*0.02739,IF(K23=22,(A23+B23+Q23)*C23*0.0333,IF(K23=20,(A23+B23+Q23)*C23*0.0393,IF(K23=18,(A23+B23+Q23)*C23*0.0511,IF(K23=16,(A23+B23+Q23)*C23*0.0628))))))),IF(A23="","",IF(K23=26,(A23+B23+Q23)*C23*0.211,IF(K23=24,(A23+B23+Q23)*C23*0.211,IF(K23=22,(A23+B23+Q23)*C23*0.258,IF(K23=20,(A23+B23+Q23)*C23*0.304,IF(K23=18,(A23+B23+Q23)*C23*0.395,IF(K23=16,(A23+B23+Q23)*C23*0.487)))))))) | M23: =IF(D23=1,0.5,IF(D23=2,"1 F",IF(D23=21,"1 R",IF(D23=3,2,"")))) | N23: =IF(M23="","",IF($N$4="M",(A23+B23+Q23)*C23*0.022,(A23+B23+Q23)*C23*0.17)) | O23: =IF(D23=4,1,IF(D23=5,2,"")) | P23: =IF(O23="","",IF($N$4="M",IF(O23=1,(A23+B23+Q23)*C23*0.022*1.1,(A23+B23+Q23)*C23*0.022*1.15),IF(O23=1,(A23+B23+Q23)*C23*0.17*1.1,(A23+B23+Q23)*C23*0.17*1.15))) | Q23: =IF($N$4="M",IF(A23="","",IF(D23=1,50,IF(D23=2,100,IF(D23=21,100,IF(D23=3,200,0))))),IF(A23="","",IF(D23=1,2,IF(D23=2,4,IF(D23=21,4,IF(D23=3,8,0)))))) | R23: =COUNTIF(G23:J23,7) -> 0 | S23: =IF(A23="","",IF($N$4="M",A23*B23*0.000011111*R23*1.5,A23*B23/144*R23*1.5)) | T23: =COUNTIF(G23:J23,71) -> 0 | U23: =IF(A23="","",IF($N$4="M",A23*B23*0.000011111*T23*1.5,A23*B23/144*T23*1.5)) | V23: =COUNTIF(G23:J23,8) -> 0 | W23: =IF(A23="","",IF($N$4="M",(A23+B23)*2*0.0032808*V23,(A23+B23)*2*V23/12)) | X23: =COUNTIF(G23:J23,81) -> 0 | Y23: =IF(A23="","",IF($N$4="M",(A23+B23)*2*0.0032808*X23,(A23+B23)*2*X23/12)) | Z23: =COUNTIF(G23:J23,9) -> 0 | AA23: =COUNTIF(G23:J23,10) -> 0 | AB23: =IF(A23="","",IF($N$4="M",(A23+B23)*2*0.0032808*AA23,(A23+B23)*2*AA23/12)) | AC23: =COUNTIF(G23:J23,100) -> 0 | AE23: =COUNTIF(G23:J23,11) -> 0 | AF23: =IF(A23="","",IF($N$4="M",A23*B23*0.000011111*AE23,A23*B23/144*AE23)) | AG23: =COUNTIF(G23:J23,111) -> 0 | AH23: =IF(A23="","",IF($N$4="M",A23*B23*0.000011111*AG23,A23*B23/144*AG23)) | AI23: =COUNTIF(G23:J23,12) -> 0 | AJ23: =IF(A23="","",IF($N$4="M",A23*B23*0.000011111*AI23,A23*B23/144*AI23)) | AK23: =COUNTIF(G23:J23,13) -> 0 | AL23: =COUNTIF(G23:J23,131) -> 0 | AM23: =IF(A23="","",IF($N$4="M",A23*B23*0.000011111*AL23,A23*B23/144*AL23)) | AN23: =COUNTIF(G23:J23,14) -> 0 | AO23: =IF(A23="","",IF($N$4="M",A23*B23*0.000011111*AN23,A23*B23/144*AN23)) | AP23: =COUNTIF(G23:J23,141) -> 0 | AQ23: =IF(A23="","",IF($N$4="M",A23*B23*0.000011111*AP23,A23*B23/144*AP23)) | AR23: =COUNTIF(G23:J23,15) -> 0 | AS23: =COUNTIF(G23:J23,16) -> 0 | AT23: =IF(A23="","",IF($N$4="M",A23*B23*0.000011111*AS23,A23*B23/144*AS23)) | AU23: =IF(D23=61,C23,0) -> 0 | AV23: =IF(D23=61,L23,0) -> 0 | AW23: =IF(A23="","",(C23-AU23)) | AX23: =IF(A23="","",(L23-AV23))
A24: 250 | B24: 250 | C24: 0 | F24: HA | G24: 21 | H24: 21 | I24: 100 | K24: =IF($N$4="M",IF(A24="","",IF(D24=6,16,IF(A24<=$M$5,26,IF(A24<=$M$6,24,IF(A24<=$M$7,22,IF(A24<=$M$8,20,18)))))),IF(A24="","",IF(D24=6,16,IF(A24<=$P$5,26,IF(A24<=$P$6,24,IF(A24<=$P$7,22,IF(A24<=$P$8,20,18))))))) | L24: =IF($N$4="M",IF(A24="","",IF(K24=26,(A24+B24+Q24)*C24*0.02739,IF(K24=24,(A24+B24+Q24)*C24*0.02739,IF(K24=22,(A24+B24+Q24)*C24*0.0333,IF(K24=20,(A24+B24+Q24)*C24*0.0393,IF(K24=18,(A24+B24+Q24)*C24*0.0511,IF(K24=16,(A24+B24+Q24)*C24*0.0628))))))),IF(A24="","",IF(K24=26,(A24+B24+Q24)*C24*0.211,IF(K24=24,(A24+B24+Q24)*C24*0.211,IF(K24=22,(A24+B24+Q24)*C24*0.258,IF(K24=20,(A24+B24+Q24)*C24*0.304,IF(K24=18,(A24+B24+Q24)*C24*0.395,IF(K24=16,(A24+B24+Q24)*C24*0.487)))))))) | M24: =IF(D24=1,0.5,IF(D24=2,"1 F",IF(D24=21,"1 R",IF(D24=3,2,"")))) | N24: =IF(M24="","",IF($N$4="M",(A24+B24+Q24)*C24*0.022,(A24+B24+Q24)*C24*0.17)) | O24: =IF(D24=4,1,IF(D24=5,2,"")) | P24: =IF(O24="","",IF($N$4="M",IF(O24=1,(A24+B24+Q24)*C24*0.022*1.1,(A24+B24+Q24)*C24*0.022*1.15),IF(O24=1,(A24+B24+Q24)*C24*0.17*1.1,(A24+B24+Q24)*C24*0.17*1.15))) | Q24: =IF($N$4="M",IF(A24="","",IF(D24=1,50,IF(D24=2,100,IF(D24=21,100,IF(D24=3,200,0))))),IF(A24="","",IF(D24=1,2,IF(D24=2,4,IF(D24=21,4,IF(D24=3,8,0)))))) | R24: =COUNTIF(G24:J24,7) -> 0 | S24: =IF(A24="","",IF($N$4="M",A24*B24*0.000011111*R24*1.5,A24*B24/144*R24*1.5)) | T24: =COUNTIF(G24:J24,71) -> 0 | U24: =IF(A24="","",IF($N$4="M",A24*B24*0.000011111*T24*1.5,A24*B24/144*T24*1.5)) | V24: =COUNTIF(G24:J24,8) -> 0 | W24: =IF(A24="","",IF($N$4="M",(A24+B24)*2*0.0032808*V24,(A24+B24)*2*V24/12)) | X24: =COUNTIF(G24:J24,81) -> 0 | Y24: =IF(A24="","",IF($N$4="M",(A24+B24)*2*0.0032808*X24,(A24+B24)*2*X24/12)) | Z24: =COUNTIF(G24:J24,9) -> 0 | AA24: =COUNTIF(G24:J24,10) -> 0 | AB24: =IF(A24="","",IF($N$4="M",(A24+B24)*2*0.0032808*AA24,(A24+B24)*2*AA24/12)) | AC24: =COUNTIF(G24:J24,100) -> 0 | AE24: =COUNTIF(G24:J24,11) -> 0 | AF24: =IF(A24="","",IF($N$4="M",A24*B24*0.000011111*AE24,A24*B24/144*AE24)) | AG24: =COUNTIF(G24:J24,111) -> 0 | AH24: =IF(A24="","",IF($N$4="M",A24*B24*0.000011111*AG24,A24*B24/144*AG24)) | AI24: =COUNTIF(G24:J24,12) -> 0 | AJ24: =IF(A24="","",IF($N$4="M",A24*B24*0.000011111*AI24,A24*B24/144*AI24)) | AK24: =COUNTIF(G24:J24,13) -> 0 | AL24: =COUNTIF(G24:J24,131) -> 0 | AM24: =IF(A24="","",IF($N$4="M",A24*B24*0.000011111*AL24,A24*B24/144*AL24)) | AN24: =COUNTIF(G24:J24,14) -> 0 | AO24: =IF(A24="","",IF($N$4="M",A24*B24*0.000011111*AN24,A24*B24/144*AN24)) | AP24: =COUNTIF(G24:J24,141) -> 0 | AQ24: =IF(A24="","",IF($N$4="M",A24*B24*0.000011111*AP24,A24*B24/144*AP24)) | AR24: =COUNTIF(G24:J24,15) -> 0 | AS24: =COUNTIF(G24:J24,16) -> 0 | AT24: =IF(A24="","",IF($N$4="M",A24*B24*0.000011111*AS24,A24*B24/144*AS24)) | AU24: =IF(D24=61,C24,0) -> 0 | AV24: =IF(D24=61,L24,0) -> 0 | AW24: =IF(A24="","",(C24-AU24)) | AX24: =IF(A24="","",(L24-AV24))
A25: 300 | B25: 300 | C25: 7 | F25: HA | G25: 21 | H25: 21 | I25: 21 | J25: 21 | K25: =IF($N$4="M",IF(A25="","",IF(D25=6,16,IF(A25<=$M$5,26,IF(A25<=$M$6,24,IF(A25<=$M$7,22,IF(A25<=$M$8,20,18)))))),IF(A25="","",IF(D25=6,16,IF(A25<=$P$5,26,IF(A25<=$P$6,24,IF(A25<=$P$7,22,IF(A25<=$P$8,20,18))))))) | L25: =IF($N$4="M",IF(A25="","",IF(K25=26,(A25+B25+Q25)*C25*0.02739,IF(K25=24,(A25+B25+Q25)*C25*0.02739,IF(K25=22,(A25+B25+Q25)*C25*0.0333,IF(K25=20,(A25+B25+Q25)*C25*0.0393,IF(K25=18,(A25+B25+Q25)*C25*0.0511,IF(K25=16,(A25+B25+Q25)*C25*0.0628))))))),IF(A25="","",IF(K25=26,(A25+B25+Q25)*C25*0.211,IF(K25=24,(A25+B25+Q25)*C25*0.211,IF(K25=22,(A25+B25+Q25)*C25*0.258,IF(K25=20,(A25+B25+Q25)*C25*0.304,IF(K25=18,(A25+B25+Q25)*C25*0.395,IF(K25=16,(A25+B25+Q25)*C25*0.487)))))))) | M25: =IF(D25=1,0.5,IF(D25=2,"1 F",IF(D25=21,"1 R",IF(D25=3,2,"")))) | N25: =IF(M25="","",IF($N$4="M",(A25+B25+Q25)*C25*0.022,(A25+B25+Q25)*C25*0.17)) | O25: =IF(D25=4,1,IF(D25=5,2,"")) | P25: =IF(O25="","",IF($N$4="M",IF(O25=1,(A25+B25+Q25)*C25*0.022*1.1,(A25+B25+Q25)*C25*0.022*1.15),IF(O25=1,(A25+B25+Q25)*C25*0.17*1.1,(A25+B25+Q25)*C25*0.17*1.15))) | Q25: =IF($N$4="M",IF(A25="","",IF(D25=1,50,IF(D25=2,100,IF(D25=21,100,IF(D25=3,200,0))))),IF(A25="","",IF(D25=1,2,IF(D25=2,4,IF(D25=21,4,IF(D25=3,8,0)))))) | R25: =COUNTIF(G25:J25,7) -> 0 | S25: =IF(A25="","",IF($N$4="M",A25*B25*0.000011111*R25*1.5,A25*B25/144*R25*1.5)) | T25: =COUNTIF(G25:J25,71) -> 0 | U25: =IF(A25="","",IF($N$4="M",A25*B25*0.000011111*T25*1.5,A25*B25/144*T25*1.5)) | V25: =COUNTIF(G25:J25,8) -> 0 | W25: =IF(A25="","",IF($N$4="M",(A25+B25)*2*0.0032808*V25,(A25+B25)*2*V25/12)) | X25: =COUNTIF(G25:J25,81) -> 0 | Y25: =IF(A25="","",IF($N$4="M",(A25+B25)*2*0.0032808*X25,(A25+B25)*2*X25/12)) | Z25: =COUNTIF(G25:J25,9) -> 0 | AA25: =COUNTIF(G25:J25,10) -> 0 | AB25: =IF(A25="","",IF($N$4="M",(A25+B25)*2*0.0032808*AA25,(A25+B25)*2*AA25/12)) | AC25: =COUNTIF(G25:J25,100) -> 0 | AE25: =COUNTIF(G25:J25,11) -> 0 | AF25: =IF(A25="","",IF($N$4="M",A25*B25*0.000011111*AE25,A25*B25/144*AE25)) | AG25: =COUNTIF(G25:J25,111) -> 0 | AH25: =IF(A25="","",IF($N$4="M",A25*B25*0.000011111*AG25,A25*B25/144*AG25)) | AI25: =COUNTIF(G25:J25,12) -> 0 | AJ25: =IF(A25="","",IF($N$4="M",A25*B25*0.000011111*AI25,A25*B25/144*AI25)) | AK25: =COUNTIF(G25:J25,13) -> 0 | AL25: =COUNTIF(G25:J25,131) -> 0 | AM25: =IF(A25="","",IF($N$4="M",A25*B25*0.000011111*AL25,A25*B25/144*AL25)) | AN25: =COUNTIF(G25:J25,14) -> 0 | AO25: =IF(A25="","",IF($N$4="M",A25*B25*0.000011111*AN25,A25*B25/144*AN25)) | AP25: =COUNTIF(G25:J25,141) -> 0 | AQ25: =IF(A25="","",IF($N$4="M",A25*B25*0.000011111*AP25,A25*B25/144*AP25)) | AR25: =COUNTIF(G25:J25,15) -> 0 | AS25: =COUNTIF(G25:J25,16) -> 0 | AT25: =IF(A25="","",IF($N$4="M",A25*B25*0.000011111*AS25,A25*B25/144*AS25)) | AU25: =IF(D25=61,C25,0) -> 0 | AV25: =IF(D25=61,L25,0) -> 0 | AW25: =IF(A25="","",(C25-AU25)) | AX25: =IF(A25="","",(L25-AV25))
A26: 1000 | B26: 400 | C26: 14.9 | F26: RE | K26: =IF($N$4="M",IF(A26="","",IF(D26=6,16,IF(A26<=$M$5,26,IF(A26<=$M$6,24,IF(A26<=$M$7,22,IF(A26<=$M$8,20,18)))))),IF(A26="","",IF(D26=6,16,IF(A26<=$P$5,26,IF(A26<=$P$6,24,IF(A26<=$P$7,22,IF(A26<=$P$8,20,18))))))) | L26: =IF($N$4="M",IF(A26="","",IF(K26=26,(A26+B26+Q26)*C26*0.02739,IF(K26=24,(A26+B26+Q26)*C26*0.02739,IF(K26=22,(A26+B26+Q26)*C26*0.0333,IF(K26=20,(A26+B26+Q26)*C26*0.0393,IF(K26=18,(A26+B26+Q26)*C26*0.0511,IF(K26=16,(A26+B26+Q26)*C26*0.0628))))))),IF(A26="","",IF(K26=26,(A26+B26+Q26)*C26*0.211,IF(K26=24,(A26+B26+Q26)*C26*0.211,IF(K26=22,(A26+B26+Q26)*C26*0.258,IF(K26=20,(A26+B26+Q26)*C26*0.304,IF(K26=18,(A26+B26+Q26)*C26*0.395,IF(K26=16,(A26+B26+Q26)*C26*0.487)))))))) | M26: =IF(D26=1,0.5,IF(D26=2,"1 F",IF(D26=21,"1 R",IF(D26=3,2,"")))) | N26: =IF(M26="","",IF($N$4="M",(A26+B26+Q26)*C26*0.022,(A26+B26+Q26)*C26*0.17)) | O26: =IF(D26=4,1,IF(D26=5,2,"")) | P26: =IF(O26="","",IF($N$4="M",IF(O26=1,(A26+B26+Q26)*C26*0.022*1.1,(A26+B26+Q26)*C26*0.022*1.15),IF(O26=1,(A26+B26+Q26)*C26*0.17*1.1,(A26+B26+Q26)*C26*0.17*1.15))) | Q26: =IF($N$4="M",IF(A26="","",IF(D26=1,50,IF(D26=2,100,IF(D26=21,100,IF(D26=3,200,0))))),IF(A26="","",IF(D26=1,2,IF(D26=2,4,IF(D26=21,4,IF(D26=3,8,0)))))) | R26: =COUNTIF(G26:J26,7) -> 0 | S26: =IF(A26="","",IF($N$4="M",A26*B26*0.000011111*R26*1.5,A26*B26/144*R26*1.5)) | T26: =COUNTIF(G26:J26,71) -> 0 | U26: =IF(A26="","",IF($N$4="M",A26*B26*0.000011111*T26*1.5,A26*B26/144*T26*1.5)) | V26: =COUNTIF(G26:J26,8) -> 0 | W26: =IF(A26="","",IF($N$4="M",(A26+B26)*2*0.0032808*V26,(A26+B26)*2*V26/12)) | X26: =COUNTIF(G26:J26,81) -> 0 | Y26: =IF(A26="","",IF($N$4="M",(A26+B26)*2*0.0032808*X26,(A26+B26)*2*X26/12)) | Z26: =COUNTIF(G26:J26,9) -> 0 | AA26: =COUNTIF(G26:J26,10) -> 0 | AB26: =IF(A26="","",IF($N$4="M",(A26+B26)*2*0.0032808*AA26,(A26+B26)*2*AA26/12)) | AC26: =COUNTIF(G26:J26,100) -> 0 | AE26: =COUNTIF(G26:J26,11) -> 0 | AF26: =IF(A26="","",IF($N$4="M",A26*B26*0.000011111*AE26,A26*B26/144*AE26)) | AG26: =COUNTIF(G26:J26,111) -> 0 | AH26: =IF(A26="","",IF($N$4="M",A26*B26*0.000011111*AG26,A26*B26/144*AG26)) | AI26: =COUNTIF(G26:J26,12) -> 0 | AJ26: =IF(A26="","",IF($N$4="M",A26*B26*0.000011111*AI26,A26*B26/144*AI26)) | AK26: =COUNTIF(G26:J26,13) -> 0 | AL26: =COUNTIF(G26:J26,131) -> 0 | AM26: =IF(A26="","",IF($N$4="M",A26*B26*0.000011111*AL26,A26*B26/144*AL26)) | AN26: =COUNTIF(G26:J26,14) -> 0 | AO26: =IF(A26="","",IF($N$4="M",A26*B26*0.000011111*AN26,A26*B26/144*AN26)) | AP26: =COUNTIF(G26:J26,141) -> 0 | AQ26: =IF(A26="","",IF($N$4="M",A26*B26*0.000011111*AP26,A26*B26/144*AP26)) | AR26: =COUNTIF(G26:J26,15) -> 0 | AS26: =COUNTIF(G26:J26,16) -> 0 | AT26: =IF(A26="","",IF($N$4="M",A26*B26*0.000011111*AS26,A26*B26/144*AS26)) | AU26: =IF(D26=61,C26,0) -> 0 | AV26: =IF(D26=61,L26,0) -> 0 | AW26: =IF(A26="","",(C26-AU26)) | AX26: =IF(A26="","",(L26-AV26))
A27: 1000 | B27: 500 | C27: 17.3 | F27: RE | K27: =IF($N$4="M",IF(A27="","",IF(D27=6,16,IF(A27<=$M$5,26,IF(A27<=$M$6,24,IF(A27<=$M$7,22,IF(A27<=$M$8,20,18)))))),IF(A27="","",IF(D27=6,16,IF(A27<=$P$5,26,IF(A27<=$P$6,24,IF(A27<=$P$7,22,IF(A27<=$P$8,20,18))))))) | L27: =IF($N$4="M",IF(A27="","",IF(K27=26,(A27+B27+Q27)*C27*0.02739,IF(K27=24,(A27+B27+Q27)*C27*0.02739,IF(K27=22,(A27+B27+Q27)*C27*0.0333,IF(K27=20,(A27+B27+Q27)*C27*0.0393,IF(K27=18,(A27+B27+Q27)*C27*0.0511,IF(K27=16,(A27+B27+Q27)*C27*0.0628))))))),IF(A27="","",IF(K27=26,(A27+B27+Q27)*C27*0.211,IF(K27=24,(A27+B27+Q27)*C27*0.211,IF(K27=22,(A27+B27+Q27)*C27*0.258,IF(K27=20,(A27+B27+Q27)*C27*0.304,IF(K27=18,(A27+B27+Q27)*C27*0.395,IF(K27=16,(A27+B27+Q27)*C27*0.487)))))))) | M27: =IF(D27=1,0.5,IF(D27=2,"1 F",IF(D27=21,"1 R",IF(D27=3,2,"")))) | N27: =IF(M27="","",IF($N$4="M",(A27+B27+Q27)*C27*0.022,(A27+B27+Q27)*C27*0.17)) | O27: =IF(D27=4,1,IF(D27=5,2,"")) | P27: =IF(O27="","",IF($N$4="M",IF(O27=1,(A27+B27+Q27)*C27*0.022*1.1,(A27+B27+Q27)*C27*0.022*1.15),IF(O27=1,(A27+B27+Q27)*C27*0.17*1.1,(A27+B27+Q27)*C27*0.17*1.15))) | Q27: =IF($N$4="M",IF(A27="","",IF(D27=1,50,IF(D27=2,100,IF(D27=21,100,IF(D27=3,200,0))))),IF(A27="","",IF(D27=1,2,IF(D27=2,4,IF(D27=21,4,IF(D27=3,8,0)))))) | R27: =COUNTIF(G27:J27,7) -> 0 | S27: =IF(A27="","",IF($N$4="M",A27*B27*0.000011111*R27*1.5,A27*B27/144*R27*1.5)) | T27: =COUNTIF(G27:J27,71) -> 0 | U27: =IF(A27="","",IF($N$4="M",A27*B27*0.000011111*T27*1.5,A27*B27/144*T27*1.5)) | V27: =COUNTIF(G27:J27,8) -> 0 | W27: =IF(A27="","",IF($N$4="M",(A27+B27)*2*0.0032808*V27,(A27+B27)*2*V27/12)) | X27: =COUNTIF(G27:J27,81) -> 0 | Y27: =IF(A27="","",IF($N$4="M",(A27+B27)*2*0.0032808*X27,(A27+B27)*2*X27/12)) | Z27: =COUNTIF(G27:J27,9) -> 0 | AA27: =COUNTIF(G27:J27,10) -> 0 | AB27: =IF(A27="","",IF($N$4="M",(A27+B27)*2*0.0032808*AA27,(A27+B27)*2*AA27/12)) | AC27: =COUNTIF(G27:J27,100) -> 0 | AE27: =COUNTIF(G27:J27,11) -> 0 | AF27: =IF(A27="","",IF($N$4="M",A27*B27*0.000011111*AE27,A27*B27/144*AE27)) | AG27: =COUNTIF(G27:J27,111) -> 0 | AH27: =IF(A27="","",IF($N$4="M",A27*B27*0.000011111*AG27,A27*B27/144*AG27)) | AI27: =COUNTIF(G27:J27,12) -> 0 | AJ27: =IF(A27="","",IF($N$4="M",A27*B27*0.000011111*AI27,A27*B27/144*AI27)) | AK27: =COUNTIF(G27:J27,13) -> 0 | AL27: =COUNTIF(G27:J27,131) -> 0 | AM27: =IF(A27="","",IF($N$4="M",A27*B27*0.000011111*AL27,A27*B27/144*AL27)) | AN27: =COUNTIF(G27:J27,14) -> 0 | AO27: =IF(A27="","",IF($N$4="M",A27*B27*0.000011111*AN27,A27*B27/144*AN27)) | AP27: =COUNTIF(G27:J27,141) -> 0 | AQ27: =IF(A27="","",IF($N$4="M",A27*B27*0.000011111*AP27,A27*B27/144*AP27)) | AR27: =COUNTIF(G27:J27,15) -> 0 | AS27: =COUNTIF(G27:J27,16) -> 0 | AT27: =IF(A27="","",IF($N$4="M",A27*B27*0.000011111*AS27,A27*B27/144*AS27)) | AU27: =IF(D27=61,C27,0) -> 0 | AV27: =IF(D27=61,L27,0) -> 0 | AW27: =IF(A27="","",(C27-AU27)) | AX27: =IF(A27="","",(L27-AV27))
A28: 1000 | B28: 500 | C28: 4.3 | D28: 6 | E28: HP | F28: RE | G28: 21 | K28: =IF($N$4="M",IF(A28="","",IF(D28=6,16,IF(A28<=$M$5,26,IF(A28<=$M$6,24,IF(A28<=$M$7,22,IF(A28<=$M$8,20,18)))))),IF(A28="","",IF(D28=6,16,IF(A28<=$P$5,26,IF(A28<=$P$6,24,IF(A28<=$P$7,22,IF(A28<=$P$8,20,18))))))) | L28: =IF($N$4="M",IF(A28="","",IF(K28=26,(A28+B28+Q28)*C28*0.02739,IF(K28=24,(A28+B28+Q28)*C28*0.02739,IF(K28=22,(A28+B28+Q28)*C28*0.0333,IF(K28=20,(A28+B28+Q28)*C28*0.0393,IF(K28=18,(A28+B28+Q28)*C28*0.0511,IF(K28=16,(A28+B28+Q28)*C28*0.0628))))))),IF(A28="","",IF(K28=26,(A28+B28+Q28)*C28*0.211,IF(K28=24,(A28+B28+Q28)*C28*0.211,IF(K28=22,(A28+B28+Q28)*C28*0.258,IF(K28=20,(A28+B28+Q28)*C28*0.304,IF(K28=18,(A28+B28+Q28)*C28*0.395,IF(K28=16,(A28+B28+Q28)*C28*0.487)))))))) | M28: =IF(D28=1,0.5,IF(D28=2,"1 F",IF(D28=21,"1 R",IF(D28=3,2,"")))) | N28: =IF(M28="","",IF($N$4="M",(A28+B28+Q28)*C28*0.022,(A28+B28+Q28)*C28*0.17)) | O28: =IF(D28=4,1,IF(D28=5,2,"")) | P28: =IF(O28="","",IF($N$4="M",IF(O28=1,(A28+B28+Q28)*C28*0.022*1.1,(A28+B28+Q28)*C28*0.022*1.15),IF(O28=1,(A28+B28+Q28)*C28*0.17*1.1,(A28+B28+Q28)*C28*0.17*1.15))) | Q28: =IF($N$4="M",IF(A28="","",IF(D28=1,50,IF(D28=2,100,IF(D28=21,100,IF(D28=3,200,0))))),IF(A28="","",IF(D28=1,2,IF(D28=2,4,IF(D28=21,4,IF(D28=3,8,0)))))) | R28: =COUNTIF(G28:J28,7) -> 0 | S28: =IF(A28="","",IF($N$4="M",A28*B28*0.000011111*R28*1.5,A28*B28/144*R28*1.5)) | T28: =COUNTIF(G28:J28,71) -> 0 | U28: =IF(A28="","",IF($N$4="M",A28*B28*0.000011111*T28*1.5,A28*B28/144*T28*1.5)) | V28: =COUNTIF(G28:J28,8) -> 0 | W28: =IF(A28="","",IF($N$4="M",(A28+B28)*2*0.0032808*V28,(A28+B28)*2*V28/12)) | X28: =COUNTIF(G28:J28,81) -> 0 | Y28: =IF(A28="","",IF($N$4="M",(A28+B28)*2*0.0032808*X28,(A28+B28)*2*X28/12)) | Z28: =COUNTIF(G28:J28,9) -> 0 | AA28: =COUNTIF(G28:J28,10) -> 0 | AB28: =IF(A28="","",IF($N$4="M",(A28+B28)*2*0.0032808*AA28,(A28+B28)*2*AA28/12)) | AC28: =COUNTIF(G28:J28,100) -> 0 | AE28: =COUNTIF(G28:J28,11) -> 0 | AF28: =IF(A28="","",IF($N$4="M",A28*B28*0.000011111*AE28,A28*B28/144*AE28)) | AG28: =COUNTIF(G28:J28,111) -> 0 | AH28: =IF(A28="","",IF($N$4="M",A28*B28*0.000011111*AG28,A28*B28/144*AG28)) | AI28: =COUNTIF(G28:J28,12) -> 0 | AJ28: =IF(A28="","",IF($N$4="M",A28*B28*0.000011111*AI28,A28*B28/144*AI28)) | AK28: =COUNTIF(G28:J28,13) -> 0 | AL28: =COUNTIF(G28:J28,131) -> 0 | AM28: =IF(A28="","",IF($N$4="M",A28*B28*0.000011111*AL28,A28*B28/144*AL28)) | AN28: =COUNTIF(G28:J28,14) -> 0 | AO28: =IF(A28="","",IF($N$4="M",A28*B28*0.000011111*AN28,A28*B28/144*AN28)) | AP28: =COUNTIF(G28:J28,141) -> 0 | AQ28: =IF(A28="","",IF($N$4="M",A28*B28*0.000011111*AP28,A28*B28/144*AP28)) | AR28: =COUNTIF(G28:J28,15) -> 0 | AS28: =COUNTIF(G28:J28,16) -> 0 | AT28: =IF(A28="","",IF($N$4="M",A28*B28*0.000011111*AS28,A28*B28/144*AS28)) | AU28: =IF(D28=61,C28,0) -> 0 | AV28: =IF(D28=61,L28,0) -> 0 | AW28: =IF(A28="","",(C28-AU28)) | AX28: =IF(A28="","",(L28-AV28))
A29: 1000 | B29: 600 | C29: 6.8 | D29: 6 | E29: HP | F29: RE | K29: =IF($N$4="M",IF(A29="","",IF(D29=6,16,IF(A29<=$M$5,26,IF(A29<=$M$6,24,IF(A29<=$M$7,22,IF(A29<=$M$8,20,18)))))),IF(A29="","",IF(D29=6,16,IF(A29<=$P$5,26,IF(A29<=$P$6,24,IF(A29<=$P$7,22,IF(A29<=$P$8,20,18))))))) | L29: =IF($N$4="M",IF(A29="","",IF(K29=26,(A29+B29+Q29)*C29*0.02739,IF(K29=24,(A29+B29+Q29)*C29*0.02739,IF(K29=22,(A29+B29+Q29)*C29*0.0333,IF(K29=20,(A29+B29+Q29)*C29*0.0393,IF(K29=18,(A29+B29+Q29)*C29*0.0511,IF(K29=16,(A29+B29+Q29)*C29*0.0628))))))),IF(A29="","",IF(K29=26,(A29+B29+Q29)*C29*0.211,IF(K29=24,(A29+B29+Q29)*C29*0.211,IF(K29=22,(A29+B29+Q29)*C29*0.258,IF(K29=20,(A29+B29+Q29)*C29*0.304,IF(K29=18,(A29+B29+Q29)*C29*0.395,IF(K29=16,(A29+B29+Q29)*C29*0.487)))))))) | M29: =IF(D29=1,0.5,IF(D29=2,"1 F",IF(D29=21,"1 R",IF(D29=3,2,"")))) | N29: =IF(M29="","",IF($N$4="M",(A29+B29+Q29)*C29*0.022,(A29+B29+Q29)*C29*0.17)) | O29: =IF(D29=4,1,IF(D29=5,2,"")) | P29: =IF(O29="","",IF($N$4="M",IF(O29=1,(A29+B29+Q29)*C29*0.022*1.1,(A29+B29+Q29)*C29*0.022*1.15),IF(O29=1,(A29+B29+Q29)*C29*0.17*1.1,(A29+B29+Q29)*C29*0.17*1.15))) | Q29: =IF($N$4="M",IF(A29="","",IF(D29=1,50,IF(D29=2,100,IF(D29=21,100,IF(D29=3,200,0))))),IF(A29="","",IF(D29=1,2,IF(D29=2,4,IF(D29=21,4,IF(D29=3,8,0)))))) | R29: =COUNTIF(G29:J29,7) -> 0 | S29: =IF(A29="","",IF($N$4="M",A29*B29*0.000011111*R29*1.5,A29*B29/144*R29*1.5)) | T29: =COUNTIF(G29:J29,71) -> 0 | U29: =IF(A29="","",IF($N$4="M",A29*B29*0.000011111*T29*1.5,A29*B29/144*T29*1.5)) | V29: =COUNTIF(G29:J29,8) -> 0 | W29: =IF(A29="","",IF($N$4="M",(A29+B29)*2*0.0032808*V29,(A29+B29)*2*V29/12)) | X29: =COUNTIF(G29:J29,81) -> 0 | Y29: =IF(A29="","",IF($N$4="M",(A29+B29)*2*0.0032808*X29,(A29+B29)*2*X29/12)) | Z29: =COUNTIF(G29:J29,9) -> 0 | AA29: =COUNTIF(G29:J29,10) -> 0 | AB29: =IF(A29="","",IF($N$4="M",(A29+B29)*2*0.0032808*AA29,(A29+B29)*2*AA29/12)) | AC29: =COUNTIF(G29:J29,100) -> 0 | AE29: =COUNTIF(G29:J29,11) -> 0 | AF29: =IF(A29="","",IF($N$4="M",A29*B29*0.000011111*AE29,A29*B29/144*AE29)) | AG29: =COUNTIF(G29:J29,111) -> 0 | AH29: =IF(A29="","",IF($N$4="M",A29*B29*0.000011111*AG29,A29*B29/144*AG29)) | AI29: =COUNTIF(G29:J29,12) -> 0 | AJ29: =IF(A29="","",IF($N$4="M",A29*B29*0.000011111*AI29,A29*B29/144*AI29)) | AK29: =COUNTIF(G29:J29,13) -> 0 | AL29: =COUNTIF(G29:J29,131) -> 0 | AM29: =IF(A29="","",IF($N$4="M",A29*B29*0.000011111*AL29,A29*B29/144*AL29)) | AN29: =COUNTIF(G29:J29,14) -> 0 | AO29: =IF(A29="","",IF($N$4="M",A29*B29*0.000011111*AN29,A29*B29/144*AN29)) | AP29: =COUNTIF(G29:J29,141) -> 0 | AQ29: =IF(A29="","",IF($N$4="M",A29*B29*0.000011111*AP29,A29*B29/144*AP29)) | AR29: =COUNTIF(G29:J29,15) -> 0 | AS29: =COUNTIF(G29:J29,16) -> 0 | AT29: =IF(A29="","",IF($N$4="M",A29*B29*0.000011111*AS29,A29*B29/144*AS29)) | AU29: =IF(D29=61,C29,0) -> 0 | AV29: =IF(D29=61,L29,0) -> 0 | AW29: =IF(A29="","",(C29-AU29)) | AX29: =IF(A29="","",(L29-AV29))
A30: 1200 | B30: 400 | C30: 14.9 | F30: RE | G30: 71 | H30: 10 | I30: 10 | K30: =IF($N$4="M",IF(A30="","",IF(D30=6,16,IF(A30<=$M$5,26,IF(A30<=$M$6,24,IF(A30<=$M$7,22,IF(A30<=$M$8,20,18)))))),IF(A30="","",IF(D30=6,16,IF(A30<=$P$5,26,IF(A30<=$P$6,24,IF(A30<=$P$7,22,IF(A30<=$P$8,20,18))))))) | L30: =IF($N$4="M",IF(A30="","",IF(K30=26,(A30+B30+Q30)*C30*0.02739,IF(K30=24,(A30+B30+Q30)*C30*0.02739,IF(K30=22,(A30+B30+Q30)*C30*0.0333,IF(K30=20,(A30+B30+Q30)*C30*0.0393,IF(K30=18,(A30+B30+Q30)*C30*0.0511,IF(K30=16,(A30+B30+Q30)*C30*0.0628))))))),IF(A30="","",IF(K30=26,(A30+B30+Q30)*C30*0.211,IF(K30=24,(A30+B30+Q30)*C30*0.211,IF(K30=22,(A30+B30+Q30)*C30*0.258,IF(K30=20,(A30+B30+Q30)*C30*0.304,IF(K30=18,(A30+B30+Q30)*C30*0.395,IF(K30=16,(A30+B30+Q30)*C30*0.487)))))))) | M30: =IF(D30=1,0.5,IF(D30=2,"1 F",IF(D30=21,"1 R",IF(D30=3,2,"")))) | N30: =IF(M30="","",IF($N$4="M",(A30+B30+Q30)*C30*0.022,(A30+B30+Q30)*C30*0.17)) | O30: =IF(D30=4,1,IF(D30=5,2,"")) | P30: =IF(O30="","",IF($N$4="M",IF(O30=1,(A30+B30+Q30)*C30*0.022*1.1,(A30+B30+Q30)*C30*0.022*1.15),IF(O30=1,(A30+B30+Q30)*C30*0.17*1.1,(A30+B30+Q30)*C30*0.17*1.15))) | Q30: =IF($N$4="M",IF(A30="","",IF(D30=1,50,IF(D30=2,100,IF(D30=21,100,IF(D30=3,200,0))))),IF(A30="","",IF(D30=1,2,IF(D30=2,4,IF(D30=21,4,IF(D30=3,8,0)))))) | R30: =COUNTIF(G30:J30,7) -> 0 | S30: =IF(A30="","",IF($N$4="M",A30*B30*0.000011111*R30*1.5,A30*B30/144*R30*1.5)) | T30: =COUNTIF(G30:J30,71) -> 0 | U30: =IF(A30="","",IF($N$4="M",A30*B30*0.000011111*T30*1.5,A30*B30/144*T30*1.5)) | V30: =COUNTIF(G30:J30,8) -> 0 | W30: =IF(A30="","",IF($N$4="M",(A30+B30)*2*0.0032808*V30,(A30+B30)*2*V30/12)) | X30: =COUNTIF(G30:J30,81) -> 0 | Y30: =IF(A30="","",IF($N$4="M",(A30+B30)*2*0.0032808*X30,(A30+B30)*2*X30/12)) | Z30: =COUNTIF(G30:J30,9) -> 0 | AA30: =COUNTIF(G30:J30,10) -> 0 | AB30: =IF(A30="","",IF($N$4="M",(A30+B30)*2*0.0032808*AA30,(A30+B30)*2*AA30/12)) | AC30: =COUNTIF(G30:J30,100) -> 0 | AE30: =COUNTIF(G30:J30,11) -> 0 | AF30: =IF(A30="","",IF($N$4="M",A30*B30*0.000011111*AE30,A30*B30/144*AE30)) | AG30: =COUNTIF(G30:J30,111) -> 0 | AH30: =IF(A30="","",IF($N$4="M",A30*B30*0.000011111*AG30,A30*B30/144*AG30)) | AI30: =COUNTIF(G30:J30,12) -> 0 | AJ30: =IF(A30="","",IF($N$4="M",A30*B30*0.000011111*AI30,A30*B30/144*AI30)) | AK30: =COUNTIF(G30:J30,13) -> 0 | AL30: =COUNTIF(G30:J30,131) -> 0 | AM30: =IF(A30="","",IF($N$4="M",A30*B30*0.000011111*AL30,A30*B30/144*AL30)) | AN30: =COUNTIF(G30:J30,14) -> 0 | AO30: =IF(A30="","",IF($N$4="M",A30*B30*0.000011111*AN30,A30*B30/144*AN30)) | AP30: =COUNTIF(G30:J30,141) -> 0 | AQ30: =IF(A30="","",IF($N$4="M",A30*B30*0.000011111*AP30,A30*B30/144*AP30)) | AR30: =COUNTIF(G30:J30,15) -> 0 | AS30: =COUNTIF(G30:J30,16) -> 0 | AT30: =IF(A30="","",IF($N$4="M",A30*B30*0.000011111*AS30,A30*B30/144*AS30)) | AU30: =IF(D30=61,C30,0) -> 0 | AV30: =IF(D30=61,L30,0) -> 0 | AW30: =IF(A30="","",(C30-AU30)) | AX30: =IF(A30="","",(L30-AV30))
A31: 1200 | B31: 600 | C31: 8 | D31: 6 | E31: HP | F31: RE | G31: 21 | H31: 81 | K31: =IF($N$4="M",IF(A31="","",IF(D31=6,16,IF(A31<=$M$5,26,IF(A31<=$M$6,24,IF(A31<=$M$7,22,IF(A31<=$M$8,20,18)))))),IF(A31="","",IF(D31=6,16,IF(A31<=$P$5,26,IF(A31<=$P$6,24,IF(A31<=$P$7,22,IF(A31<=$P$8,20,18))))))) | L31: =IF($N$4="M",IF(A31="","",IF(K31=26,(A31+B31+Q31)*C31*0.02739,IF(K31=24,(A31+B31+Q31)*C31*0.02739,IF(K31=22,(A31+B31+Q31)*C31*0.0333,IF(K31=20,(A31+B31+Q31)*C31*0.0393,IF(K31=18,(A31+B31+Q31)*C31*0.0511,IF(K31=16,(A31+B31+Q31)*C31*0.0628))))))),IF(A31="","",IF(K31=26,(A31+B31+Q31)*C31*0.211,IF(K31=24,(A31+B31+Q31)*C31*0.211,IF(K31=22,(A31+B31+Q31)*C31*0.258,IF(K31=20,(A31+B31+Q31)*C31*0.304,IF(K31=18,(A31+B31+Q31)*C31*0.395,IF(K31=16,(A31+B31+Q31)*C31*0.487)))))))) | M31: =IF(D31=1,0.5,IF(D31=2,"1 F",IF(D31=21,"1 R",IF(D31=3,2,"")))) | N31: =IF(M31="","",IF($N$4="M",(A31+B31+Q31)*C31*0.022,(A31+B31+Q31)*C31*0.17)) | O31: =IF(D31=4,1,IF(D31=5,2,"")) | P31: =IF(O31="","",IF($N$4="M",IF(O31=1,(A31+B31+Q31)*C31*0.022*1.1,(A31+B31+Q31)*C31*0.022*1.15),IF(O31=1,(A31+B31+Q31)*C31*0.17*1.1,(A31+B31+Q31)*C31*0.17*1.15))) | Q31: =IF($N$4="M",IF(A31="","",IF(D31=1,50,IF(D31=2,100,IF(D31=21,100,IF(D31=3,200,0))))),IF(A31="","",IF(D31=1,2,IF(D31=2,4,IF(D31=21,4,IF(D31=3,8,0)))))) | R31: =COUNTIF(G31:J31,7) -> 0 | S31: =IF(A31="","",IF($N$4="M",A31*B31*0.000011111*R31*1.5,A31*B31/144*R31*1.5)) | T31: =COUNTIF(G31:J31,71) -> 0 | U31: =IF(A31="","",IF($N$4="M",A31*B31*0.000011111*T31*1.5,A31*B31/144*T31*1.5)) | V31: =COUNTIF(G31:J31,8) -> 0 | W31: =IF(A31="","",IF($N$4="M",(A31+B31)*2*0.0032808*V31,(A31+B31)*2*V31/12)) | X31: =COUNTIF(G31:J31,81) -> 0 | Y31: =IF(A31="","",IF($N$4="M",(A31+B31)*2*0.0032808*X31,(A31+B31)*2*X31/12)) | Z31: =COUNTIF(G31:J31,9) -> 0 | AA31: =COUNTIF(G31:J31,10) -> 0 | AB31: =IF(A31="","",IF($N$4="M",(A31+B31)*2*0.0032808*AA31,(A31+B31)*2*AA31/12)) | AC31: =COUNTIF(G31:J31,100) -> 0 | AE31: =COUNTIF(G31:J31,11) -> 0 | AF31: =IF(A31="","",IF($N$4="M",A31*B31*0.000011111*AE31,A31*B31/144*AE31)) | AG31: =COUNTIF(G31:J31,111) -> 0 | AH31: =IF(A31="","",IF($N$4="M",A31*B31*0.000011111*AG31,A31*B31/144*AG31)) | AI31: =COUNTIF(G31:J31,12) -> 0 | AJ31: =IF(A31="","",IF($N$4="M",A31*B31*0.000011111*AI31,A31*B31/144*AI31)) | AK31: =COUNTIF(G31:J31,13) -> 0 | AL31: =COUNTIF(G31:J31,131) -> 0 | AM31: =IF(A31="","",IF($N$4="M",A31*B31*0.000011111*AL31,A31*B31/144*AL31)) | AN31: =COUNTIF(G31:J31,14) -> 0 | AO31: =IF(A31="","",IF($N$4="M",A31*B31*0.000011111*AN31,A31*B31/144*AN31)) | AP31: =COUNTIF(G31:J31,141) -> 0 | AQ31: =IF(A31="","",IF($N$4="M",A31*B31*0.000011111*AP31,A31*B31/144*AP31)) | AR31: =COUNTIF(G31:J31,15) -> 0 | AS31: =COUNTIF(G31:J31,16) -> 0 | AT31: =IF(A31="","",IF($N$4="M",A31*B31*0.000011111*AS31,A31*B31/144*AS31)) | AU31: =IF(D31=61,C31,0) -> 0 | AV31: =IF(D31=61,L31,0) -> 0 | AW31: =IF(A31="","",(C31-AU31)) | AX31: =IF(A31="","",(L31-AV31))
A32: 150 | B32: 150 | C32: 80.5 | F32: HA | G32: 100 | H32: 7 | I32: 13 | J32: 13 | K32: =IF($N$4="M",IF(A32="","",IF(D32=6,16,IF(A32<=$M$5,26,IF(A32<=$M$6,24,IF(A32<=$M$7,22,IF(A32<=$M$8,20,18)))))),IF(A32="","",IF(D32=6,16,IF(A32<=$P$5,26,IF(A32<=$P$6,24,IF(A32<=$P$7,22,IF(A32<=$P$8,20,18))))))) | L32: =IF($N$4="M",IF(A32="","",IF(K32=26,(A32+B32+Q32)*C32*0.02739,IF(K32=24,(A32+B32+Q32)*C32*0.02739,IF(K32=22,(A32+B32+Q32)*C32*0.0333,IF(K32=20,(A32+B32+Q32)*C32*0.0393,IF(K32=18,(A32+B32+Q32)*C32*0.0511,IF(K32=16,(A32+B32+Q32)*C32*0.0628))))))),IF(A32="","",IF(K32=26,(A32+B32+Q32)*C32*0.211,IF(K32=24,(A32+B32+Q32)*C32*0.211,IF(K32=22,(A32+B32+Q32)*C32*0.258,IF(K32=20,(A32+B32+Q32)*C32*0.304,IF(K32=18,(A32+B32+Q32)*C32*0.395,IF(K32=16,(A32+B32+Q32)*C32*0.487)))))))) | M32: =IF(D32=1,0.5,IF(D32=2,"1 F",IF(D32=21,"1 R",IF(D32=3,2,"")))) | N32: =IF(M32="","",IF($N$4="M",(A32+B32+Q32)*C32*0.022,(A32+B32+Q32)*C32*0.17)) | O32: =IF(D32=4,1,IF(D32=5,2,"")) | P32: =IF(O32="","",IF($N$4="M",IF(O32=1,(A32+B32+Q32)*C32*0.022*1.1,(A32+B32+Q32)*C32*0.022*1.15),IF(O32=1,(A32+B32+Q32)*C32*0.17*1.1,(A32+B32+Q32)*C32*0.17*1.15))) | Q32: =IF($N$4="M",IF(A32="","",IF(D32=1,50,IF(D32=2,100,IF(D32=21,100,IF(D32=3,200,0))))),IF(A32="","",IF(D32=1,2,IF(D32=2,4,IF(D32=21,4,IF(D32=3,8,0)))))) | R32: =COUNTIF(G32:J32,7) -> 0 | S32: =IF(A32="","",IF($N$4="M",A32*B32*0.000011111*R32*1.5,A32*B32/144*R32*1.5)) | T32: =COUNTIF(G32:J32,71) -> 0 | U32: =IF(A32="","",IF($N$4="M",A32*B32*0.000011111*T32*1.5,A32*B32/144*T32*1.5)) | V32: =COUNTIF(G32:J32,8) -> 0 | W32: =IF(A32="","",IF($N$4="M",(A32+B32)*2*0.0032808*V32,(A32+B32)*2*V32/12)) | X32: =COUNTIF(G32:J32,81) -> 0 | Y32: =IF(A32="","",IF($N$4="M",(A32+B32)*2*0.0032808*X32,(A32+B32)*2*X32/12)) | Z32: =COUNTIF(G32:J32,9) -> 0 | AA32: =COUNTIF(G32:J32,10) -> 0 | AB32: =IF(A32="","",IF($N$4="M",(A32+B32)*2*0.0032808*AA32,(A32+B32)*2*AA32/12)) | AC32: =COUNTIF(G32:J32,100) -> 0 | AE32: =COUNTIF(G32:J32,11) -> 0 | AF32: =IF(A32="","",IF($N$4="M",A32*B32*0.000011111*AE32,A32*B32/144*AE32)) | AG32: =COUNTIF(G32:J32,111) -> 0 | AH32: =IF(A32="","",IF($N$4="M",A32*B32*0.000011111*AG32,A32*B32/144*AG32)) | AI32: =COUNTIF(G32:J32,12) -> 0 | AJ32: =IF(A32="","",IF($N$4="M",A32*B32*0.000011111*AI32,A32*B32/144*AI32)) | AK32: =COUNTIF(G32:J32,13) -> 0 | AL32: =COUNTIF(G32:J32,131) -> 0 | AM32: =IF(A32="","",IF($N$4="M",A32*B32*0.000011111*AL32,A32*B32/144*AL32)) | AN32: =COUNTIF(G32:J32,14) -> 0 | AO32: =IF(A32="","",IF($N$4="M",A32*B32*0.000011111*AN32,A32*B32/144*AN32)) | AP32: =COUNTIF(G32:J32,141) -> 0 | AQ32: =IF(A32="","",IF($N$4="M",A32*B32*0.000011111*AP32,A32*B32/144*AP32)) | AR32: =COUNTIF(G32:J32,15) -> 0 | AS32: =COUNTIF(G32:J32,16) -> 0 | AT32: =IF(A32="","",IF($N$4="M",A32*B32*0.000011111*AS32,A32*B32/144*AS32)) | AU32: =IF(D32=61,C32,0) -> 0 | AV32: =IF(D32=61,L32,0) -> 0 | AW32: =IF(A32="","",(C32-AU32)) | AX32: =IF(A32="","",(L32-AV32))
A33: 150 | B33: 150 | C33: 0 | F33: HA | G33: 13 | H33: 13 | I33: 13 | J33: 13 | K33: =IF($N$4="M",IF(A33="","",IF(D33=6,16,IF(A33<=$M$5,26,IF(A33<=$M$6,24,IF(A33<=$M$7,22,IF(A33<=$M$8,20,18)))))),IF(A33="","",IF(D33=6,16,IF(A33<=$P$5,26,IF(A33<=$P$6,24,IF(A33<=$P$7,22,IF(A33<=$P$8,20,18))))))) | L33: =IF($N$4="M",IF(A33="","",IF(K33=26,(A33+B33+Q33)*C33*0.02739,IF(K33=24,(A33+B33+Q33)*C33*0.02739,IF(K33=22,(A33+B33+Q33)*C33*0.0333,IF(K33=20,(A33+B33+Q33)*C33*0.0393,IF(K33=18,(A33+B33+Q33)*C33*0.0511,IF(K33=16,(A33+B33+Q33)*C33*0.0628))))))),IF(A33="","",IF(K33=26,(A33+B33+Q33)*C33*0.211,IF(K33=24,(A33+B33+Q33)*C33*0.211,IF(K33=22,(A33+B33+Q33)*C33*0.258,IF(K33=20,(A33+B33+Q33)*C33*0.304,IF(K33=18,(A33+B33+Q33)*C33*0.395,IF(K33=16,(A33+B33+Q33)*C33*0.487)))))))) | M33: =IF(D33=1,0.5,IF(D33=2,"1 F",IF(D33=21,"1 R",IF(D33=3,2,"")))) | N33: =IF(M33="","",IF($N$4="M",(A33+B33+Q33)*C33*0.022,(A33+B33+Q33)*C33*0.17)) | O33: =IF(D33=4,1,IF(D33=5,2,"")) | P33: =IF(O33="","",IF($N$4="M",IF(O33=1,(A33+B33+Q33)*C33*0.022*1.1,(A33+B33+Q33)*C33*0.022*1.15),IF(O33=1,(A33+B33+Q33)*C33*0.17*1.1,(A33+B33+Q33)*C33*0.17*1.15))) | Q33: =IF($N$4="M",IF(A33="","",IF(D33=1,50,IF(D33=2,100,IF(D33=21,100,IF(D33=3,200,0))))),IF(A33="","",IF(D33=1,2,IF(D33=2,4,IF(D33=21,4,IF(D33=3,8,0)))))) | R33: =COUNTIF(G33:J33,7) -> 0 | S33: =IF(A33="","",IF($N$4="M",A33*B33*0.000011111*R33*1.5,A33*B33/144*R33*1.5)) | T33: =COUNTIF(G33:J33,71) -> 0 | U33: =IF(A33="","",IF($N$4="M",A33*B33*0.000011111*T33*1.5,A33*B33/144*T33*1.5)) | V33: =COUNTIF(G33:J33,8) -> 0 | W33: =IF(A33="","",IF($N$4="M",(A33+B33)*2*0.0032808*V33,(A33+B33)*2*V33/12)) | X33: =COUNTIF(G33:J33,81) -> 0 | Y33: =IF(A33="","",IF($N$4="M",(A33+B33)*2*0.0032808*X33,(A33+B33)*2*X33/12)) | Z33: =COUNTIF(G33:J33,9) -> 0 | AA33: =COUNTIF(G33:J33,10) -> 0 | AB33: =IF(A33="","",IF($N$4="M",(A33+B33)*2*0.0032808*AA33,(A33+B33)*2*AA33/12)) | AC33: =COUNTIF(G33:J33,100) -> 0 | AE33: =COUNTIF(G33:J33,11) -> 0 | AF33: =IF(A33="","",IF($N$4="M",A33*B33*0.000011111*AE33,A33*B33/144*AE33)) | AG33: =COUNTIF(G33:J33,111) -> 0 | AH33: =IF(A33="","",IF($N$4="M",A33*B33*0.000011111*AG33,A33*B33/144*AG33)) | AI33: =COUNTIF(G33:J33,12) -> 0 | AJ33: =IF(A33="","",IF($N$4="M",A33*B33*0.000011111*AI33,A33*B33/144*AI33)) | AK33: =COUNTIF(G33:J33,13) -> 0 | AL33: =COUNTIF(G33:J33,131) -> 0 | AM33: =IF(A33="","",IF($N$4="M",A33*B33*0.000011111*AL33,A33*B33/144*AL33)) | AN33: =COUNTIF(G33:J33,14) -> 0 | AO33: =IF(A33="","",IF($N$4="M",A33*B33*0.000011111*AN33,A33*B33/144*AN33)) | AP33: =COUNTIF(G33:J33,141) -> 0 | AQ33: =IF(A33="","",IF($N$4="M",A33*B33*0.000011111*AP33,A33*B33/144*AP33)) | AR33: =COUNTIF(G33:J33,15) -> 0 | AS33: =COUNTIF(G33:J33,16) -> 0 | AT33: =IF(A33="","",IF($N$4="M",A33*B33*0.000011111*AS33,A33*B33/144*AS33)) | AU33: =IF(D33=61,C33,0) -> 0 | AV33: =IF(D33=61,L33,0) -> 0 | AW33: =IF(A33="","",(C33-AU33)) | AX33: =IF(A33="","",(L33-AV33))
A34: 150 | B34: 150 | C34: 0 | F34: HA | G34: 10 | H34: 10 | K34: =IF($N$4="M",IF(A34="","",IF(D34=6,16,IF(A34<=$M$5,26,IF(A34<=$M$6,24,IF(A34<=$M$7,22,IF(A34<=$M$8,20,18)))))),IF(A34="","",IF(D34=6,16,IF(A34<=$P$5,26,IF(A34<=$P$6,24,IF(A34<=$P$7,22,IF(A34<=$P$8,20,18))))))) | L34: =IF($N$4="M",IF(A34="","",IF(K34=26,(A34+B34+Q34)*C34*0.02739,IF(K34=24,(A34+B34+Q34)*C34*0.02739,IF(K34=22,(A34+B34+Q34)*C34*0.0333,IF(K34=20,(A34+B34+Q34)*C34*0.0393,IF(K34=18,(A34+B34+Q34)*C34*0.0511,IF(K34=16,(A34+B34+Q34)*C34*0.0628))))))),IF(A34="","",IF(K34=26,(A34+B34+Q34)*C34*0.211,IF(K34=24,(A34+B34+Q34)*C34*0.211,IF(K34=22,(A34+B34+Q34)*C34*0.258,IF(K34=20,(A34+B34+Q34)*C34*0.304,IF(K34=18,(A34+B34+Q34)*C34*0.395,IF(K34=16,(A34+B34+Q34)*C34*0.487)))))))) | M34: =IF(D34=1,0.5,IF(D34=2,"1 F",IF(D34=21,"1 R",IF(D34=3,2,"")))) | N34: =IF(M34="","",IF($N$4="M",(A34+B34+Q34)*C34*0.022,(A34+B34+Q34)*C34*0.17)) | O34: =IF(D34=4,1,IF(D34=5,2,"")) | P34: =IF(O34="","",IF($N$4="M",IF(O34=1,(A34+B34+Q34)*C34*0.022*1.1,(A34+B34+Q34)*C34*0.022*1.15),IF(O34=1,(A34+B34+Q34)*C34*0.17*1.1,(A34+B34+Q34)*C34*0.17*1.15))) | Q34: =IF($N$4="M",IF(A34="","",IF(D34=1,50,IF(D34=2,100,IF(D34=21,100,IF(D34=3,200,0))))),IF(A34="","",IF(D34=1,2,IF(D34=2,4,IF(D34=21,4,IF(D34=3,8,0)))))) | R34: =COUNTIF(G34:J34,7) -> 0 | S34: =IF(A34="","",IF($N$4="M",A34*B34*0.000011111*R34*1.5,A34*B34/144*R34*1.5)) | T34: =COUNTIF(G34:J34,71) -> 0 | U34: =IF(A34="","",IF($N$4="M",A34*B34*0.000011111*T34*1.5,A34*B34/144*T34*1.5)) | V34: =COUNTIF(G34:J34,8) -> 0 | W34: =IF(A34="","",IF($N$4="M",(A34+B34)*2*0.0032808*V34,(A34+B34)*2*V34/12)) | X34: =COUNTIF(G34:J34,81) -> 0 | Y34: =IF(A34="","",IF($N$4="M",(A34+B34)*2*0.0032808*X34,(A34+B34)*2*X34/12)) | Z34: =COUNTIF(G34:J34,9) -> 0 | AA34: =COUNTIF(G34:J34,10) -> 0 | AB34: =IF(A34="","",IF($N$4="M",(A34+B34)*2*0.0032808*AA34,(A34+B34)*2*AA34/12)) | AC34: =COUNTIF(G34:J34,100) -> 0 | AE34: =COUNTIF(G34:J34,11) -> 0 | AF34: =IF(A34="","",IF($N$4="M",A34*B34*0.000011111*AE34,A34*B34/144*AE34)) | AG34: =COUNTIF(G34:J34,111) -> 0 | AH34: =IF(A34="","",IF($N$4="M",A34*B34*0.000011111*AG34,A34*B34/144*AG34)) | AI34: =COUNTIF(G34:J34,12) -> 0 | AJ34: =IF(A34="","",IF($N$4="M",A34*B34*0.000011111*AI34,A34*B34/144*AI34)) | AK34: =COUNTIF(G34:J34,13) -> 0 | AL34: =COUNTIF(G34:J34,131) -> 0 | AM34: =IF(A34="","",IF($N$4="M",A34*B34*0.000011111*AL34,A34*B34/144*AL34)) | AN34: =COUNTIF(G34:J34,14) -> 0 | AO34: =IF(A34="","",IF($N$4="M",A34*B34*0.000011111*AN34,A34*B34/144*AN34)) | AP34: =COUNTIF(G34:J34,141) -> 0 | AQ34: =IF(A34="","",IF($N$4="M",A34*B34*0.000011111*AP34,A34*B34/144*AP34)) | AR34: =COUNTIF(G34:J34,15) -> 0 | AS34: =COUNTIF(G34:J34,16) -> 0 | AT34: =IF(A34="","",IF($N$4="M",A34*B34*0.000011111*AS34,A34*B34/144*AS34)) | AU34: =IF(D34=61,C34,0) -> 0 | AV34: =IF(D34=61,L34,0) -> 0 | AW34: =IF(A34="","",(C34-AU34)) | AX34: =IF(A34="","",(L34-AV34))
A35: 200 | B35: 150 | C35: 8.7 | F35: HA | G35: 7 | H35: 13 | K35: =IF($N$4="M",IF(A35="","",IF(D35=6,16,IF(A35<=$M$5,26,IF(A35<=$M$6,24,IF(A35<=$M$7,22,IF(A35<=$M$8,20,18)))))),IF(A35="","",IF(D35=6,16,IF(A35<=$P$5,26,IF(A35<=$P$6,24,IF(A35<=$P$7,22,IF(A35<=$P$8,20,18))))))) | L35: =IF($N$4="M",IF(A35="","",IF(K35=26,(A35+B35+Q35)*C35*0.02739,IF(K35=24,(A35+B35+Q35)*C35*0.02739,IF(K35=22,(A35+B35+Q35)*C35*0.0333,IF(K35=20,(A35+B35+Q35)*C35*0.0393,IF(K35=18,(A35+B35+Q35)*C35*0.0511,IF(K35=16,(A35+B35+Q35)*C35*0.0628))))))),IF(A35="","",IF(K35=26,(A35+B35+Q35)*C35*0.211,IF(K35=24,(A35+B35+Q35)*C35*0.211,IF(K35=22,(A35+B35+Q35)*C35*0.258,IF(K35=20,(A35+B35+Q35)*C35*0.304,IF(K35=18,(A35+B35+Q35)*C35*0.395,IF(K35=16,(A35+B35+Q35)*C35*0.487)))))))) | M35: =IF(D35=1,0.5,IF(D35=2,"1 F",IF(D35=21,"1 R",IF(D35=3,2,"")))) | N35: =IF(M35="","",IF($N$4="M",(A35+B35+Q35)*C35*0.022,(A35+B35+Q35)*C35*0.17)) | O35: =IF(D35=4,1,IF(D35=5,2,"")) | P35: =IF(O35="","",IF($N$4="M",IF(O35=1,(A35+B35+Q35)*C35*0.022*1.1,(A35+B35+Q35)*C35*0.022*1.15),IF(O35=1,(A35+B35+Q35)*C35*0.17*1.1,(A35+B35+Q35)*C35*0.17*1.15))) | Q35: =IF($N$4="M",IF(A35="","",IF(D35=1,50,IF(D35=2,100,IF(D35=21,100,IF(D35=3,200,0))))),IF(A35="","",IF(D35=1,2,IF(D35=2,4,IF(D35=21,4,IF(D35=3,8,0)))))) | R35: =COUNTIF(G35:J35,7) -> 0 | S35: =IF(A35="","",IF($N$4="M",A35*B35*0.000011111*R35*1.5,A35*B35/144*R35*1.5)) | T35: =COUNTIF(G35:J35,71) -> 0 | U35: =IF(A35="","",IF($N$4="M",A35*B35*0.000011111*T35*1.5,A35*B35/144*T35*1.5)) | V35: =COUNTIF(G35:J35,8) -> 0 | W35: =IF(A35="","",IF($N$4="M",(A35+B35)*2*0.0032808*V35,(A35+B35)*2*V35/12)) | X35: =COUNTIF(G35:J35,81) -> 0 | Y35: =IF(A35="","",IF($N$4="M",(A35+B35)*2*0.0032808*X35,(A35+B35)*2*X35/12)) | Z35: =COUNTIF(G35:J35,9) -> 0 | AA35: =COUNTIF(G35:J35,10) -> 0 | AB35: =IF(A35="","",IF($N$4="M",(A35+B35)*2*0.0032808*AA35,(A35+B35)*2*AA35/12)) | AC35: =COUNTIF(G35:J35,100) -> 0 | AE35: =COUNTIF(G35:J35,11) -> 0 | AF35: =IF(A35="","",IF($N$4="M",A35*B35*0.000011111*AE35,A35*B35/144*AE35)) | AG35: =COUNTIF(G35:J35,111) -> 0 | AH35: =IF(A35="","",IF($N$4="M",A35*B35*0.000011111*AG35,A35*B35/144*AG35)) | AI35: =COUNTIF(G35:J35,12) -> 0 | AJ35: =IF(A35="","",IF($N$4="M",A35*B35*0.000011111*AI35,A35*B35/144*AI35)) | AK35: =COUNTIF(G35:J35,13) -> 0 | AL35: =COUNTIF(G35:J35,131) -> 0 | AM35: =IF(A35="","",IF($N$4="M",A35*B35*0.000011111*AL35,A35*B35/144*AL35)) | AN35: =COUNTIF(G35:J35,14) -> 0 | AO35: =IF(A35="","",IF($N$4="M",A35*B35*0.000011111*AN35,A35*B35/144*AN35)) | AP35: =COUNTIF(G35:J35,141) -> 0 | AQ35: =IF(A35="","",IF($N$4="M",A35*B35*0.000011111*AP35,A35*B35/144*AP35)) | AR35: =COUNTIF(G35:J35,15) -> 0 | AS35: =COUNTIF(G35:J35,16) -> 0 | AT35: =IF(A35="","",IF($N$4="M",A35*B35*0.000011111*AS35,A35*B35/144*AS35)) | AU35: =IF(D35=61,C35,0) -> 0 | AV35: =IF(D35=61,L35,0) -> 0 | AW35: =IF(A35="","",(C35-AU35)) | AX35: =IF(A35="","",(L35-AV35))
A36: 200 | B36: 200 | C36: 75.9 | F36: HA | K36: =IF($N$4="M",IF(A36="","",IF(D36=6,16,IF(A36<=$M$5,26,IF(A36<=$M$6,24,IF(A36<=$M$7,22,IF(A36<=$M$8,20,18)))))),IF(A36="","",IF(D36=6,16,IF(A36<=$P$5,26,IF(A36<=$P$6,24,IF(A36<=$P$7,22,IF(A36<=$P$8,20,18))))))) | L36: =IF($N$4="M",IF(A36="","",IF(K36=26,(A36+B36+Q36)*C36*0.02739,IF(K36=24,(A36+B36+Q36)*C36*0.02739,IF(K36=22,(A36+B36+Q36)*C36*0.0333,IF(K36=20,(A36+B36+Q36)*C36*0.0393,IF(K36=18,(A36+B36+Q36)*C36*0.0511,IF(K36=16,(A36+B36+Q36)*C36*0.0628))))))),IF(A36="","",IF(K36=26,(A36+B36+Q36)*C36*0.211,IF(K36=24,(A36+B36+Q36)*C36*0.211,IF(K36=22,(A36+B36+Q36)*C36*0.258,IF(K36=20,(A36+B36+Q36)*C36*0.304,IF(K36=18,(A36+B36+Q36)*C36*0.395,IF(K36=16,(A36+B36+Q36)*C36*0.487)))))))) | M36: =IF(D36=1,0.5,IF(D36=2,"1 F",IF(D36=21,"1 R",IF(D36=3,2,"")))) | N36: =IF(M36="","",IF($N$4="M",(A36+B36+Q36)*C36*0.022,(A36+B36+Q36)*C36*0.17)) | O36: =IF(D36=4,1,IF(D36=5,2,"")) | P36: =IF(O36="","",IF($N$4="M",IF(O36=1,(A36+B36+Q36)*C36*0.022*1.1,(A36+B36+Q36)*C36*0.022*1.15),IF(O36=1,(A36+B36+Q36)*C36*0.17*1.1,(A36+B36+Q36)*C36*0.17*1.15))) | Q36: =IF($N$4="M",IF(A36="","",IF(D36=1,50,IF(D36=2,100,IF(D36=21,100,IF(D36=3,200,0))))),IF(A36="","",IF(D36=1,2,IF(D36=2,4,IF(D36=21,4,IF(D36=3,8,0)))))) | R36: =COUNTIF(G36:J36,7) -> 0 | S36: =IF(A36="","",IF($N$4="M",A36*B36*0.000011111*R36*1.5,A36*B36/144*R36*1.5)) | T36: =COUNTIF(G36:J36,71) -> 0 | U36: =IF(A36="","",IF($N$4="M",A36*B36*0.000011111*T36*1.5,A36*B36/144*T36*1.5)) | V36: =COUNTIF(G36:J36,8) -> 0 | W36: =IF(A36="","",IF($N$4="M",(A36+B36)*2*0.0032808*V36,(A36+B36)*2*V36/12)) | X36: =COUNTIF(G36:J36,81) -> 0 | Y36: =IF(A36="","",IF($N$4="M",(A36+B36)*2*0.0032808*X36,(A36+B36)*2*X36/12)) | Z36: =COUNTIF(G36:J36,9) -> 0 | AA36: =COUNTIF(G36:J36,10) -> 0 | AB36: =IF(A36="","",IF($N$4="M",(A36+B36)*2*0.0032808*AA36,(A36+B36)*2*AA36/12)) | AC36: =COUNTIF(G36:J36,100) -> 0 | AE36: =COUNTIF(G36:J36,11) -> 0 | AF36: =IF(A36="","",IF($N$4="M",A36*B36*0.000011111*AE36,A36*B36/144*AE36)) | AG36: =COUNTIF(G36:J36,111) -> 0 | AH36: =IF(A36="","",IF($N$4="M",A36*B36*0.000011111*AG36,A36*B36/144*AG36)) | AI36: =COUNTIF(G36:J36,12) -> 0 | AJ36: =IF(A36="","",IF($N$4="M",A36*B36*0.000011111*AI36,A36*B36/144*AI36)) | AK36: =COUNTIF(G36:J36,13) -> 0 | AL36: =COUNTIF(G36:J36,131) -> 0 | AM36: =IF(A36="","",IF($N$4="M",A36*B36*0.000011111*AL36,A36*B36/144*AL36)) | AN36: =COUNTIF(G36:J36,14) -> 0 | AO36: =IF(A36="","",IF($N$4="M",A36*B36*0.000011111*AN36,A36*B36/144*AN36)) | AP36: =COUNTIF(G36:J36,141) -> 0 | AQ36: =IF(A36="","",IF($N$4="M",A36*B36*0.000011111*AP36,A36*B36/144*AP36)) | AR36: =COUNTIF(G36:J36,15) -> 0 | AS36: =COUNTIF(G36:J36,16) -> 0 | AT36: =IF(A36="","",IF($N$4="M",A36*B36*0.000011111*AS36,A36*B36/144*AS36)) | AU36: =IF(D36=61,C36,0) -> 0 | AV36: =IF(D36=61,L36,0) -> 0 | AW36: =IF(A36="","",(C36-AU36)) | AX36: =IF(A36="","",(L36-AV36))
A37: 200 | B37: 200 | C37: 6.6 | F37: HA | G37: 21 | K37: =IF($N$4="M",IF(A37="","",IF(D37=6,16,IF(A37<=$M$5,26,IF(A37<=$M$6,24,IF(A37<=$M$7,22,IF(A37<=$M$8,20,18)))))),IF(A37="","",IF(D37=6,16,IF(A37<=$P$5,26,IF(A37<=$P$6,24,IF(A37<=$P$7,22,IF(A37<=$P$8,20,18))))))) | L37: =IF($N$4="M",IF(A37="","",IF(K37=26,(A37+B37+Q37)*C37*0.02739,IF(K37=24,(A37+B37+Q37)*C37*0.02739,IF(K37=22,(A37+B37+Q37)*C37*0.0333,IF(K37=20,(A37+B37+Q37)*C37*0.0393,IF(K37=18,(A37+B37+Q37)*C37*0.0511,IF(K37=16,(A37+B37+Q37)*C37*0.0628))))))),IF(A37="","",IF(K37=26,(A37+B37+Q37)*C37*0.211,IF(K37=24,(A37+B37+Q37)*C37*0.211,IF(K37=22,(A37+B37+Q37)*C37*0.258,IF(K37=20,(A37+B37+Q37)*C37*0.304,IF(K37=18,(A37+B37+Q37)*C37*0.395,IF(K37=16,(A37+B37+Q37)*C37*0.487)))))))) | M37: =IF(D37=1,0.5,IF(D37=2,"1 F",IF(D37=21,"1 R",IF(D37=3,2,"")))) | N37: =IF(M37="","",IF($N$4="M",(A37+B37+Q37)*C37*0.022,(A37+B37+Q37)*C37*0.17)) | O37: =IF(D37=4,1,IF(D37=5,2,"")) | P37: =IF(O37="","",IF($N$4="M",IF(O37=1,(A37+B37+Q37)*C37*0.022*1.1,(A37+B37+Q37)*C37*0.022*1.15),IF(O37=1,(A37+B37+Q37)*C37*0.17*1.1,(A37+B37+Q37)*C37*0.17*1.15))) | Q37: =IF($N$4="M",IF(A37="","",IF(D37=1,50,IF(D37=2,100,IF(D37=21,100,IF(D37=3,200,0))))),IF(A37="","",IF(D37=1,2,IF(D37=2,4,IF(D37=21,4,IF(D37=3,8,0)))))) | R37: =COUNTIF(G37:J37,7) -> 0 | S37: =IF(A37="","",IF($N$4="M",A37*B37*0.000011111*R37*1.5,A37*B37/144*R37*1.5)) | T37: =COUNTIF(G37:J37,71) -> 0 | U37: =IF(A37="","",IF($N$4="M",A37*B37*0.000011111*T37*1.5,A37*B37/144*T37*1.5)) | V37: =COUNTIF(G37:J37,8) -> 0 | W37: =IF(A37="","",IF($N$4="M",(A37+B37)*2*0.0032808*V37,(A37+B37)*2*V37/12)) | X37: =COUNTIF(G37:J37,81) -> 0 | Y37: =IF(A37="","",IF($N$4="M",(A37+B37)*2*0.0032808*X37,(A37+B37)*2*X37/12)) | Z37: =COUNTIF(G37:J37,9) -> 0 | AA37: =COUNTIF(G37:J37,10) -> 0 | AB37: =IF(A37="","",IF($N$4="M",(A37+B37)*2*0.0032808*AA37,(A37+B37)*2*AA37/12)) | AC37: =COUNTIF(G37:J37,100) -> 0 | AE37: =COUNTIF(G37:J37,11) -> 0 | AF37: =IF(A37="","",IF($N$4="M",A37*B37*0.000011111*AE37,A37*B37/144*AE37)) | AG37: =COUNTIF(G37:J37,111) -> 0 | AH37: =IF(A37="","",IF($N$4="M",A37*B37*0.000011111*AG37,A37*B37/144*AG37)) | AI37: =COUNTIF(G37:J37,12) -> 0 | AJ37: =IF(A37="","",IF($N$4="M",A37*B37*0.000011111*AI37,A37*B37/144*AI37)) | AK37: =COUNTIF(G37:J37,13) -> 0 | AL37: =COUNTIF(G37:J37,131) -> 0 | AM37: =IF(A37="","",IF($N$4="M",A37*B37*0.000011111*AL37,A37*B37/144*AL37)) | AN37: =COUNTIF(G37:J37,14) -> 0 | AO37: =IF(A37="","",IF($N$4="M",A37*B37*0.000011111*AN37,A37*B37/144*AN37)) | AP37: =COUNTIF(G37:J37,141) -> 0 | AQ37: =IF(A37="","",IF($N$4="M",A37*B37*0.000011111*AP37,A37*B37/144*AP37)) | AR37: =COUNTIF(G37:J37,15) -> 0 | AS37: =COUNTIF(G37:J37,16) -> 0 | AT37: =IF(A37="","",IF($N$4="M",A37*B37*0.000011111*AS37,A37*B37/144*AS37)) | AU37: =IF(D37=61,C37,0) -> 0 | AV37: =IF(D37=61,L37,0) -> 0 | AW37: =IF(A37="","",(C37-AU37)) | AX37: =IF(A37="","",(L37-AV37))
A38: 2400 | B38: 900 | C38: 2.6 | F38: RE | K38: =IF($N$4="M",IF(A38="","",IF(D38=6,16,IF(A38<=$M$5,26,IF(A38<=$M$6,24,IF(A38<=$M$7,22,IF(A38<=$M$8,20,18)))))),IF(A38="","",IF(D38=6,16,IF(A38<=$P$5,26,IF(A38<=$P$6,24,IF(A38<=$P$7,22,IF(A38<=$P$8,20,18))))))) | L38: =IF($N$4="M",IF(A38="","",IF(K38=26,(A38+B38+Q38)*C38*0.02739,IF(K38=24,(A38+B38+Q38)*C38*0.02739,IF(K38=22,(A38+B38+Q38)*C38*0.0333,IF(K38=20,(A38+B38+Q38)*C38*0.0393,IF(K38=18,(A38+B38+Q38)*C38*0.0511,IF(K38=16,(A38+B38+Q38)*C38*0.0628))))))),IF(A38="","",IF(K38=26,(A38+B38+Q38)*C38*0.211,IF(K38=24,(A38+B38+Q38)*C38*0.211,IF(K38=22,(A38+B38+Q38)*C38*0.258,IF(K38=20,(A38+B38+Q38)*C38*0.304,IF(K38=18,(A38+B38+Q38)*C38*0.395,IF(K38=16,(A38+B38+Q38)*C38*0.487)))))))) | M38: =IF(D38=1,0.5,IF(D38=2,"1 F",IF(D38=21,"1 R",IF(D38=3,2,"")))) | N38: =IF(M38="","",IF($N$4="M",(A38+B38+Q38)*C38*0.022,(A38+B38+Q38)*C38*0.17)) | O38: =IF(D38=4,1,IF(D38=5,2,"")) | P38: =IF(O38="","",IF($N$4="M",IF(O38=1,(A38+B38+Q38)*C38*0.022*1.1,(A38+B38+Q38)*C38*0.022*1.15),IF(O38=1,(A38+B38+Q38)*C38*0.17*1.1,(A38+B38+Q38)*C38*0.17*1.15))) | Q38: =IF($N$4="M",IF(A38="","",IF(D38=1,50,IF(D38=2,100,IF(D38=21,100,IF(D38=3,200,0))))),IF(A38="","",IF(D38=1,2,IF(D38=2,4,IF(D38=21,4,IF(D38=3,8,0)))))) | R38: =COUNTIF(G38:J38,7) -> 0 | S38: =IF(A38="","",IF($N$4="M",A38*B38*0.000011111*R38*1.5,A38*B38/144*R38*1.5)) | T38: =COUNTIF(G38:J38,71) -> 0 | U38: =IF(A38="","",IF($N$4="M",A38*B38*0.000011111*T38*1.5,A38*B38/144*T38*1.5)) | V38: =COUNTIF(G38:J38,8) -> 0 | W38: =IF(A38="","",IF($N$4="M",(A38+B38)*2*0.0032808*V38,(A38+B38)*2*V38/12)) | X38: =COUNTIF(G38:J38,81) -> 0 | Y38: =IF(A38="","",IF($N$4="M",(A38+B38)*2*0.0032808*X38,(A38+B38)*2*X38/12)) | Z38: =COUNTIF(G38:J38,9) -> 0 | AA38: =COUNTIF(G38:J38,10) -> 0 | AB38: =IF(A38="","",IF($N$4="M",(A38+B38)*2*0.0032808*AA38,(A38+B38)*2*AA38/12)) | AC38: =COUNTIF(G38:J38,100) -> 0 | AE38: =COUNTIF(G38:J38,11) -> 0 | AF38: =IF(A38="","",IF($N$4="M",A38*B38*0.000011111*AE38,A38*B38/144*AE38)) | AG38: =COUNTIF(G38:J38,111) -> 0 | AH38: =IF(A38="","",IF($N$4="M",A38*B38*0.000011111*AG38,A38*B38/144*AG38)) | AI38: =COUNTIF(G38:J38,12) -> 0 | AJ38: =IF(A38="","",IF($N$4="M",A38*B38*0.000011111*AI38,A38*B38/144*AI38)) | AK38: =COUNTIF(G38:J38,13) -> 0 | AL38: =COUNTIF(G38:J38,131) -> 0 | AM38: =IF(A38="","",IF($N$4="M",A38*B38*0.000011111*AL38,A38*B38/144*AL38)) | AN38: =COUNTIF(G38:J38,14) -> 0 | AO38: =IF(A38="","",IF($N$4="M",A38*B38*0.000011111*AN38,A38*B38/144*AN38)) | AP38: =COUNTIF(G38:J38,141) -> 0 | AQ38: =IF(A38="","",IF($N$4="M",A38*B38*0.000011111*AP38,A38*B38/144*AP38)) | AR38: =COUNTIF(G38:J38,15) -> 0 | AS38: =COUNTIF(G38:J38,16) -> 0 | AT38: =IF(A38="","",IF($N$4="M",A38*B38*0.000011111*AS38,A38*B38/144*AS38)) | AU38: =IF(D38=61,C38,0) -> 0 | AV38: =IF(D38=61,L38,0) -> 0 | AW38: =IF(A38="","",(C38-AU38)) | AX38: =IF(A38="","",(L38-AV38))
A39: 250 | B39: 150 | C39: 3.7 | F39: HA | K39: =IF($N$4="M",IF(A39="","",IF(D39=6,16,IF(A39<=$M$5,26,IF(A39<=$M$6,24,IF(A39<=$M$7,22,IF(A39<=$M$8,20,18)))))),IF(A39="","",IF(D39=6,16,IF(A39<=$P$5,26,IF(A39<=$P$6,24,IF(A39<=$P$7,22,IF(A39<=$P$8,20,18))))))) | L39: =IF($N$4="M",IF(A39="","",IF(K39=26,(A39+B39+Q39)*C39*0.02739,IF(K39=24,(A39+B39+Q39)*C39*0.02739,IF(K39=22,(A39+B39+Q39)*C39*0.0333,IF(K39=20,(A39+B39+Q39)*C39*0.0393,IF(K39=18,(A39+B39+Q39)*C39*0.0511,IF(K39=16,(A39+B39+Q39)*C39*0.0628))))))),IF(A39="","",IF(K39=26,(A39+B39+Q39)*C39*0.211,IF(K39=24,(A39+B39+Q39)*C39*0.211,IF(K39=22,(A39+B39+Q39)*C39*0.258,IF(K39=20,(A39+B39+Q39)*C39*0.304,IF(K39=18,(A39+B39+Q39)*C39*0.395,IF(K39=16,(A39+B39+Q39)*C39*0.487)))))))) | M39: =IF(D39=1,0.5,IF(D39=2,"1 F",IF(D39=21,"1 R",IF(D39=3,2,"")))) | N39: =IF(M39="","",IF($N$4="M",(A39+B39+Q39)*C39*0.022,(A39+B39+Q39)*C39*0.17)) | O39: =IF(D39=4,1,IF(D39=5,2,"")) | P39: =IF(O39="","",IF($N$4="M",IF(O39=1,(A39+B39+Q39)*C39*0.022*1.1,(A39+B39+Q39)*C39*0.022*1.15),IF(O39=1,(A39+B39+Q39)*C39*0.17*1.1,(A39+B39+Q39)*C39*0.17*1.15))) | Q39: =IF($N$4="M",IF(A39="","",IF(D39=1,50,IF(D39=2,100,IF(D39=21,100,IF(D39=3,200,0))))),IF(A39="","",IF(D39=1,2,IF(D39=2,4,IF(D39=21,4,IF(D39=3,8,0)))))) | R39: =COUNTIF(G39:J39,7) -> 0 | S39: =IF(A39="","",IF($N$4="M",A39*B39*0.000011111*R39*1.5,A39*B39/144*R39*1.5)) | T39: =COUNTIF(G39:J39,71) -> 0 | U39: =IF(A39="","",IF($N$4="M",A39*B39*0.000011111*T39*1.5,A39*B39/144*T39*1.5)) | V39: =COUNTIF(G39:J39,8) -> 0 | W39: =IF(A39="","",IF($N$4="M",(A39+B39)*2*0.0032808*V39,(A39+B39)*2*V39/12)) | X39: =COUNTIF(G39:J39,81) -> 0 | Y39: =IF(A39="","",IF($N$4="M",(A39+B39)*2*0.0032808*X39,(A39+B39)*2*X39/12)) | Z39: =COUNTIF(G39:J39,9) -> 0 | AA39: =COUNTIF(G39:J39,10) -> 0 | AB39: =IF(A39="","",IF($N$4="M",(A39+B39)*2*0.0032808*AA39,(A39+B39)*2*AA39/12)) | AC39: =COUNTIF(G39:J39,100) -> 0 | AE39: =COUNTIF(G39:J39,11) -> 0 | AF39: =IF(A39="","",IF($N$4="M",A39*B39*0.000011111*AE39,A39*B39/144*AE39)) | AG39: =COUNTIF(G39:J39,111) -> 0 | AH39: =IF(A39="","",IF($N$4="M",A39*B39*0.000011111*AG39,A39*B39/144*AG39)) | AI39: =COUNTIF(G39:J39,12) -> 0 | AJ39: =IF(A39="","",IF($N$4="M",A39*B39*0.000011111*AI39,A39*B39/144*AI39)) | AK39: =COUNTIF(G39:J39,13) -> 0 | AL39: =COUNTIF(G39:J39,131) -> 0 | AM39: =IF(A39="","",IF($N$4="M",A39*B39*0.000011111*AL39,A39*B39/144*AL39)) | AN39: =COUNTIF(G39:J39,14) -> 0 | AO39: =IF(A39="","",IF($N$4="M",A39*B39*0.000011111*AN39,A39*B39/144*AN39)) | AP39: =COUNTIF(G39:J39,141) -> 0 | AQ39: =IF(A39="","",IF($N$4="M",A39*B39*0.000011111*AP39,A39*B39/144*AP39)) | AR39: =COUNTIF(G39:J39,15) -> 0 | AS39: =COUNTIF(G39:J39,16) -> 0 | AT39: =IF(A39="","",IF($N$4="M",A39*B39*0.000011111*AS39,A39*B39/144*AS39)) | AU39: =IF(D39=61,C39,0) -> 0 | AV39: =IF(D39=61,L39,0) -> 0 | AW39: =IF(A39="","",(C39-AU39)) | AX39: =IF(A39="","",(L39-AV39))
A40: 250 | B40: 200 | C40: 47.6 | F40: HA | G40: 7 | K40: =IF($N$4="M",IF(A40="","",IF(D40=6,16,IF(A40<=$M$5,26,IF(A40<=$M$6,24,IF(A40<=$M$7,22,IF(A40<=$M$8,20,18)))))),IF(A40="","",IF(D40=6,16,IF(A40<=$P$5,26,IF(A40<=$P$6,24,IF(A40<=$P$7,22,IF(A40<=$P$8,20,18))))))) | L40: =IF($N$4="M",IF(A40="","",IF(K40=26,(A40+B40+Q40)*C40*0.02739,IF(K40=24,(A40+B40+Q40)*C40*0.02739,IF(K40=22,(A40+B40+Q40)*C40*0.0333,IF(K40=20,(A40+B40+Q40)*C40*0.0393,IF(K40=18,(A40+B40+Q40)*C40*0.0511,IF(K40=16,(A40+B40+Q40)*C40*0.0628))))))),IF(A40="","",IF(K40=26,(A40+B40+Q40)*C40*0.211,IF(K40=24,(A40+B40+Q40)*C40*0.211,IF(K40=22,(A40+B40+Q40)*C40*0.258,IF(K40=20,(A40+B40+Q40)*C40*0.304,IF(K40=18,(A40+B40+Q40)*C40*0.395,IF(K40=16,(A40+B40+Q40)*C40*0.487)))))))) | M40: =IF(D40=1,0.5,IF(D40=2,"1 F",IF(D40=21,"1 R",IF(D40=3,2,"")))) | N40: =IF(M40="","",IF($N$4="M",(A40+B40+Q40)*C40*0.022,(A40+B40+Q40)*C40*0.17)) | O40: =IF(D40=4,1,IF(D40=5,2,"")) | P40: =IF(O40="","",IF($N$4="M",IF(O40=1,(A40+B40+Q40)*C40*0.022*1.1,(A40+B40+Q40)*C40*0.022*1.15),IF(O40=1,(A40+B40+Q40)*C40*0.17*1.1,(A40+B40+Q40)*C40*0.17*1.15))) | Q40: =IF($N$4="M",IF(A40="","",IF(D40=1,50,IF(D40=2,100,IF(D40=21,100,IF(D40=3,200,0))))),IF(A40="","",IF(D40=1,2,IF(D40=2,4,IF(D40=21,4,IF(D40=3,8,0)))))) | R40: =COUNTIF(G40:J40,7) -> 0 | S40: =IF(A40="","",IF($N$4="M",A40*B40*0.000011111*R40*1.5,A40*B40/144*R40*1.5)) | T40: =COUNTIF(G40:J40,71) -> 0 | U40: =IF(A40="","",IF($N$4="M",A40*B40*0.000011111*T40*1.5,A40*B40/144*T40*1.5)) | V40: =COUNTIF(G40:J40,8) -> 0 | W40: =IF(A40="","",IF($N$4="M",(A40+B40)*2*0.0032808*V40,(A40+B40)*2*V40/12)) | X40: =COUNTIF(G40:J40,81) -> 0 | Y40: =IF(A40="","",IF($N$4="M",(A40+B40)*2*0.0032808*X40,(A40+B40)*2*X40/12)) | Z40: =COUNTIF(G40:J40,9) -> 0 | AA40: =COUNTIF(G40:J40,10) -> 0 | AB40: =IF(A40="","",IF($N$4="M",(A40+B40)*2*0.0032808*AA40,(A40+B40)*2*AA40/12)) | AC40: =COUNTIF(G40:J40,100) -> 0 | AE40: =COUNTIF(G40:J40,11) -> 0 | AF40: =IF(A40="","",IF($N$4="M",A40*B40*0.000011111*AE40,A40*B40/144*AE40)) | AG40: =COUNTIF(G40:J40,111) -> 0 | AH40: =IF(A40="","",IF($N$4="M",A40*B40*0.000011111*AG40,A40*B40/144*AG40)) | AI40: =COUNTIF(G40:J40,12) -> 0 | AJ40: =IF(A40="","",IF($N$4="M",A40*B40*0.000011111*AI40,A40*B40/144*AI40)) | AK40: =COUNTIF(G40:J40,13) -> 0 | AL40: =COUNTIF(G40:J40,131) -> 0 | AM40: =IF(A40="","",IF($N$4="M",A40*B40*0.000011111*AL40,A40*B40/144*AL40)) | AN40: =COUNTIF(G40:J40,14) -> 0 | AO40: =IF(A40="","",IF($N$4="M",A40*B40*0.000011111*AN40,A40*B40/144*AN40)) | AP40: =COUNTIF(G40:J40,141) -> 0 | AQ40: =IF(A40="","",IF($N$4="M",A40*B40*0.000011111*AP40,A40*B40/144*AP40)) | AR40: =COUNTIF(G40:J40,15) -> 0 | AS40: =COUNTIF(G40:J40,16) -> 0 | AT40: =IF(A40="","",IF($N$4="M",A40*B40*0.000011111*AS40,A40*B40/144*AS40)) | AU40: =IF(D40=61,C40,0) -> 0 | AV40: =IF(D40=61,L40,0) -> 0 | AW40: =IF(A40="","",(C40-AU40)) | AX40: =IF(A40="","",(L40-AV40))
A41: 250 | B41: 250 | C41: 37.2 | F41: HA | K41: =IF($N$4="M",IF(A41="","",IF(D41=6,16,IF(A41<=$M$5,26,IF(A41<=$M$6,24,IF(A41<=$M$7,22,IF(A41<=$M$8,20,18)))))),IF(A41="","",IF(D41=6,16,IF(A41<=$P$5,26,IF(A41<=$P$6,24,IF(A41<=$P$7,22,IF(A41<=$P$8,20,18))))))) | L41: =IF($N$4="M",IF(A41="","",IF(K41=26,(A41+B41+Q41)*C41*0.02739,IF(K41=24,(A41+B41+Q41)*C41*0.02739,IF(K41=22,(A41+B41+Q41)*C41*0.0333,IF(K41=20,(A41+B41+Q41)*C41*0.0393,IF(K41=18,(A41+B41+Q41)*C41*0.0511,IF(K41=16,(A41+B41+Q41)*C41*0.0628))))))),IF(A41="","",IF(K41=26,(A41+B41+Q41)*C41*0.211,IF(K41=24,(A41+B41+Q41)*C41*0.211,IF(K41=22,(A41+B41+Q41)*C41*0.258,IF(K41=20,(A41+B41+Q41)*C41*0.304,IF(K41=18,(A41+B41+Q41)*C41*0.395,IF(K41=16,(A41+B41+Q41)*C41*0.487)))))))) | M41: =IF(D41=1,0.5,IF(D41=2,"1 F",IF(D41=21,"1 R",IF(D41=3,2,"")))) | N41: =IF(M41="","",IF($N$4="M",(A41+B41+Q41)*C41*0.022,(A41+B41+Q41)*C41*0.17)) | O41: =IF(D41=4,1,IF(D41=5,2,"")) | P41: =IF(O41="","",IF($N$4="M",IF(O41=1,(A41+B41+Q41)*C41*0.022*1.1,(A41+B41+Q41)*C41*0.022*1.15),IF(O41=1,(A41+B41+Q41)*C41*0.17*1.1,(A41+B41+Q41)*C41*0.17*1.15))) | Q41: =IF($N$4="M",IF(A41="","",IF(D41=1,50,IF(D41=2,100,IF(D41=21,100,IF(D41=3,200,0))))),IF(A41="","",IF(D41=1,2,IF(D41=2,4,IF(D41=21,4,IF(D41=3,8,0)))))) | R41: =COUNTIF(G41:J41,7) -> 0 | S41: =IF(A41="","",IF($N$4="M",A41*B41*0.000011111*R41*1.5,A41*B41/144*R41*1.5)) | T41: =COUNTIF(G41:J41,71) -> 0 | U41: =IF(A41="","",IF($N$4="M",A41*B41*0.000011111*T41*1.5,A41*B41/144*T41*1.5)) | V41: =COUNTIF(G41:J41,8) -> 0 | W41: =IF(A41="","",IF($N$4="M",(A41+B41)*2*0.0032808*V41,(A41+B41)*2*V41/12)) | X41: =COUNTIF(G41:J41,81) -> 0 | Y41: =IF(A41="","",IF($N$4="M",(A41+B41)*2*0.0032808*X41,(A41+B41)*2*X41/12)) | Z41: =COUNTIF(G41:J41,9) -> 0 | AA41: =COUNTIF(G41:J41,10) -> 0 | AB41: =IF(A41="","",IF($N$4="M",(A41+B41)*2*0.0032808*AA41,(A41+B41)*2*AA41/12)) | AC41: =COUNTIF(G41:J41,100) -> 0 | AE41: =COUNTIF(G41:J41,11) -> 0 | AF41: =IF(A41="","",IF($N$4="M",A41*B41*0.000011111*AE41,A41*B41/144*AE41)) | AG41: =COUNTIF(G41:J41,111) -> 0 | AH41: =IF(A41="","",IF($N$4="M",A41*B41*0.000011111*AG41,A41*B41/144*AG41)) | AI41: =COUNTIF(G41:J41,12) -> 0 | AJ41: =IF(A41="","",IF($N$4="M",A41*B41*0.000011111*AI41,A41*B41/144*AI41)) | AK41: =COUNTIF(G41:J41,13) -> 0 | AL41: =COUNTIF(G41:J41,131) -> 0 | AM41: =IF(A41="","",IF($N$4="M",A41*B41*0.000011111*AL41,A41*B41/144*AL41)) | AN41: =COUNTIF(G41:J41,14) -> 0 | AO41: =IF(A41="","",IF($N$4="M",A41*B41*0.000011111*AN41,A41*B41/144*AN41)) | AP41: =COUNTIF(G41:J41,141) -> 0 | AQ41: =IF(A41="","",IF($N$4="M",A41*B41*0.000011111*AP41,A41*B41/144*AP41)) | AR41: =COUNTIF(G41:J41,15) -> 0 | AS41: =COUNTIF(G41:J41,16) -> 0 | AT41: =IF(A41="","",IF($N$4="M",A41*B41*0.000011111*AS41,A41*B41/144*AS41)) | AU41: =IF(D41=61,C41,0) -> 0 | AV41: =IF(D41=61,L41,0) -> 0 | AW41: =IF(A41="","",(C41-AU41)) | AX41: =IF(A41="","",(L41-AV41))
A42: 250 | B42: 250 | C42: 7.9 | F42: HA | G42: 21 | K42: =IF($N$4="M",IF(A42="","",IF(D42=6,16,IF(A42<=$M$5,26,IF(A42<=$M$6,24,IF(A42<=$M$7,22,IF(A42<=$M$8,20,18)))))),IF(A42="","",IF(D42=6,16,IF(A42<=$P$5,26,IF(A42<=$P$6,24,IF(A42<=$P$7,22,IF(A42<=$P$8,20,18))))))) | L42: =IF($N$4="M",IF(A42="","",IF(K42=26,(A42+B42+Q42)*C42*0.02739,IF(K42=24,(A42+B42+Q42)*C42*0.02739,IF(K42=22,(A42+B42+Q42)*C42*0.0333,IF(K42=20,(A42+B42+Q42)*C42*0.0393,IF(K42=18,(A42+B42+Q42)*C42*0.0511,IF(K42=16,(A42+B42+Q42)*C42*0.0628))))))),IF(A42="","",IF(K42=26,(A42+B42+Q42)*C42*0.211,IF(K42=24,(A42+B42+Q42)*C42*0.211,IF(K42=22,(A42+B42+Q42)*C42*0.258,IF(K42=20,(A42+B42+Q42)*C42*0.304,IF(K42=18,(A42+B42+Q42)*C42*0.395,IF(K42=16,(A42+B42+Q42)*C42*0.487)))))))) | M42: =IF(D42=1,0.5,IF(D42=2,"1 F",IF(D42=21,"1 R",IF(D42=3,2,"")))) | N42: =IF(M42="","",IF($N$4="M",(A42+B42+Q42)*C42*0.022,(A42+B42+Q42)*C42*0.17)) | O42: =IF(D42=4,1,IF(D42=5,2,"")) | P42: =IF(O42="","",IF($N$4="M",IF(O42=1,(A42+B42+Q42)*C42*0.022*1.1,(A42+B42+Q42)*C42*0.022*1.15),IF(O42=1,(A42+B42+Q42)*C42*0.17*1.1,(A42+B42+Q42)*C42*0.17*1.15))) | Q42: =IF($N$4="M",IF(A42="","",IF(D42=1,50,IF(D42=2,100,IF(D42=21,100,IF(D42=3,200,0))))),IF(A42="","",IF(D42=1,2,IF(D42=2,4,IF(D42=21,4,IF(D42=3,8,0)))))) | R42: =COUNTIF(G42:J42,7) -> 0 | S42: =IF(A42="","",IF($N$4="M",A42*B42*0.000011111*R42*1.5,A42*B42/144*R42*1.5)) | T42: =COUNTIF(G42:J42,71) -> 0 | U42: =IF(A42="","",IF($N$4="M",A42*B42*0.000011111*T42*1.5,A42*B42/144*T42*1.5)) | V42: =COUNTIF(G42:J42,8) -> 0 | W42: =IF(A42="","",IF($N$4="M",(A42+B42)*2*0.0032808*V42,(A42+B42)*2*V42/12)) | X42: =COUNTIF(G42:J42,81) -> 0 | Y42: =IF(A42="","",IF($N$4="M",(A42+B42)*2*0.0032808*X42,(A42+B42)*2*X42/12)) | Z42: =COUNTIF(G42:J42,9) -> 0 | AA42: =COUNTIF(G42:J42,10) -> 0 | AB42: =IF(A42="","",IF($N$4="M",(A42+B42)*2*0.0032808*AA42,(A42+B42)*2*AA42/12)) | AC42: =COUNTIF(G42:J42,100) -> 0 | AE42: =COUNTIF(G42:J42,11) -> 0 | AF42: =IF(A42="","",IF($N$4="M",A42*B42*0.000011111*AE42,A42*B42/144*AE42)) | AG42: =COUNTIF(G42:J42,111) -> 0 | AH42: =IF(A42="","",IF($N$4="M",A42*B42*0.000011111*AG42,A42*B42/144*AG42)) | AI42: =COUNTIF(G42:J42,12) -> 0 | AJ42: =IF(A42="","",IF($N$4="M",A42*B42*0.000011111*AI42,A42*B42/144*AI42)) | AK42: =COUNTIF(G42:J42,13) -> 0 | AL42: =COUNTIF(G42:J42,131) -> 0 | AM42: =IF(A42="","",IF($N$4="M",A42*B42*0.000011111*AL42,A42*B42/144*AL42)) | AN42: =COUNTIF(G42:J42,14) -> 0 | AO42: =IF(A42="","",IF($N$4="M",A42*B42*0.000011111*AN42,A42*B42/144*AN42)) | AP42: =COUNTIF(G42:J42,141) -> 0 | AQ42: =IF(A42="","",IF($N$4="M",A42*B42*0.000011111*AP42,A42*B42/144*AP42)) | AR42: =COUNTIF(G42:J42,15) -> 0 | AS42: =COUNTIF(G42:J42,16) -> 0 | AT42: =IF(A42="","",IF($N$4="M",A42*B42*0.000011111*AS42,A42*B42/144*AS42)) | AU42: =IF(D42=61,C42,0) -> 0 | AV42: =IF(D42=61,L42,0) -> 0 | AW42: =IF(A42="","",(C42-AU42)) | AX42: =IF(A42="","",(L42-AV42))
A43: 250 | B43: 250 | C43: 6.6 | D43: 6 | E43: HP | F43: HA | K43: =IF($N$4="M",IF(A43="","",IF(D43=6,16,IF(A43<=$M$5,26,IF(A43<=$M$6,24,IF(A43<=$M$7,22,IF(A43<=$M$8,20,18)))))),IF(A43="","",IF(D43=6,16,IF(A43<=$P$5,26,IF(A43<=$P$6,24,IF(A43<=$P$7,22,IF(A43<=$P$8,20,18))))))) | L43: =IF($N$4="M",IF(A43="","",IF(K43=26,(A43+B43+Q43)*C43*0.02739,IF(K43=24,(A43+B43+Q43)*C43*0.02739,IF(K43=22,(A43+B43+Q43)*C43*0.0333,IF(K43=20,(A43+B43+Q43)*C43*0.0393,IF(K43=18,(A43+B43+Q43)*C43*0.0511,IF(K43=16,(A43+B43+Q43)*C43*0.0628))))))),IF(A43="","",IF(K43=26,(A43+B43+Q43)*C43*0.211,IF(K43=24,(A43+B43+Q43)*C43*0.211,IF(K43=22,(A43+B43+Q43)*C43*0.258,IF(K43=20,(A43+B43+Q43)*C43*0.304,IF(K43=18,(A43+B43+Q43)*C43*0.395,IF(K43=16,(A43+B43+Q43)*C43*0.487)))))))) | M43: =IF(D43=1,0.5,IF(D43=2,"1 F",IF(D43=21,"1 R",IF(D43=3,2,"")))) | N43: =IF(M43="","",IF($N$4="M",(A43+B43+Q43)*C43*0.022,(A43+B43+Q43)*C43*0.17)) | O43: =IF(D43=4,1,IF(D43=5,2,"")) | P43: =IF(O43="","",IF($N$4="M",IF(O43=1,(A43+B43+Q43)*C43*0.022*1.1,(A43+B43+Q43)*C43*0.022*1.15),IF(O43=1,(A43+B43+Q43)*C43*0.17*1.1,(A43+B43+Q43)*C43*0.17*1.15))) | Q43: =IF($N$4="M",IF(A43="","",IF(D43=1,50,IF(D43=2,100,IF(D43=21,100,IF(D43=3,200,0))))),IF(A43="","",IF(D43=1,2,IF(D43=2,4,IF(D43=21,4,IF(D43=3,8,0)))))) | R43: =COUNTIF(G43:J43,7) -> 0 | S43: =IF(A43="","",IF($N$4="M",A43*B43*0.000011111*R43*1.5,A43*B43/144*R43*1.5)) | T43: =COUNTIF(G43:J43,71) -> 0 | U43: =IF(A43="","",IF($N$4="M",A43*B43*0.000011111*T43*1.5,A43*B43/144*T43*1.5)) | V43: =COUNTIF(G43:J43,8) -> 0 | W43: =IF(A43="","",IF($N$4="M",(A43+B43)*2*0.0032808*V43,(A43+B43)*2*V43/12)) | X43: =COUNTIF(G43:J43,81) -> 0 | Y43: =IF(A43="","",IF($N$4="M",(A43+B43)*2*0.0032808*X43,(A43+B43)*2*X43/12)) | Z43: =COUNTIF(G43:J43,9) -> 0 | AA43: =COUNTIF(G43:J43,10) -> 0 | AB43: =IF(A43="","",IF($N$4="M",(A43+B43)*2*0.0032808*AA43,(A43+B43)*2*AA43/12)) | AC43: =COUNTIF(G43:J43,100) -> 0 | AE43: =COUNTIF(G43:J43,11) -> 0 | AF43: =IF(A43="","",IF($N$4="M",A43*B43*0.000011111*AE43,A43*B43/144*AE43)) | AG43: =COUNTIF(G43:J43,111) -> 0 | AH43: =IF(A43="","",IF($N$4="M",A43*B43*0.000011111*AG43,A43*B43/144*AG43)) | AI43: =COUNTIF(G43:J43,12) -> 0 | AJ43: =IF(A43="","",IF($N$4="M",A43*B43*0.000011111*AI43,A43*B43/144*AI43)) | AK43: =COUNTIF(G43:J43,13) -> 0 | AL43: =COUNTIF(G43:J43,131) -> 0 | AM43: =IF(A43="","",IF($N$4="M",A43*B43*0.000011111*AL43,A43*B43/144*AL43)) | AN43: =COUNTIF(G43:J43,14) -> 0 | AO43: =IF(A43="","",IF($N$4="M",A43*B43*0.000011111*AN43,A43*B43/144*AN43)) | AP43: =COUNTIF(G43:J43,141) -> 0 | AQ43: =IF(A43="","",IF($N$4="M",A43*B43*0.000011111*AP43,A43*B43/144*AP43)) | AR43: =COUNTIF(G43:J43,15) -> 0 | AS43: =COUNTIF(G43:J43,16) -> 0 | AT43: =IF(A43="","",IF($N$4="M",A43*B43*0.000011111*AS43,A43*B43/144*AS43)) | AU43: =IF(D43=61,C43,0) -> 0 | AV43: =IF(D43=61,L43,0) -> 0 | AW43: =IF(A43="","",(C43-AU43)) | AX43: =IF(A43="","",(L43-AV43))
A44: 300 | B44: 200 | C44: 6.3 | F44: HA | K44: =IF($N$4="M",IF(A44="","",IF(D44=6,16,IF(A44<=$M$5,26,IF(A44<=$M$6,24,IF(A44<=$M$7,22,IF(A44<=$M$8,20,18)))))),IF(A44="","",IF(D44=6,16,IF(A44<=$P$5,26,IF(A44<=$P$6,24,IF(A44<=$P$7,22,IF(A44<=$P$8,20,18))))))) | L44: =IF($N$4="M",IF(A44="","",IF(K44=26,(A44+B44+Q44)*C44*0.02739,IF(K44=24,(A44+B44+Q44)*C44*0.02739,IF(K44=22,(A44+B44+Q44)*C44*0.0333,IF(K44=20,(A44+B44+Q44)*C44*0.0393,IF(K44=18,(A44+B44+Q44)*C44*0.0511,IF(K44=16,(A44+B44+Q44)*C44*0.0628))))))),IF(A44="","",IF(K44=26,(A44+B44+Q44)*C44*0.211,IF(K44=24,(A44+B44+Q44)*C44*0.211,IF(K44=22,(A44+B44+Q44)*C44*0.258,IF(K44=20,(A44+B44+Q44)*C44*0.304,IF(K44=18,(A44+B44+Q44)*C44*0.395,IF(K44=16,(A44+B44+Q44)*C44*0.487)))))))) | M44: =IF(D44=1,0.5,IF(D44=2,"1 F",IF(D44=21,"1 R",IF(D44=3,2,"")))) | N44: =IF(M44="","",IF($N$4="M",(A44+B44+Q44)*C44*0.022,(A44+B44+Q44)*C44*0.17)) | O44: =IF(D44=4,1,IF(D44=5,2,"")) | P44: =IF(O44="","",IF($N$4="M",IF(O44=1,(A44+B44+Q44)*C44*0.022*1.1,(A44+B44+Q44)*C44*0.022*1.15),IF(O44=1,(A44+B44+Q44)*C44*0.17*1.1,(A44+B44+Q44)*C44*0.17*1.15))) | Q44: =IF($N$4="M",IF(A44="","",IF(D44=1,50,IF(D44=2,100,IF(D44=21,100,IF(D44=3,200,0))))),IF(A44="","",IF(D44=1,2,IF(D44=2,4,IF(D44=21,4,IF(D44=3,8,0)))))) | R44: =COUNTIF(G44:J44,7) -> 0 | S44: =IF(A44="","",IF($N$4="M",A44*B44*0.000011111*R44*1.5,A44*B44/144*R44*1.5)) | T44: =COUNTIF(G44:J44,71) -> 0 | U44: =IF(A44="","",IF($N$4="M",A44*B44*0.000011111*T44*1.5,A44*B44/144*T44*1.5)) | V44: =COUNTIF(G44:J44,8) -> 0 | W44: =IF(A44="","",IF($N$4="M",(A44+B44)*2*0.0032808*V44,(A44+B44)*2*V44/12)) | X44: =COUNTIF(G44:J44,81) -> 0 | Y44: =IF(A44="","",IF($N$4="M",(A44+B44)*2*0.0032808*X44,(A44+B44)*2*X44/12)) | Z44: =COUNTIF(G44:J44,9) -> 0 | AA44: =COUNTIF(G44:J44,10) -> 0 | AB44: =IF(A44="","",IF($N$4="M",(A44+B44)*2*0.0032808*AA44,(A44+B44)*2*AA44/12)) | AC44: =COUNTIF(G44:J44,100) -> 0 | AE44: =COUNTIF(G44:J44,11) -> 0 | AF44: =IF(A44="","",IF($N$4="M",A44*B44*0.000011111*AE44,A44*B44/144*AE44)) | AG44: =COUNTIF(G44:J44,111) -> 0 | AH44: =IF(A44="","",IF($N$4="M",A44*B44*0.000011111*AG44,A44*B44/144*AG44)) | AI44: =COUNTIF(G44:J44,12) -> 0 | AJ44: =IF(A44="","",IF($N$4="M",A44*B44*0.000011111*AI44,A44*B44/144*AI44)) | AK44: =COUNTIF(G44:J44,13) -> 0 | AL44: =COUNTIF(G44:J44,131) -> 0 | AM44: =IF(A44="","",IF($N$4="M",A44*B44*0.000011111*AL44,A44*B44/144*AL44)) | AN44: =COUNTIF(G44:J44,14) -> 0 | AO44: =IF(A44="","",IF($N$4="M",A44*B44*0.000011111*AN44,A44*B44/144*AN44)) | AP44: =COUNTIF(G44:J44,141) -> 0 | AQ44: =IF(A44="","",IF($N$4="M",A44*B44*0.000011111*AP44,A44*B44/144*AP44)) | AR44: =COUNTIF(G44:J44,15) -> 0 | AS44: =COUNTIF(G44:J44,16) -> 0 | AT44: =IF(A44="","",IF($N$4="M",A44*B44*0.000011111*AS44,A44*B44/144*AS44)) | AU44: =IF(D44=61,C44,0) -> 0 | AV44: =IF(D44=61,L44,0) -> 0 | AW44: =IF(A44="","",(C44-AU44)) | AX44: =IF(A44="","",(L44-AV44))
A45: 300 | B45: 200 | C45: 5 | D45: 6 | E45: HP | F45: HA | K45: =IF($N$4="M",IF(A45="","",IF(D45=6,16,IF(A45<=$M$5,26,IF(A45<=$M$6,24,IF(A45<=$M$7,22,IF(A45<=$M$8,20,18)))))),IF(A45="","",IF(D45=6,16,IF(A45<=$P$5,26,IF(A45<=$P$6,24,IF(A45<=$P$7,22,IF(A45<=$P$8,20,18))))))) | L45: =IF($N$4="M",IF(A45="","",IF(K45=26,(A45+B45+Q45)*C45*0.02739,IF(K45=24,(A45+B45+Q45)*C45*0.02739,IF(K45=22,(A45+B45+Q45)*C45*0.0333,IF(K45=20,(A45+B45+Q45)*C45*0.0393,IF(K45=18,(A45+B45+Q45)*C45*0.0511,IF(K45=16,(A45+B45+Q45)*C45*0.0628))))))),IF(A45="","",IF(K45=26,(A45+B45+Q45)*C45*0.211,IF(K45=24,(A45+B45+Q45)*C45*0.211,IF(K45=22,(A45+B45+Q45)*C45*0.258,IF(K45=20,(A45+B45+Q45)*C45*0.304,IF(K45=18,(A45+B45+Q45)*C45*0.395,IF(K45=16,(A45+B45+Q45)*C45*0.487)))))))) | M45: =IF(D45=1,0.5,IF(D45=2,"1 F",IF(D45=21,"1 R",IF(D45=3,2,"")))) | N45: =IF(M45="","",IF($N$4="M",(A45+B45+Q45)*C45*0.022,(A45+B45+Q45)*C45*0.17)) | O45: =IF(D45=4,1,IF(D45=5,2,"")) | P45: =IF(O45="","",IF($N$4="M",IF(O45=1,(A45+B45+Q45)*C45*0.022*1.1,(A45+B45+Q45)*C45*0.022*1.15),IF(O45=1,(A45+B45+Q45)*C45*0.17*1.1,(A45+B45+Q45)*C45*0.17*1.15))) | Q45: =IF($N$4="M",IF(A45="","",IF(D45=1,50,IF(D45=2,100,IF(D45=21,100,IF(D45=3,200,0))))),IF(A45="","",IF(D45=1,2,IF(D45=2,4,IF(D45=21,4,IF(D45=3,8,0)))))) | R45: =COUNTIF(G45:J45,7) -> 0 | S45: =IF(A45="","",IF($N$4="M",A45*B45*0.000011111*R45*1.5,A45*B45/144*R45*1.5)) | T45: =COUNTIF(G45:J45,71) -> 0 | U45: =IF(A45="","",IF($N$4="M",A45*B45*0.000011111*T45*1.5,A45*B45/144*T45*1.5)) | V45: =COUNTIF(G45:J45,8) -> 0 | W45: =IF(A45="","",IF($N$4="M",(A45+B45)*2*0.0032808*V45,(A45+B45)*2*V45/12)) | X45: =COUNTIF(G45:J45,81) -> 0 | Y45: =IF(A45="","",IF($N$4="M",(A45+B45)*2*0.0032808*X45,(A45+B45)*2*X45/12)) | Z45: =COUNTIF(G45:J45,9) -> 0 | AA45: =COUNTIF(G45:J45,10) -> 0 | AB45: =IF(A45="","",IF($N$4="M",(A45+B45)*2*0.0032808*AA45,(A45+B45)*2*AA45/12)) | AC45: =COUNTIF(G45:J45,100) -> 0 | AE45: =COUNTIF(G45:J45,11) -> 0 | AF45: =IF(A45="","",IF($N$4="M",A45*B45*0.000011111*AE45,A45*B45/144*AE45)) | AG45: =COUNTIF(G45:J45,111) -> 0 | AH45: =IF(A45="","",IF($N$4="M",A45*B45*0.000011111*AG45,A45*B45/144*AG45)) | AI45: =COUNTIF(G45:J45,12) -> 0 | AJ45: =IF(A45="","",IF($N$4="M",A45*B45*0.000011111*AI45,A45*B45/144*AI45)) | AK45: =COUNTIF(G45:J45,13) -> 0 | AL45: =COUNTIF(G45:J45,131) -> 0 | AM45: =IF(A45="","",IF($N$4="M",A45*B45*0.000011111*AL45,A45*B45/144*AL45)) | AN45: =COUNTIF(G45:J45,14) -> 0 | AO45: =IF(A45="","",IF($N$4="M",A45*B45*0.000011111*AN45,A45*B45/144*AN45)) | AP45: =COUNTIF(G45:J45,141) -> 0 | AQ45: =IF(A45="","",IF($N$4="M",A45*B45*0.000011111*AP45,A45*B45/144*AP45)) | AR45: =COUNTIF(G45:J45,15) -> 0 | AS45: =COUNTIF(G45:J45,16) -> 0 | AT45: =IF(A45="","",IF($N$4="M",A45*B45*0.000011111*AS45,A45*B45/144*AS45)) | AU45: =IF(D45=61,C45,0) -> 0 | AV45: =IF(D45=61,L45,0) -> 0 | AW45: =IF(A45="","",(C45-AU45)) | AX45: =IF(A45="","",(L45-AV45))
A46: 300 | B46: 250 | C46: 3.4 | F46: HA | K46: =IF($N$4="M",IF(A46="","",IF(D46=6,16,IF(A46<=$M$5,26,IF(A46<=$M$6,24,IF(A46<=$M$7,22,IF(A46<=$M$8,20,18)))))),IF(A46="","",IF(D46=6,16,IF(A46<=$P$5,26,IF(A46<=$P$6,24,IF(A46<=$P$7,22,IF(A46<=$P$8,20,18))))))) | L46: =IF($N$4="M",IF(A46="","",IF(K46=26,(A46+B46+Q46)*C46*0.02739,IF(K46=24,(A46+B46+Q46)*C46*0.02739,IF(K46=22,(A46+B46+Q46)*C46*0.0333,IF(K46=20,(A46+B46+Q46)*C46*0.0393,IF(K46=18,(A46+B46+Q46)*C46*0.0511,IF(K46=16,(A46+B46+Q46)*C46*0.0628))))))),IF(A46="","",IF(K46=26,(A46+B46+Q46)*C46*0.211,IF(K46=24,(A46+B46+Q46)*C46*0.211,IF(K46=22,(A46+B46+Q46)*C46*0.258,IF(K46=20,(A46+B46+Q46)*C46*0.304,IF(K46=18,(A46+B46+Q46)*C46*0.395,IF(K46=16,(A46+B46+Q46)*C46*0.487)))))))) | M46: =IF(D46=1,0.5,IF(D46=2,"1 F",IF(D46=21,"1 R",IF(D46=3,2,"")))) | N46: =IF(M46="","",IF($N$4="M",(A46+B46+Q46)*C46*0.022,(A46+B46+Q46)*C46*0.17)) | O46: =IF(D46=4,1,IF(D46=5,2,"")) | P46: =IF(O46="","",IF($N$4="M",IF(O46=1,(A46+B46+Q46)*C46*0.022*1.1,(A46+B46+Q46)*C46*0.022*1.15),IF(O46=1,(A46+B46+Q46)*C46*0.17*1.1,(A46+B46+Q46)*C46*0.17*1.15))) | Q46: =IF($N$4="M",IF(A46="","",IF(D46=1,50,IF(D46=2,100,IF(D46=21,100,IF(D46=3,200,0))))),IF(A46="","",IF(D46=1,2,IF(D46=2,4,IF(D46=21,4,IF(D46=3,8,0)))))) | R46: =COUNTIF(G46:J46,7) -> 0 | S46: =IF(A46="","",IF($N$4="M",A46*B46*0.000011111*R46*1.5,A46*B46/144*R46*1.5)) | T46: =COUNTIF(G46:J46,71) -> 0 | U46: =IF(A46="","",IF($N$4="M",A46*B46*0.000011111*T46*1.5,A46*B46/144*T46*1.5)) | V46: =COUNTIF(G46:J46,8) -> 0 | W46: =IF(A46="","",IF($N$4="M",(A46+B46)*2*0.0032808*V46,(A46+B46)*2*V46/12)) | X46: =COUNTIF(G46:J46,81) -> 0 | Y46: =IF(A46="","",IF($N$4="M",(A46+B46)*2*0.0032808*X46,(A46+B46)*2*X46/12)) | Z46: =COUNTIF(G46:J46,9) -> 0 | AA46: =COUNTIF(G46:J46,10) -> 0 | AB46: =IF(A46="","",IF($N$4="M",(A46+B46)*2*0.0032808*AA46,(A46+B46)*2*AA46/12)) | AC46: =COUNTIF(G46:J46,100) -> 0 | AE46: =COUNTIF(G46:J46,11) -> 0 | AF46: =IF(A46="","",IF($N$4="M",A46*B46*0.000011111*AE46,A46*B46/144*AE46)) | AG46: =COUNTIF(G46:J46,111) -> 0 | AH46: =IF(A46="","",IF($N$4="M",A46*B46*0.000011111*AG46,A46*B46/144*AG46)) | AI46: =COUNTIF(G46:J46,12) -> 0 | AJ46: =IF(A46="","",IF($N$4="M",A46*B46*0.000011111*AI46,A46*B46/144*AI46)) | AK46: =COUNTIF(G46:J46,13) -> 0 | AL46: =COUNTIF(G46:J46,131) -> 0 | AM46: =IF(A46="","",IF($N$4="M",A46*B46*0.000011111*AL46,A46*B46/144*AL46)) | AN46: =COUNTIF(G46:J46,14) -> 0 | AO46: =IF(A46="","",IF($N$4="M",A46*B46*0.000011111*AN46,A46*B46/144*AN46)) | AP46: =COUNTIF(G46:J46,141) -> 0 | AQ46: =IF(A46="","",IF($N$4="M",A46*B46*0.000011111*AP46,A46*B46/144*AP46)) | AR46: =COUNTIF(G46:J46,15) -> 0 | AS46: =COUNTIF(G46:J46,16) -> 0 | AT46: =IF(A46="","",IF($N$4="M",A46*B46*0.000011111*AS46,A46*B46/144*AS46)) | AU46: =IF(D46=61,C46,0) -> 0 | AV46: =IF(D46=61,L46,0) -> 0 | AW46: =IF(A46="","",(C46-AU46)) | AX46: =IF(A46="","",(L46-AV46))
A47: 300 | B47: 300 | C47: 87.9 | F47: HA | G47: 10 | H47: 10 | I47: 7 | K47: =IF($N$4="M",IF(A47="","",IF(D47=6,16,IF(A47<=$M$5,26,IF(A47<=$M$6,24,IF(A47<=$M$7,22,IF(A47<=$M$8,20,18)))))),IF(A47="","",IF(D47=6,16,IF(A47<=$P$5,26,IF(A47<=$P$6,24,IF(A47<=$P$7,22,IF(A47<=$P$8,20,18))))))) | L47: =IF($N$4="M",IF(A47="","",IF(K47=26,(A47+B47+Q47)*C47*0.02739,IF(K47=24,(A47+B47+Q47)*C47*0.02739,IF(K47=22,(A47+B47+Q47)*C47*0.0333,IF(K47=20,(A47+B47+Q47)*C47*0.0393,IF(K47=18,(A47+B47+Q47)*C47*0.0511,IF(K47=16,(A47+B47+Q47)*C47*0.0628))))))),IF(A47="","",IF(K47=26,(A47+B47+Q47)*C47*0.211,IF(K47=24,(A47+B47+Q47)*C47*0.211,IF(K47=22,(A47+B47+Q47)*C47*0.258,IF(K47=20,(A47+B47+Q47)*C47*0.304,IF(K47=18,(A47+B47+Q47)*C47*0.395,IF(K47=16,(A47+B47+Q47)*C47*0.487)))))))) | M47: =IF(D47=1,0.5,IF(D47=2,"1 F",IF(D47=21,"1 R",IF(D47=3,2,"")))) | N47: =IF(M47="","",IF($N$4="M",(A47+B47+Q47)*C47*0.022,(A47+B47+Q47)*C47*0.17)) | O47: =IF(D47=4,1,IF(D47=5,2,"")) | P47: =IF(O47="","",IF($N$4="M",IF(O47=1,(A47+B47+Q47)*C47*0.022*1.1,(A47+B47+Q47)*C47*0.022*1.15),IF(O47=1,(A47+B47+Q47)*C47*0.17*1.1,(A47+B47+Q47)*C47*0.17*1.15))) | Q47: =IF($N$4="M",IF(A47="","",IF(D47=1,50,IF(D47=2,100,IF(D47=21,100,IF(D47=3,200,0))))),IF(A47="","",IF(D47=1,2,IF(D47=2,4,IF(D47=21,4,IF(D47=3,8,0)))))) | R47: =COUNTIF(G47:J47,7) -> 0 | S47: =IF(A47="","",IF($N$4="M",A47*B47*0.000011111*R47*1.5,A47*B47/144*R47*1.5)) | T47: =COUNTIF(G47:J47,71) -> 0 | U47: =IF(A47="","",IF($N$4="M",A47*B47*0.000011111*T47*1.5,A47*B47/144*T47*1.5)) | V47: =COUNTIF(G47:J47,8) -> 0 | W47: =IF(A47="","",IF($N$4="M",(A47+B47)*2*0.0032808*V47,(A47+B47)*2*V47/12)) | X47: =COUNTIF(G47:J47,81) -> 0 | Y47: =IF(A47="","",IF($N$4="M",(A47+B47)*2*0.0032808*X47,(A47+B47)*2*X47/12)) | Z47: =COUNTIF(G47:J47,9) -> 0 | AA47: =COUNTIF(G47:J47,10) -> 0 | AB47: =IF(A47="","",IF($N$4="M",(A47+B47)*2*0.0032808*AA47,(A47+B47)*2*AA47/12)) | AC47: =COUNTIF(G47:J47,100) -> 0 | AE47: =COUNTIF(G47:J47,11) -> 0 | AF47: =IF(A47="","",IF($N$4="M",A47*B47*0.000011111*AE47,A47*B47/144*AE47)) | AG47: =COUNTIF(G47:J47,111) -> 0 | AH47: =IF(A47="","",IF($N$4="M",A47*B47*0.000011111*AG47,A47*B47/144*AG47)) | AI47: =COUNTIF(G47:J47,12) -> 0 | AJ47: =IF(A47="","",IF($N$4="M",A47*B47*0.000011111*AI47,A47*B47/144*AI47)) | AK47: =COUNTIF(G47:J47,13) -> 0 | AL47: =COUNTIF(G47:J47,131) -> 0 | AM47: =IF(A47="","",IF($N$4="M",A47*B47*0.000011111*AL47,A47*B47/144*AL47)) | AN47: =COUNTIF(G47:J47,14) -> 0 | AO47: =IF(A47="","",IF($N$4="M",A47*B47*0.000011111*AN47,A47*B47/144*AN47)) | AP47: =COUNTIF(G47:J47,141) -> 0 | AQ47: =IF(A47="","",IF($N$4="M",A47*B47*0.000011111*AP47,A47*B47/144*AP47)) | AR47: =COUNTIF(G47:J47,15) -> 0 | AS47: =COUNTIF(G47:J47,16) -> 0 | AT47: =IF(A47="","",IF($N$4="M",A47*B47*0.000011111*AS47,A47*B47/144*AS47)) | AU47: =IF(D47=61,C47,0) -> 0 | AV47: =IF(D47=61,L47,0) -> 0 | AW47: =IF(A47="","",(C47-AU47)) | AX47: =IF(A47="","",(L47-AV47))
A48: 350 | B48: 250 | C48: 5.1 | F48: HA | K48: =IF($N$4="M",IF(A48="","",IF(D48=6,16,IF(A48<=$M$5,26,IF(A48<=$M$6,24,IF(A48<=$M$7,22,IF(A48<=$M$8,20,18)))))),IF(A48="","",IF(D48=6,16,IF(A48<=$P$5,26,IF(A48<=$P$6,24,IF(A48<=$P$7,22,IF(A48<=$P$8,20,18))))))) | L48: =IF($N$4="M",IF(A48="","",IF(K48=26,(A48+B48+Q48)*C48*0.02739,IF(K48=24,(A48+B48+Q48)*C48*0.02739,IF(K48=22,(A48+B48+Q48)*C48*0.0333,IF(K48=20,(A48+B48+Q48)*C48*0.0393,IF(K48=18,(A48+B48+Q48)*C48*0.0511,IF(K48=16,(A48+B48+Q48)*C48*0.0628))))))),IF(A48="","",IF(K48=26,(A48+B48+Q48)*C48*0.211,IF(K48=24,(A48+B48+Q48)*C48*0.211,IF(K48=22,(A48+B48+Q48)*C48*0.258,IF(K48=20,(A48+B48+Q48)*C48*0.304,IF(K48=18,(A48+B48+Q48)*C48*0.395,IF(K48=16,(A48+B48+Q48)*C48*0.487)))))))) | M48: =IF(D48=1,0.5,IF(D48=2,"1 F",IF(D48=21,"1 R",IF(D48=3,2,"")))) | N48: =IF(M48="","",IF($N$4="M",(A48+B48+Q48)*C48*0.022,(A48+B48+Q48)*C48*0.17)) | O48: =IF(D48=4,1,IF(D48=5,2,"")) | P48: =IF(O48="","",IF($N$4="M",IF(O48=1,(A48+B48+Q48)*C48*0.022*1.1,(A48+B48+Q48)*C48*0.022*1.15),IF(O48=1,(A48+B48+Q48)*C48*0.17*1.1,(A48+B48+Q48)*C48*0.17*1.15))) | Q48: =IF($N$4="M",IF(A48="","",IF(D48=1,50,IF(D48=2,100,IF(D48=21,100,IF(D48=3,200,0))))),IF(A48="","",IF(D48=1,2,IF(D48=2,4,IF(D48=21,4,IF(D48=3,8,0)))))) | R48: =COUNTIF(G48:J48,7) -> 0 | S48: =IF(A48="","",IF($N$4="M",A48*B48*0.000011111*R48*1.5,A48*B48/144*R48*1.5)) | T48: =COUNTIF(G48:J48,71) -> 0 | U48: =IF(A48="","",IF($N$4="M",A48*B48*0.000011111*T48*1.5,A48*B48/144*T48*1.5)) | V48: =COUNTIF(G48:J48,8) -> 0 | W48: =IF(A48="","",IF($N$4="M",(A48+B48)*2*0.0032808*V48,(A48+B48)*2*V48/12)) | X48: =COUNTIF(G48:J48,81) -> 0 | Y48: =IF(A48="","",IF($N$4="M",(A48+B48)*2*0.0032808*X48,(A48+B48)*2*X48/12)) | Z48: =COUNTIF(G48:J48,9) -> 0 | AA48: =COUNTIF(G48:J48,10) -> 0 | AB48: =IF(A48="","",IF($N$4="M",(A48+B48)*2*0.0032808*AA48,(A48+B48)*2*AA48/12)) | AC48: =COUNTIF(G48:J48,100) -> 0 | AE48: =COUNTIF(G48:J48,11) -> 0 | AF48: =IF(A48="","",IF($N$4="M",A48*B48*0.000011111*AE48,A48*B48/144*AE48)) | AG48: =COUNTIF(G48:J48,111) -> 0 | AH48: =IF(A48="","",IF($N$4="M",A48*B48*0.000011111*AG48,A48*B48/144*AG48)) | AI48: =COUNTIF(G48:J48,12) -> 0 | AJ48: =IF(A48="","",IF($N$4="M",A48*B48*0.000011111*AI48,A48*B48/144*AI48)) | AK48: =COUNTIF(G48:J48,13) -> 0 | AL48: =COUNTIF(G48:J48,131) -> 0 | AM48: =IF(A48="","",IF($N$4="M",A48*B48*0.000011111*AL48,A48*B48/144*AL48)) | AN48: =COUNTIF(G48:J48,14) -> 0 | AO48: =IF(A48="","",IF($N$4="M",A48*B48*0.000011111*AN48,A48*B48/144*AN48)) | AP48: =COUNTIF(G48:J48,141) -> 0 | AQ48: =IF(A48="","",IF($N$4="M",A48*B48*0.000011111*AP48,A48*B48/144*AP48)) | AR48: =COUNTIF(G48:J48,15) -> 0 | AS48: =COUNTIF(G48:J48,16) -> 0 | AT48: =IF(A48="","",IF($N$4="M",A48*B48*0.000011111*AS48,A48*B48/144*AS48)) | AU48: =IF(D48=61,C48,0) -> 0 | AV48: =IF(D48=61,L48,0) -> 0 | AW48: =IF(A48="","",(C48-AU48)) | AX48: =IF(A48="","",(L48-AV48))
A49: 350 | B49: 300 | C49: 34.1 | F49: HA | G49: 7 | K49: =IF($N$4="M",IF(A49="","",IF(D49=6,16,IF(A49<=$M$5,26,IF(A49<=$M$6,24,IF(A49<=$M$7,22,IF(A49<=$M$8,20,18)))))),IF(A49="","",IF(D49=6,16,IF(A49<=$P$5,26,IF(A49<=$P$6,24,IF(A49<=$P$7,22,IF(A49<=$P$8,20,18))))))) | L49: =IF($N$4="M",IF(A49="","",IF(K49=26,(A49+B49+Q49)*C49*0.02739,IF(K49=24,(A49+B49+Q49)*C49*0.02739,IF(K49=22,(A49+B49+Q49)*C49*0.0333,IF(K49=20,(A49+B49+Q49)*C49*0.0393,IF(K49=18,(A49+B49+Q49)*C49*0.0511,IF(K49=16,(A49+B49+Q49)*C49*0.0628))))))),IF(A49="","",IF(K49=26,(A49+B49+Q49)*C49*0.211,IF(K49=24,(A49+B49+Q49)*C49*0.211,IF(K49=22,(A49+B49+Q49)*C49*0.258,IF(K49=20,(A49+B49+Q49)*C49*0.304,IF(K49=18,(A49+B49+Q49)*C49*0.395,IF(K49=16,(A49+B49+Q49)*C49*0.487)))))))) | M49: =IF(D49=1,0.5,IF(D49=2,"1 F",IF(D49=21,"1 R",IF(D49=3,2,"")))) | N49: =IF(M49="","",IF($N$4="M",(A49+B49+Q49)*C49*0.022,(A49+B49+Q49)*C49*0.17)) | O49: =IF(D49=4,1,IF(D49=5,2,"")) | P49: =IF(O49="","",IF($N$4="M",IF(O49=1,(A49+B49+Q49)*C49*0.022*1.1,(A49+B49+Q49)*C49*0.022*1.15),IF(O49=1,(A49+B49+Q49)*C49*0.17*1.1,(A49+B49+Q49)*C49*0.17*1.15))) | Q49: =IF($N$4="M",IF(A49="","",IF(D49=1,50,IF(D49=2,100,IF(D49=21,100,IF(D49=3,200,0))))),IF(A49="","",IF(D49=1,2,IF(D49=2,4,IF(D49=21,4,IF(D49=3,8,0)))))) | R49: =COUNTIF(G49:J49,7) -> 0 | S49: =IF(A49="","",IF($N$4="M",A49*B49*0.000011111*R49*1.5,A49*B49/144*R49*1.5)) | T49: =COUNTIF(G49:J49,71) -> 0 | U49: =IF(A49="","",IF($N$4="M",A49*B49*0.000011111*T49*1.5,A49*B49/144*T49*1.5)) | V49: =COUNTIF(G49:J49,8) -> 0 | W49: =IF(A49="","",IF($N$4="M",(A49+B49)*2*0.0032808*V49,(A49+B49)*2*V49/12)) | X49: =COUNTIF(G49:J49,81) -> 0 | Y49: =IF(A49="","",IF($N$4="M",(A49+B49)*2*0.0032808*X49,(A49+B49)*2*X49/12)) | Z49: =COUNTIF(G49:J49,9) -> 0 | AA49: =COUNTIF(G49:J49,10) -> 0 | AB49: =IF(A49="","",IF($N$4="M",(A49+B49)*2*0.0032808*AA49,(A49+B49)*2*AA49/12)) | AC49: =COUNTIF(G49:J49,100) -> 0 | AE49: =COUNTIF(G49:J49,11) -> 0 | AF49: =IF(A49="","",IF($N$4="M",A49*B49*0.000011111*AE49,A49*B49/144*AE49)) | AG49: =COUNTIF(G49:J49,111) -> 0 | AH49: =IF(A49="","",IF($N$4="M",A49*B49*0.000011111*AG49,A49*B49/144*AG49)) | AI49: =COUNTIF(G49:J49,12) -> 0 | AJ49: =IF(A49="","",IF($N$4="M",A49*B49*0.000011111*AI49,A49*B49/144*AI49)) | AK49: =COUNTIF(G49:J49,13) -> 0 | AL49: =COUNTIF(G49:J49,131) -> 0 | AM49: =IF(A49="","",IF($N$4="M",A49*B49*0.000011111*AL49,A49*B49/144*AL49)) | AN49: =COUNTIF(G49:J49,14) -> 0 | AO49: =IF(A49="","",IF($N$4="M",A49*B49*0.000011111*AN49,A49*B49/144*AN49)) | AP49: =COUNTIF(G49:J49,141) -> 0 | AQ49: =IF(A49="","",IF($N$4="M",A49*B49*0.000011111*AP49,A49*B49/144*AP49)) | AR49: =COUNTIF(G49:J49,15) -> 0 | AS49: =COUNTIF(G49:J49,16) -> 0 | AT49: =IF(A49="","",IF($N$4="M",A49*B49*0.000011111*AS49,A49*B49/144*AS49)) | AU49: =IF(D49=61,C49,0) -> 0 | AV49: =IF(D49=61,L49,0) -> 0 | AW49: =IF(A49="","",(C49-AU49)) | AX49: =IF(A49="","",(L49-AV49))
A50: 400 | B50: 250 | C50: 4.2 | F50: HA | G50: 7 | H50: 13 | K50: =IF($N$4="M",IF(A50="","",IF(D50=6,16,IF(A50<=$M$5,26,IF(A50<=$M$6,24,IF(A50<=$M$7,22,IF(A50<=$M$8,20,18)))))),IF(A50="","",IF(D50=6,16,IF(A50<=$P$5,26,IF(A50<=$P$6,24,IF(A50<=$P$7,22,IF(A50<=$P$8,20,18))))))) | L50: =IF($N$4="M",IF(A50="","",IF(K50=26,(A50+B50+Q50)*C50*0.02739,IF(K50=24,(A50+B50+Q50)*C50*0.02739,IF(K50=22,(A50+B50+Q50)*C50*0.0333,IF(K50=20,(A50+B50+Q50)*C50*0.0393,IF(K50=18,(A50+B50+Q50)*C50*0.0511,IF(K50=16,(A50+B50+Q50)*C50*0.0628))))))),IF(A50="","",IF(K50=26,(A50+B50+Q50)*C50*0.211,IF(K50=24,(A50+B50+Q50)*C50*0.211,IF(K50=22,(A50+B50+Q50)*C50*0.258,IF(K50=20,(A50+B50+Q50)*C50*0.304,IF(K50=18,(A50+B50+Q50)*C50*0.395,IF(K50=16,(A50+B50+Q50)*C50*0.487)))))))) | M50: =IF(D50=1,0.5,IF(D50=2,"1 F",IF(D50=21,"1 R",IF(D50=3,2,"")))) | N50: =IF(M50="","",IF($N$4="M",(A50+B50+Q50)*C50*0.022,(A50+B50+Q50)*C50*0.17)) | O50: =IF(D50=4,1,IF(D50=5,2,"")) | P50: =IF(O50="","",IF($N$4="M",IF(O50=1,(A50+B50+Q50)*C50*0.022*1.1,(A50+B50+Q50)*C50*0.022*1.15),IF(O50=1,(A50+B50+Q50)*C50*0.17*1.1,(A50+B50+Q50)*C50*0.17*1.15))) | Q50: =IF($N$4="M",IF(A50="","",IF(D50=1,50,IF(D50=2,100,IF(D50=21,100,IF(D50=3,200,0))))),IF(A50="","",IF(D50=1,2,IF(D50=2,4,IF(D50=21,4,IF(D50=3,8,0)))))) | R50: =COUNTIF(G50:J50,7) -> 0 | S50: =IF(A50="","",IF($N$4="M",A50*B50*0.000011111*R50*1.5,A50*B50/144*R50*1.5)) | T50: =COUNTIF(G50:J50,71) -> 0 | U50: =IF(A50="","",IF($N$4="M",A50*B50*0.000011111*T50*1.5,A50*B50/144*T50*1.5)) | V50: =COUNTIF(G50:J50,8) -> 0 | W50: =IF(A50="","",IF($N$4="M",(A50+B50)*2*0.0032808*V50,(A50+B50)*2*V50/12)) | X50: =COUNTIF(G50:J50,81) -> 0 | Y50: =IF(A50="","",IF($N$4="M",(A50+B50)*2*0.0032808*X50,(A50+B50)*2*X50/12)) | Z50: =COUNTIF(G50:J50,9) -> 0 | AA50: =COUNTIF(G50:J50,10) -> 0 | AB50: =IF(A50="","",IF($N$4="M",(A50+B50)*2*0.0032808*AA50,(A50+B50)*2*AA50/12)) | AC50: =COUNTIF(G50:J50,100) -> 0 | AE50: =COUNTIF(G50:J50,11) -> 0 | AF50: =IF(A50="","",IF($N$4="M",A50*B50*0.000011111*AE50,A50*B50/144*AE50)) | AG50: =COUNTIF(G50:J50,111) -> 0 | AH50: =IF(A50="","",IF($N$4="M",A50*B50*0.000011111*AG50,A50*B50/144*AG50)) | AI50: =COUNTIF(G50:J50,12) -> 0 | AJ50: =IF(A50="","",IF($N$4="M",A50*B50*0.000011111*AI50,A50*B50/144*AI50)) | AK50: =COUNTIF(G50:J50,13) -> 0 | AL50: =COUNTIF(G50:J50,131) -> 0 | AM50: =IF(A50="","",IF($N$4="M",A50*B50*0.000011111*AL50,A50*B50/144*AL50)) | AN50: =COUNTIF(G50:J50,14) -> 0 | AO50: =IF(A50="","",IF($N$4="M",A50*B50*0.000011111*AN50,A50*B50/144*AN50)) | AP50: =COUNTIF(G50:J50,141) -> 0 | AQ50: =IF(A50="","",IF($N$4="M",A50*B50*0.000011111*AP50,A50*B50/144*AP50)) | AR50: =COUNTIF(G50:J50,15) -> 0 | AS50: =COUNTIF(G50:J50,16) -> 0 | AT50: =IF(A50="","",IF($N$4="M",A50*B50*0.000011111*AS50,A50*B50/144*AS50)) | AU50: =IF(D50=61,C50,0) -> 0 | AV50: =IF(D50=61,L50,0) -> 0 | AW50: =IF(A50="","",(C50-AU50)) | AX50: =IF(A50="","",(L50-AV50))
A51: 450 | B51: 250 | C51: 21.6 | F51: HA | G51: 7 | K51: =IF($N$4="M",IF(A51="","",IF(D51=6,16,IF(A51<=$M$5,26,IF(A51<=$M$6,24,IF(A51<=$M$7,22,IF(A51<=$M$8,20,18)))))),IF(A51="","",IF(D51=6,16,IF(A51<=$P$5,26,IF(A51<=$P$6,24,IF(A51<=$P$7,22,IF(A51<=$P$8,20,18))))))) | L51: =IF($N$4="M",IF(A51="","",IF(K51=26,(A51+B51+Q51)*C51*0.02739,IF(K51=24,(A51+B51+Q51)*C51*0.02739,IF(K51=22,(A51+B51+Q51)*C51*0.0333,IF(K51=20,(A51+B51+Q51)*C51*0.0393,IF(K51=18,(A51+B51+Q51)*C51*0.0511,IF(K51=16,(A51+B51+Q51)*C51*0.0628))))))),IF(A51="","",IF(K51=26,(A51+B51+Q51)*C51*0.211,IF(K51=24,(A51+B51+Q51)*C51*0.211,IF(K51=22,(A51+B51+Q51)*C51*0.258,IF(K51=20,(A51+B51+Q51)*C51*0.304,IF(K51=18,(A51+B51+Q51)*C51*0.395,IF(K51=16,(A51+B51+Q51)*C51*0.487)))))))) | M51: =IF(D51=1,0.5,IF(D51=2,"1 F",IF(D51=21,"1 R",IF(D51=3,2,"")))) | N51: =IF(M51="","",IF($N$4="M",(A51+B51+Q51)*C51*0.022,(A51+B51+Q51)*C51*0.17)) | O51: =IF(D51=4,1,IF(D51=5,2,"")) | P51: =IF(O51="","",IF($N$4="M",IF(O51=1,(A51+B51+Q51)*C51*0.022*1.1,(A51+B51+Q51)*C51*0.022*1.15),IF(O51=1,(A51+B51+Q51)*C51*0.17*1.1,(A51+B51+Q51)*C51*0.17*1.15))) | Q51: =IF($N$4="M",IF(A51="","",IF(D51=1,50,IF(D51=2,100,IF(D51=21,100,IF(D51=3,200,0))))),IF(A51="","",IF(D51=1,2,IF(D51=2,4,IF(D51=21,4,IF(D51=3,8,0)))))) | R51: =COUNTIF(G51:J51,7) -> 0 | S51: =IF(A51="","",IF($N$4="M",A51*B51*0.000011111*R51*1.5,A51*B51/144*R51*1.5)) | T51: =COUNTIF(G51:J51,71) -> 0 | U51: =IF(A51="","",IF($N$4="M",A51*B51*0.000011111*T51*1.5,A51*B51/144*T51*1.5)) | V51: =COUNTIF(G51:J51,8) -> 0 | W51: =IF(A51="","",IF($N$4="M",(A51+B51)*2*0.0032808*V51,(A51+B51)*2*V51/12)) | X51: =COUNTIF(G51:J51,81) -> 0 | Y51: =IF(A51="","",IF($N$4="M",(A51+B51)*2*0.0032808*X51,(A51+B51)*2*X51/12)) | Z51: =COUNTIF(G51:J51,9) -> 0 | AA51: =COUNTIF(G51:J51,10) -> 0 | AB51: =IF(A51="","",IF($N$4="M",(A51+B51)*2*0.0032808*AA51,(A51+B51)*2*AA51/12)) | AC51: =COUNTIF(G51:J51,100) -> 0 | AE51: =COUNTIF(G51:J51,11) -> 0 | AF51: =IF(A51="","",IF($N$4="M",A51*B51*0.000011111*AE51,A51*B51/144*AE51)) | AG51: =COUNTIF(G51:J51,111) -> 0 | AH51: =IF(A51="","",IF($N$4="M",A51*B51*0.000011111*AG51,A51*B51/144*AG51)) | AI51: =COUNTIF(G51:J51,12) -> 0 | AJ51: =IF(A51="","",IF($N$4="M",A51*B51*0.000011111*AI51,A51*B51/144*AI51)) | AK51: =COUNTIF(G51:J51,13) -> 0 | AL51: =COUNTIF(G51:J51,131) -> 0 | AM51: =IF(A51="","",IF($N$4="M",A51*B51*0.000011111*AL51,A51*B51/144*AL51)) | AN51: =COUNTIF(G51:J51,14) -> 0 | AO51: =IF(A51="","",IF($N$4="M",A51*B51*0.000011111*AN51,A51*B51/144*AN51)) | AP51: =COUNTIF(G51:J51,141) -> 0 | AQ51: =IF(A51="","",IF($N$4="M",A51*B51*0.000011111*AP51,A51*B51/144*AP51)) | AR51: =COUNTIF(G51:J51,15) -> 0 | AS51: =COUNTIF(G51:J51,16) -> 0 | AT51: =IF(A51="","",IF($N$4="M",A51*B51*0.000011111*AS51,A51*B51/144*AS51)) | AU51: =IF(D51=61,C51,0) -> 0 | AV51: =IF(D51=61,L51,0) -> 0 | AW51: =IF(A51="","",(C51-AU51)) | AX51: =IF(A51="","",(L51-AV51))
A52: 450 | B52: 300 | C52: 25 | F52: HA | K52: =IF($N$4="M",IF(A52="","",IF(D52=6,16,IF(A52<=$M$5,26,IF(A52<=$M$6,24,IF(A52<=$M$7,22,IF(A52<=$M$8,20,18)))))),IF(A52="","",IF(D52=6,16,IF(A52<=$P$5,26,IF(A52<=$P$6,24,IF(A52<=$P$7,22,IF(A52<=$P$8,20,18))))))) | L52: =IF($N$4="M",IF(A52="","",IF(K52=26,(A52+B52+Q52)*C52*0.02739,IF(K52=24,(A52+B52+Q52)*C52*0.02739,IF(K52=22,(A52+B52+Q52)*C52*0.0333,IF(K52=20,(A52+B52+Q52)*C52*0.0393,IF(K52=18,(A52+B52+Q52)*C52*0.0511,IF(K52=16,(A52+B52+Q52)*C52*0.0628))))))),IF(A52="","",IF(K52=26,(A52+B52+Q52)*C52*0.211,IF(K52=24,(A52+B52+Q52)*C52*0.211,IF(K52=22,(A52+B52+Q52)*C52*0.258,IF(K52=20,(A52+B52+Q52)*C52*0.304,IF(K52=18,(A52+B52+Q52)*C52*0.395,IF(K52=16,(A52+B52+Q52)*C52*0.487)))))))) | M52: =IF(D52=1,0.5,IF(D52=2,"1 F",IF(D52=21,"1 R",IF(D52=3,2,"")))) | N52: =IF(M52="","",IF($N$4="M",(A52+B52+Q52)*C52*0.022,(A52+B52+Q52)*C52*0.17)) | O52: =IF(D52=4,1,IF(D52=5,2,"")) | P52: =IF(O52="","",IF($N$4="M",IF(O52=1,(A52+B52+Q52)*C52*0.022*1.1,(A52+B52+Q52)*C52*0.022*1.15),IF(O52=1,(A52+B52+Q52)*C52*0.17*1.1,(A52+B52+Q52)*C52*0.17*1.15))) | Q52: =IF($N$4="M",IF(A52="","",IF(D52=1,50,IF(D52=2,100,IF(D52=21,100,IF(D52=3,200,0))))),IF(A52="","",IF(D52=1,2,IF(D52=2,4,IF(D52=21,4,IF(D52=3,8,0)))))) | R52: =COUNTIF(G52:J52,7) -> 0 | S52: =IF(A52="","",IF($N$4="M",A52*B52*0.000011111*R52*1.5,A52*B52/144*R52*1.5)) | T52: =COUNTIF(G52:J52,71) -> 0 | U52: =IF(A52="","",IF($N$4="M",A52*B52*0.000011111*T52*1.5,A52*B52/144*T52*1.5)) | V52: =COUNTIF(G52:J52,8) -> 0 | W52: =IF(A52="","",IF($N$4="M",(A52+B52)*2*0.0032808*V52,(A52+B52)*2*V52/12)) | X52: =COUNTIF(G52:J52,81) -> 0 | Y52: =IF(A52="","",IF($N$4="M",(A52+B52)*2*0.0032808*X52,(A52+B52)*2*X52/12)) | Z52: =COUNTIF(G52:J52,9) -> 0 | AA52: =COUNTIF(G52:J52,10) -> 0 | AB52: =IF(A52="","",IF($N$4="M",(A52+B52)*2*0.0032808*AA52,(A52+B52)*2*AA52/12)) | AC52: =COUNTIF(G52:J52,100) -> 0 | AE52: =COUNTIF(G52:J52,11) -> 0 | AF52: =IF(A52="","",IF($N$4="M",A52*B52*0.000011111*AE52,A52*B52/144*AE52)) | AG52: =COUNTIF(G52:J52,111) -> 0 | AH52: =IF(A52="","",IF($N$4="M",A52*B52*0.000011111*AG52,A52*B52/144*AG52)) | AI52: =COUNTIF(G52:J52,12) -> 0 | AJ52: =IF(A52="","",IF($N$4="M",A52*B52*0.000011111*AI52,A52*B52/144*AI52)) | AK52: =COUNTIF(G52:J52,13) -> 0 | AL52: =COUNTIF(G52:J52,131) -> 0 | AM52: =IF(A52="","",IF($N$4="M",A52*B52*0.000011111*AL52,A52*B52/144*AL52)) | AN52: =COUNTIF(G52:J52,14) -> 0 | AO52: =IF(A52="","",IF($N$4="M",A52*B52*0.000011111*AN52,A52*B52/144*AN52)) | AP52: =COUNTIF(G52:J52,141) -> 0 | AQ52: =IF(A52="","",IF($N$4="M",A52*B52*0.000011111*AP52,A52*B52/144*AP52)) | AR52: =COUNTIF(G52:J52,15) -> 0 | AS52: =COUNTIF(G52:J52,16) -> 0 | AT52: =IF(A52="","",IF($N$4="M",A52*B52*0.000011111*AS52,A52*B52/144*AS52)) | AU52: =IF(D52=61,C52,0) -> 0 | AV52: =IF(D52=61,L52,0) -> 0 | AW52: =IF(A52="","",(C52-AU52)) | AX52: =IF(A52="","",(L52-AV52))
A53: 450 | B53: 300 | C53: 6.3 | D53: 6 | E53: HP | F53: HA | K53: =IF($N$4="M",IF(A53="","",IF(D53=6,16,IF(A53<=$M$5,26,IF(A53<=$M$6,24,IF(A53<=$M$7,22,IF(A53<=$M$8,20,18)))))),IF(A53="","",IF(D53=6,16,IF(A53<=$P$5,26,IF(A53<=$P$6,24,IF(A53<=$P$7,22,IF(A53<=$P$8,20,18))))))) | L53: =IF($N$4="M",IF(A53="","",IF(K53=26,(A53+B53+Q53)*C53*0.02739,IF(K53=24,(A53+B53+Q53)*C53*0.02739,IF(K53=22,(A53+B53+Q53)*C53*0.0333,IF(K53=20,(A53+B53+Q53)*C53*0.0393,IF(K53=18,(A53+B53+Q53)*C53*0.0511,IF(K53=16,(A53+B53+Q53)*C53*0.0628))))))),IF(A53="","",IF(K53=26,(A53+B53+Q53)*C53*0.211,IF(K53=24,(A53+B53+Q53)*C53*0.211,IF(K53=22,(A53+B53+Q53)*C53*0.258,IF(K53=20,(A53+B53+Q53)*C53*0.304,IF(K53=18,(A53+B53+Q53)*C53*0.395,IF(K53=16,(A53+B53+Q53)*C53*0.487)))))))) | M53: =IF(D53=1,0.5,IF(D53=2,"1 F",IF(D53=21,"1 R",IF(D53=3,2,"")))) | N53: =IF(M53="","",IF($N$4="M",(A53+B53+Q53)*C53*0.022,(A53+B53+Q53)*C53*0.17)) | O53: =IF(D53=4,1,IF(D53=5,2,"")) | P53: =IF(O53="","",IF($N$4="M",IF(O53=1,(A53+B53+Q53)*C53*0.022*1.1,(A53+B53+Q53)*C53*0.022*1.15),IF(O53=1,(A53+B53+Q53)*C53*0.17*1.1,(A53+B53+Q53)*C53*0.17*1.15))) | Q53: =IF($N$4="M",IF(A53="","",IF(D53=1,50,IF(D53=2,100,IF(D53=21,100,IF(D53=3,200,0))))),IF(A53="","",IF(D53=1,2,IF(D53=2,4,IF(D53=21,4,IF(D53=3,8,0)))))) | R53: =COUNTIF(G53:J53,7) -> 0 | S53: =IF(A53="","",IF($N$4="M",A53*B53*0.000011111*R53*1.5,A53*B53/144*R53*1.5)) | T53: =COUNTIF(G53:J53,71) -> 0 | U53: =IF(A53="","",IF($N$4="M",A53*B53*0.000011111*T53*1.5,A53*B53/144*T53*1.5)) | V53: =COUNTIF(G53:J53,8) -> 0 | W53: =IF(A53="","",IF($N$4="M",(A53+B53)*2*0.0032808*V53,(A53+B53)*2*V53/12)) | X53: =COUNTIF(G53:J53,81) -> 0 | Y53: =IF(A53="","",IF($N$4="M",(A53+B53)*2*0.0032808*X53,(A53+B53)*2*X53/12)) | Z53: =COUNTIF(G53:J53,9) -> 0 | AA53: =COUNTIF(G53:J53,10) -> 0 | AB53: =IF(A53="","",IF($N$4="M",(A53+B53)*2*0.0032808*AA53,(A53+B53)*2*AA53/12)) | AC53: =COUNTIF(G53:J53,100) -> 0 | AE53: =COUNTIF(G53:J53,11) -> 0 | AF53: =IF(A53="","",IF($N$4="M",A53*B53*0.000011111*AE53,A53*B53/144*AE53)) | AG53: =COUNTIF(G53:J53,111) -> 0 | AH53: =IF(A53="","",IF($N$4="M",A53*B53*0.000011111*AG53,A53*B53/144*AG53)) | AI53: =COUNTIF(G53:J53,12) -> 0 | AJ53: =IF(A53="","",IF($N$4="M",A53*B53*0.000011111*AI53,A53*B53/144*AI53)) | AK53: =COUNTIF(G53:J53,13) -> 0 | AL53: =COUNTIF(G53:J53,131) -> 0 | AM53: =IF(A53="","",IF($N$4="M",A53*B53*0.000011111*AL53,A53*B53/144*AL53)) | AN53: =COUNTIF(G53:J53,14) -> 0 | AO53: =IF(A53="","",IF($N$4="M",A53*B53*0.000011111*AN53,A53*B53/144*AN53)) | AP53: =COUNTIF(G53:J53,141) -> 0 | AQ53: =IF(A53="","",IF($N$4="M",A53*B53*0.000011111*AP53,A53*B53/144*AP53)) | AR53: =COUNTIF(G53:J53,15) -> 0 | AS53: =COUNTIF(G53:J53,16) -> 0 | AT53: =IF(A53="","",IF($N$4="M",A53*B53*0.000011111*AS53,A53*B53/144*AS53)) | AU53: =IF(D53=61,C53,0) -> 0 | AV53: =IF(D53=61,L53,0) -> 0 | AW53: =IF(A53="","",(C53-AU53)) | AX53: =IF(A53="","",(L53-AV53))
A54: 600 | B54: 300 | C54: 6.1 | F54: HA | K54: =IF($N$4="M",IF(A54="","",IF(D54=6,16,IF(A54<=$M$5,26,IF(A54<=$M$6,24,IF(A54<=$M$7,22,IF(A54<=$M$8,20,18)))))),IF(A54="","",IF(D54=6,16,IF(A54<=$P$5,26,IF(A54<=$P$6,24,IF(A54<=$P$7,22,IF(A54<=$P$8,20,18))))))) | L54: =IF($N$4="M",IF(A54="","",IF(K54=26,(A54+B54+Q54)*C54*0.02739,IF(K54=24,(A54+B54+Q54)*C54*0.02739,IF(K54=22,(A54+B54+Q54)*C54*0.0333,IF(K54=20,(A54+B54+Q54)*C54*0.0393,IF(K54=18,(A54+B54+Q54)*C54*0.0511,IF(K54=16,(A54+B54+Q54)*C54*0.0628))))))),IF(A54="","",IF(K54=26,(A54+B54+Q54)*C54*0.211,IF(K54=24,(A54+B54+Q54)*C54*0.211,IF(K54=22,(A54+B54+Q54)*C54*0.258,IF(K54=20,(A54+B54+Q54)*C54*0.304,IF(K54=18,(A54+B54+Q54)*C54*0.395,IF(K54=16,(A54+B54+Q54)*C54*0.487)))))))) | M54: =IF(D54=1,0.5,IF(D54=2,"1 F",IF(D54=21,"1 R",IF(D54=3,2,"")))) | N54: =IF(M54="","",IF($N$4="M",(A54+B54+Q54)*C54*0.022,(A54+B54+Q54)*C54*0.17)) | O54: =IF(D54=4,1,IF(D54=5,2,"")) | P54: =IF(O54="","",IF($N$4="M",IF(O54=1,(A54+B54+Q54)*C54*0.022*1.1,(A54+B54+Q54)*C54*0.022*1.15),IF(O54=1,(A54+B54+Q54)*C54*0.17*1.1,(A54+B54+Q54)*C54*0.17*1.15))) | Q54: =IF($N$4="M",IF(A54="","",IF(D54=1,50,IF(D54=2,100,IF(D54=21,100,IF(D54=3,200,0))))),IF(A54="","",IF(D54=1,2,IF(D54=2,4,IF(D54=21,4,IF(D54=3,8,0)))))) | R54: =COUNTIF(G54:J54,7) -> 0 | S54: =IF(A54="","",IF($N$4="M",A54*B54*0.000011111*R54*1.5,A54*B54/144*R54*1.5)) | T54: =COUNTIF(G54:J54,71) -> 0 | U54: =IF(A54="","",IF($N$4="M",A54*B54*0.000011111*T54*1.5,A54*B54/144*T54*1.5)) | V54: =COUNTIF(G54:J54,8) -> 0 | W54: =IF(A54="","",IF($N$4="M",(A54+B54)*2*0.0032808*V54,(A54+B54)*2*V54/12)) | X54: =COUNTIF(G54:J54,81) -> 0 | Y54: =IF(A54="","",IF($N$4="M",(A54+B54)*2*0.0032808*X54,(A54+B54)*2*X54/12)) | Z54: =COUNTIF(G54:J54,9) -> 0 | AA54: =COUNTIF(G54:J54,10) -> 0 | AB54: =IF(A54="","",IF($N$4="M",(A54+B54)*2*0.0032808*AA54,(A54+B54)*2*AA54/12)) | AC54: =COUNTIF(G54:J54,100) -> 0 | AE54: =COUNTIF(G54:J54,11) -> 0 | AF54: =IF(A54="","",IF($N$4="M",A54*B54*0.000011111*AE54,A54*B54/144*AE54)) | AG54: =COUNTIF(G54:J54,111) -> 0 | AH54: =IF(A54="","",IF($N$4="M",A54*B54*0.000011111*AG54,A54*B54/144*AG54)) | AI54: =COUNTIF(G54:J54,12) -> 0 | AJ54: =IF(A54="","",IF($N$4="M",A54*B54*0.000011111*AI54,A54*B54/144*AI54)) | AK54: =COUNTIF(G54:J54,13) -> 0 | AL54: =COUNTIF(G54:J54,131) -> 0 | AM54: =IF(A54="","",IF($N$4="M",A54*B54*0.000011111*AL54,A54*B54/144*AL54)) | AN54: =COUNTIF(G54:J54,14) -> 0 | AO54: =IF(A54="","",IF($N$4="M",A54*B54*0.000011111*AN54,A54*B54/144*AN54)) | AP54: =COUNTIF(G54:J54,141) -> 0 | AQ54: =IF(A54="","",IF($N$4="M",A54*B54*0.000011111*AP54,A54*B54/144*AP54)) | AR54: =COUNTIF(G54:J54,15) -> 0 | AS54: =COUNTIF(G54:J54,16) -> 0 | AT54: =IF(A54="","",IF($N$4="M",A54*B54*0.000011111*AS54,A54*B54/144*AS54)) | AU54: =IF(D54=61,C54,0) -> 0 | AV54: =IF(D54=61,L54,0) -> 0 | AW54: =IF(A54="","",(C54-AU54)) | AX54: =IF(A54="","",(L54-AV54))
A55: 600 | B55: 300 | C55: 5.2 | D55: 6 | E55: HP | F55: HA | K55: =IF($N$4="M",IF(A55="","",IF(D55=6,16,IF(A55<=$M$5,26,IF(A55<=$M$6,24,IF(A55<=$M$7,22,IF(A55<=$M$8,20,18)))))),IF(A55="","",IF(D55=6,16,IF(A55<=$P$5,26,IF(A55<=$P$6,24,IF(A55<=$P$7,22,IF(A55<=$P$8,20,18))))))) | L55: =IF($N$4="M",IF(A55="","",IF(K55=26,(A55+B55+Q55)*C55*0.02739,IF(K55=24,(A55+B55+Q55)*C55*0.02739,IF(K55=22,(A55+B55+Q55)*C55*0.0333,IF(K55=20,(A55+B55+Q55)*C55*0.0393,IF(K55=18,(A55+B55+Q55)*C55*0.0511,IF(K55=16,(A55+B55+Q55)*C55*0.0628))))))),IF(A55="","",IF(K55=26,(A55+B55+Q55)*C55*0.211,IF(K55=24,(A55+B55+Q55)*C55*0.211,IF(K55=22,(A55+B55+Q55)*C55*0.258,IF(K55=20,(A55+B55+Q55)*C55*0.304,IF(K55=18,(A55+B55+Q55)*C55*0.395,IF(K55=16,(A55+B55+Q55)*C55*0.487)))))))) | M55: =IF(D55=1,0.5,IF(D55=2,"1 F",IF(D55=21,"1 R",IF(D55=3,2,"")))) | N55: =IF(M55="","",IF($N$4="M",(A55+B55+Q55)*C55*0.022,(A55+B55+Q55)*C55*0.17)) | O55: =IF(D55=4,1,IF(D55=5,2,"")) | P55: =IF(O55="","",IF($N$4="M",IF(O55=1,(A55+B55+Q55)*C55*0.022*1.1,(A55+B55+Q55)*C55*0.022*1.15),IF(O55=1,(A55+B55+Q55)*C55*0.17*1.1,(A55+B55+Q55)*C55*0.17*1.15))) | Q55: =IF($N$4="M",IF(A55="","",IF(D55=1,50,IF(D55=2,100,IF(D55=21,100,IF(D55=3,200,0))))),IF(A55="","",IF(D55=1,2,IF(D55=2,4,IF(D55=21,4,IF(D55=3,8,0)))))) | R55: =COUNTIF(G55:J55,7) -> 0 | S55: =IF(A55="","",IF($N$4="M",A55*B55*0.000011111*R55*1.5,A55*B55/144*R55*1.5)) | T55: =COUNTIF(G55:J55,71) -> 0 | U55: =IF(A55="","",IF($N$4="M",A55*B55*0.000011111*T55*1.5,A55*B55/144*T55*1.5)) | V55: =COUNTIF(G55:J55,8) -> 0 | W55: =IF(A55="","",IF($N$4="M",(A55+B55)*2*0.0032808*V55,(A55+B55)*2*V55/12)) | X55: =COUNTIF(G55:J55,81) -> 0 | Y55: =IF(A55="","",IF($N$4="M",(A55+B55)*2*0.0032808*X55,(A55+B55)*2*X55/12)) | Z55: =COUNTIF(G55:J55,9) -> 0 | AA55: =COUNTIF(G55:J55,10) -> 0 | AB55: =IF(A55="","",IF($N$4="M",(A55+B55)*2*0.0032808*AA55,(A55+B55)*2*AA55/12)) | AC55: =COUNTIF(G55:J55,100) -> 0 | AE55: =COUNTIF(G55:J55,11) -> 0 | AF55: =IF(A55="","",IF($N$4="M",A55*B55*0.000011111*AE55,A55*B55/144*AE55)) | AG55: =COUNTIF(G55:J55,111) -> 0 | AH55: =IF(A55="","",IF($N$4="M",A55*B55*0.000011111*AG55,A55*B55/144*AG55)) | AI55: =COUNTIF(G55:J55,12) -> 0 | AJ55: =IF(A55="","",IF($N$4="M",A55*B55*0.000011111*AI55,A55*B55/144*AI55)) | AK55: =COUNTIF(G55:J55,13) -> 0 | AL55: =COUNTIF(G55:J55,131) -> 0 | AM55: =IF(A55="","",IF($N$4="M",A55*B55*0.000011111*AL55,A55*B55/144*AL55)) | AN55: =COUNTIF(G55:J55,14) -> 0 | AO55: =IF(A55="","",IF($N$4="M",A55*B55*0.000011111*AN55,A55*B55/144*AN55)) | AP55: =COUNTIF(G55:J55,141) -> 0 | AQ55: =IF(A55="","",IF($N$4="M",A55*B55*0.000011111*AP55,A55*B55/144*AP55)) | AR55: =COUNTIF(G55:J55,15) -> 0 | AS55: =COUNTIF(G55:J55,16) -> 0 | AT55: =IF(A55="","",IF($N$4="M",A55*B55*0.000011111*AS55,A55*B55/144*AS55)) | AU55: =IF(D55=61,C55,0) -> 0 | AV55: =IF(D55=61,L55,0) -> 0 | AW55: =IF(A55="","",(C55-AU55)) | AX55: =IF(A55="","",(L55-AV55))
A56: 750 | B56: 300 | C56: 6.9 | F56: HA | K56: =IF($N$4="M",IF(A56="","",IF(D56=6,16,IF(A56<=$M$5,26,IF(A56<=$M$6,24,IF(A56<=$M$7,22,IF(A56<=$M$8,20,18)))))),IF(A56="","",IF(D56=6,16,IF(A56<=$P$5,26,IF(A56<=$P$6,24,IF(A56<=$P$7,22,IF(A56<=$P$8,20,18))))))) | L56: =IF($N$4="M",IF(A56="","",IF(K56=26,(A56+B56+Q56)*C56*0.02739,IF(K56=24,(A56+B56+Q56)*C56*0.02739,IF(K56=22,(A56+B56+Q56)*C56*0.0333,IF(K56=20,(A56+B56+Q56)*C56*0.0393,IF(K56=18,(A56+B56+Q56)*C56*0.0511,IF(K56=16,(A56+B56+Q56)*C56*0.0628))))))),IF(A56="","",IF(K56=26,(A56+B56+Q56)*C56*0.211,IF(K56=24,(A56+B56+Q56)*C56*0.211,IF(K56=22,(A56+B56+Q56)*C56*0.258,IF(K56=20,(A56+B56+Q56)*C56*0.304,IF(K56=18,(A56+B56+Q56)*C56*0.395,IF(K56=16,(A56+B56+Q56)*C56*0.487)))))))) | M56: =IF(D56=1,0.5,IF(D56=2,"1 F",IF(D56=21,"1 R",IF(D56=3,2,"")))) | N56: =IF(M56="","",IF($N$4="M",(A56+B56+Q56)*C56*0.022,(A56+B56+Q56)*C56*0.17)) | O56: =IF(D56=4,1,IF(D56=5,2,"")) | P56: =IF(O56="","",IF($N$4="M",IF(O56=1,(A56+B56+Q56)*C56*0.022*1.1,(A56+B56+Q56)*C56*0.022*1.15),IF(O56=1,(A56+B56+Q56)*C56*0.17*1.1,(A56+B56+Q56)*C56*0.17*1.15))) | Q56: =IF($N$4="M",IF(A56="","",IF(D56=1,50,IF(D56=2,100,IF(D56=21,100,IF(D56=3,200,0))))),IF(A56="","",IF(D56=1,2,IF(D56=2,4,IF(D56=21,4,IF(D56=3,8,0)))))) | R56: =COUNTIF(G56:J56,7) -> 0 | S56: =IF(A56="","",IF($N$4="M",A56*B56*0.000011111*R56*1.5,A56*B56/144*R56*1.5)) | T56: =COUNTIF(G56:J56,71) -> 0 | U56: =IF(A56="","",IF($N$4="M",A56*B56*0.000011111*T56*1.5,A56*B56/144*T56*1.5)) | V56: =COUNTIF(G56:J56,8) -> 0 | W56: =IF(A56="","",IF($N$4="M",(A56+B56)*2*0.0032808*V56,(A56+B56)*2*V56/12)) | X56: =COUNTIF(G56:J56,81) -> 0 | Y56: =IF(A56="","",IF($N$4="M",(A56+B56)*2*0.0032808*X56,(A56+B56)*2*X56/12)) | Z56: =COUNTIF(G56:J56,9) -> 0 | AA56: =COUNTIF(G56:J56,10) -> 0 | AB56: =IF(A56="","",IF($N$4="M",(A56+B56)*2*0.0032808*AA56,(A56+B56)*2*AA56/12)) | AC56: =COUNTIF(G56:J56,100) -> 0 | AE56: =COUNTIF(G56:J56,11) -> 0 | AF56: =IF(A56="","",IF($N$4="M",A56*B56*0.000011111*AE56,A56*B56/144*AE56)) | AG56: =COUNTIF(G56:J56,111) -> 0 | AH56: =IF(A56="","",IF($N$4="M",A56*B56*0.000011111*AG56,A56*B56/144*AG56)) | AI56: =COUNTIF(G56:J56,12) -> 0 | AJ56: =IF(A56="","",IF($N$4="M",A56*B56*0.000011111*AI56,A56*B56/144*AI56)) | AK56: =COUNTIF(G56:J56,13) -> 0 | AL56: =COUNTIF(G56:J56,131) -> 0 | AM56: =IF(A56="","",IF($N$4="M",A56*B56*0.000011111*AL56,A56*B56/144*AL56)) | AN56: =COUNTIF(G56:J56,14) -> 0 | AO56: =IF(A56="","",IF($N$4="M",A56*B56*0.000011111*AN56,A56*B56/144*AN56)) | AP56: =COUNTIF(G56:J56,141) -> 0 | AQ56: =IF(A56="","",IF($N$4="M",A56*B56*0.000011111*AP56,A56*B56/144*AP56)) | AR56: =COUNTIF(G56:J56,15) -> 0 | AS56: =COUNTIF(G56:J56,16) -> 0 | AT56: =IF(A56="","",IF($N$4="M",A56*B56*0.000011111*AS56,A56*B56/144*AS56)) | AU56: =IF(D56=61,C56,0) -> 0 | AV56: =IF(D56=61,L56,0) -> 0 | AW56: =IF(A56="","",(C56-AU56)) | AX56: =IF(A56="","",(L56-AV56))
A57: 750 | B57: 350 | C57: 6.4 | F57: HA | K57: =IF($N$4="M",IF(A57="","",IF(D57=6,16,IF(A57<=$M$5,26,IF(A57<=$M$6,24,IF(A57<=$M$7,22,IF(A57<=$M$8,20,18)))))),IF(A57="","",IF(D57=6,16,IF(A57<=$P$5,26,IF(A57<=$P$6,24,IF(A57<=$P$7,22,IF(A57<=$P$8,20,18))))))) | L57: =IF($N$4="M",IF(A57="","",IF(K57=26,(A57+B57+Q57)*C57*0.02739,IF(K57=24,(A57+B57+Q57)*C57*0.02739,IF(K57=22,(A57+B57+Q57)*C57*0.0333,IF(K57=20,(A57+B57+Q57)*C57*0.0393,IF(K57=18,(A57+B57+Q57)*C57*0.0511,IF(K57=16,(A57+B57+Q57)*C57*0.0628))))))),IF(A57="","",IF(K57=26,(A57+B57+Q57)*C57*0.211,IF(K57=24,(A57+B57+Q57)*C57*0.211,IF(K57=22,(A57+B57+Q57)*C57*0.258,IF(K57=20,(A57+B57+Q57)*C57*0.304,IF(K57=18,(A57+B57+Q57)*C57*0.395,IF(K57=16,(A57+B57+Q57)*C57*0.487)))))))) | M57: =IF(D57=1,0.5,IF(D57=2,"1 F",IF(D57=21,"1 R",IF(D57=3,2,"")))) | N57: =IF(M57="","",IF($N$4="M",(A57+B57+Q57)*C57*0.022,(A57+B57+Q57)*C57*0.17)) | O57: =IF(D57=4,1,IF(D57=5,2,"")) | P57: =IF(O57="","",IF($N$4="M",IF(O57=1,(A57+B57+Q57)*C57*0.022*1.1,(A57+B57+Q57)*C57*0.022*1.15),IF(O57=1,(A57+B57+Q57)*C57*0.17*1.1,(A57+B57+Q57)*C57*0.17*1.15))) | Q57: =IF($N$4="M",IF(A57="","",IF(D57=1,50,IF(D57=2,100,IF(D57=21,100,IF(D57=3,200,0))))),IF(A57="","",IF(D57=1,2,IF(D57=2,4,IF(D57=21,4,IF(D57=3,8,0)))))) | R57: =COUNTIF(G57:J57,7) -> 0 | S57: =IF(A57="","",IF($N$4="M",A57*B57*0.000011111*R57*1.5,A57*B57/144*R57*1.5)) | T57: =COUNTIF(G57:J57,71) -> 0 | U57: =IF(A57="","",IF($N$4="M",A57*B57*0.000011111*T57*1.5,A57*B57/144*T57*1.5)) | V57: =COUNTIF(G57:J57,8) -> 0 | W57: =IF(A57="","",IF($N$4="M",(A57+B57)*2*0.0032808*V57,(A57+B57)*2*V57/12)) | X57: =COUNTIF(G57:J57,81) -> 0 | Y57: =IF(A57="","",IF($N$4="M",(A57+B57)*2*0.0032808*X57,(A57+B57)*2*X57/12)) | Z57: =COUNTIF(G57:J57,9) -> 0 | AA57: =COUNTIF(G57:J57,10) -> 0 | AB57: =IF(A57="","",IF($N$4="M",(A57+B57)*2*0.0032808*AA57,(A57+B57)*2*AA57/12)) | AC57: =COUNTIF(G57:J57,100) -> 0 | AE57: =COUNTIF(G57:J57,11) -> 0 | AF57: =IF(A57="","",IF($N$4="M",A57*B57*0.000011111*AE57,A57*B57/144*AE57)) | AG57: =COUNTIF(G57:J57,111) -> 0 | AH57: =IF(A57="","",IF($N$4="M",A57*B57*0.000011111*AG57,A57*B57/144*AG57)) | AI57: =COUNTIF(G57:J57,12) -> 0 | AJ57: =IF(A57="","",IF($N$4="M",A57*B57*0.000011111*AI57,A57*B57/144*AI57)) | AK57: =COUNTIF(G57:J57,13) -> 0 | AL57: =COUNTIF(G57:J57,131) -> 0 | AM57: =IF(A57="","",IF($N$4="M",A57*B57*0.000011111*AL57,A57*B57/144*AL57)) | AN57: =COUNTIF(G57:J57,14) -> 0 | AO57: =IF(A57="","",IF($N$4="M",A57*B57*0.000011111*AN57,A57*B57/144*AN57)) | AP57: =COUNTIF(G57:J57,141) -> 0 | AQ57: =IF(A57="","",IF($N$4="M",A57*B57*0.000011111*AP57,A57*B57/144*AP57)) | AR57: =COUNTIF(G57:J57,15) -> 0 | AS57: =COUNTIF(G57:J57,16) -> 0 | AT57: =IF(A57="","",IF($N$4="M",A57*B57*0.000011111*AS57,A57*B57/144*AS57)) | AU57: =IF(D57=61,C57,0) -> 0 | AV57: =IF(D57=61,L57,0) -> 0 | AW57: =IF(A57="","",(C57-AU57)) | AX57: =IF(A57="","",(L57-AV57))
A58: 800 | B58: 350 | C58: 5.4 | F58: RE | K58: =IF($N$4="M",IF(A58="","",IF(D58=6,16,IF(A58<=$M$5,26,IF(A58<=$M$6,24,IF(A58<=$M$7,22,IF(A58<=$M$8,20,18)))))),IF(A58="","",IF(D58=6,16,IF(A58<=$P$5,26,IF(A58<=$P$6,24,IF(A58<=$P$7,22,IF(A58<=$P$8,20,18))))))) | L58: =IF($N$4="M",IF(A58="","",IF(K58=26,(A58+B58+Q58)*C58*0.02739,IF(K58=24,(A58+B58+Q58)*C58*0.02739,IF(K58=22,(A58+B58+Q58)*C58*0.0333,IF(K58=20,(A58+B58+Q58)*C58*0.0393,IF(K58=18,(A58+B58+Q58)*C58*0.0511,IF(K58=16,(A58+B58+Q58)*C58*0.0628))))))),IF(A58="","",IF(K58=26,(A58+B58+Q58)*C58*0.211,IF(K58=24,(A58+B58+Q58)*C58*0.211,IF(K58=22,(A58+B58+Q58)*C58*0.258,IF(K58=20,(A58+B58+Q58)*C58*0.304,IF(K58=18,(A58+B58+Q58)*C58*0.395,IF(K58=16,(A58+B58+Q58)*C58*0.487)))))))) | M58: =IF(D58=1,0.5,IF(D58=2,"1 F",IF(D58=21,"1 R",IF(D58=3,2,"")))) | N58: =IF(M58="","",IF($N$4="M",(A58+B58+Q58)*C58*0.022,(A58+B58+Q58)*C58*0.17)) | O58: =IF(D58=4,1,IF(D58=5,2,"")) | P58: =IF(O58="","",IF($N$4="M",IF(O58=1,(A58+B58+Q58)*C58*0.022*1.1,(A58+B58+Q58)*C58*0.022*1.15),IF(O58=1,(A58+B58+Q58)*C58*0.17*1.1,(A58+B58+Q58)*C58*0.17*1.15))) | Q58: =IF($N$4="M",IF(A58="","",IF(D58=1,50,IF(D58=2,100,IF(D58=21,100,IF(D58=3,200,0))))),IF(A58="","",IF(D58=1,2,IF(D58=2,4,IF(D58=21,4,IF(D58=3,8,0)))))) | R58: =COUNTIF(G58:J58,7) -> 0 | S58: =IF(A58="","",IF($N$4="M",A58*B58*0.000011111*R58*1.5,A58*B58/144*R58*1.5)) | T58: =COUNTIF(G58:J58,71) -> 0 | U58: =IF(A58="","",IF($N$4="M",A58*B58*0.000011111*T58*1.5,A58*B58/144*T58*1.5)) | V58: =COUNTIF(G58:J58,8) -> 0 | W58: =IF(A58="","",IF($N$4="M",(A58+B58)*2*0.0032808*V58,(A58+B58)*2*V58/12)) | X58: =COUNTIF(G58:J58,81) -> 0 | Y58: =IF(A58="","",IF($N$4="M",(A58+B58)*2*0.0032808*X58,(A58+B58)*2*X58/12)) | Z58: =COUNTIF(G58:J58,9) -> 0 | AA58: =COUNTIF(G58:J58,10) -> 0 | AB58: =IF(A58="","",IF($N$4="M",(A58+B58)*2*0.0032808*AA58,(A58+B58)*2*AA58/12)) | AC58: =COUNTIF(G58:J58,100) -> 0 | AE58: =COUNTIF(G58:J58,11) -> 0 | AF58: =IF(A58="","",IF($N$4="M",A58*B58*0.000011111*AE58,A58*B58/144*AE58)) | AG58: =COUNTIF(G58:J58,111) -> 0 | AH58: =IF(A58="","",IF($N$4="M",A58*B58*0.000011111*AG58,A58*B58/144*AG58)) | AI58: =COUNTIF(G58:J58,12) -> 0 | AJ58: =IF(A58="","",IF($N$4="M",A58*B58*0.000011111*AI58,A58*B58/144*AI58)) | AK58: =COUNTIF(G58:J58,13) -> 0 | AL58: =COUNTIF(G58:J58,131) -> 0 | AM58: =IF(A58="","",IF($N$4="M",A58*B58*0.000011111*AL58,A58*B58/144*AL58)) | AN58: =COUNTIF(G58:J58,14) -> 0 | AO58: =IF(A58="","",IF($N$4="M",A58*B58*0.000011111*AN58,A58*B58/144*AN58)) | AP58: =COUNTIF(G58:J58,141) -> 0 | AQ58: =IF(A58="","",IF($N$4="M",A58*B58*0.000011111*AP58,A58*B58/144*AP58)) | AR58: =COUNTIF(G58:J58,15) -> 0 | AS58: =COUNTIF(G58:J58,16) -> 0 | AT58: =IF(A58="","",IF($N$4="M",A58*B58*0.000011111*AS58,A58*B58/144*AS58)) | AU58: =IF(D58=61,C58,0) -> 0 | AV58: =IF(D58=61,L58,0) -> 0 | AW58: =IF(A58="","",(C58-AU58)) | AX58: =IF(A58="","",(L58-AV58))
A59: 800 | B59: 400 | C59: 4.7 | F59: RE | K59: =IF($N$4="M",IF(A59="","",IF(D59=6,16,IF(A59<=$M$5,26,IF(A59<=$M$6,24,IF(A59<=$M$7,22,IF(A59<=$M$8,20,18)))))),IF(A59="","",IF(D59=6,16,IF(A59<=$P$5,26,IF(A59<=$P$6,24,IF(A59<=$P$7,22,IF(A59<=$P$8,20,18))))))) | L59: =IF($N$4="M",IF(A59="","",IF(K59=26,(A59+B59+Q59)*C59*0.02739,IF(K59=24,(A59+B59+Q59)*C59*0.02739,IF(K59=22,(A59+B59+Q59)*C59*0.0333,IF(K59=20,(A59+B59+Q59)*C59*0.0393,IF(K59=18,(A59+B59+Q59)*C59*0.0511,IF(K59=16,(A59+B59+Q59)*C59*0.0628))))))),IF(A59="","",IF(K59=26,(A59+B59+Q59)*C59*0.211,IF(K59=24,(A59+B59+Q59)*C59*0.211,IF(K59=22,(A59+B59+Q59)*C59*0.258,IF(K59=20,(A59+B59+Q59)*C59*0.304,IF(K59=18,(A59+B59+Q59)*C59*0.395,IF(K59=16,(A59+B59+Q59)*C59*0.487)))))))) | M59: =IF(D59=1,0.5,IF(D59=2,"1 F",IF(D59=21,"1 R",IF(D59=3,2,"")))) | N59: =IF(M59="","",IF($N$4="M",(A59+B59+Q59)*C59*0.022,(A59+B59+Q59)*C59*0.17)) | O59: =IF(D59=4,1,IF(D59=5,2,"")) | P59: =IF(O59="","",IF($N$4="M",IF(O59=1,(A59+B59+Q59)*C59*0.022*1.1,(A59+B59+Q59)*C59*0.022*1.15),IF(O59=1,(A59+B59+Q59)*C59*0.17*1.1,(A59+B59+Q59)*C59*0.17*1.15))) | Q59: =IF($N$4="M",IF(A59="","",IF(D59=1,50,IF(D59=2,100,IF(D59=21,100,IF(D59=3,200,0))))),IF(A59="","",IF(D59=1,2,IF(D59=2,4,IF(D59=21,4,IF(D59=3,8,0)))))) | R59: =COUNTIF(G59:J59,7) -> 0 | S59: =IF(A59="","",IF($N$4="M",A59*B59*0.000011111*R59*1.5,A59*B59/144*R59*1.5)) | T59: =COUNTIF(G59:J59,71) -> 0 | U59: =IF(A59="","",IF($N$4="M",A59*B59*0.000011111*T59*1.5,A59*B59/144*T59*1.5)) | V59: =COUNTIF(G59:J59,8) -> 0 | W59: =IF(A59="","",IF($N$4="M",(A59+B59)*2*0.0032808*V59,(A59+B59)*2*V59/12)) | X59: =COUNTIF(G59:J59,81) -> 0 | Y59: =IF(A59="","",IF($N$4="M",(A59+B59)*2*0.0032808*X59,(A59+B59)*2*X59/12)) | Z59: =COUNTIF(G59:J59,9) -> 0 | AA59: =COUNTIF(G59:J59,10) -> 0 | AB59: =IF(A59="","",IF($N$4="M",(A59+B59)*2*0.0032808*AA59,(A59+B59)*2*AA59/12)) | AC59: =COUNTIF(G59:J59,100) -> 0 | AE59: =COUNTIF(G59:J59,11) -> 0 | AF59: =IF(A59="","",IF($N$4="M",A59*B59*0.000011111*AE59,A59*B59/144*AE59)) | AG59: =COUNTIF(G59:J59,111) -> 0 | AH59: =IF(A59="","",IF($N$4="M",A59*B59*0.000011111*AG59,A59*B59/144*AG59)) | AI59: =COUNTIF(G59:J59,12) -> 0 | AJ59: =IF(A59="","",IF($N$4="M",A59*B59*0.000011111*AI59,A59*B59/144*AI59)) | AK59: =COUNTIF(G59:J59,13) -> 0 | AL59: =COUNTIF(G59:J59,131) -> 0 | AM59: =IF(A59="","",IF($N$4="M",A59*B59*0.000011111*AL59,A59*B59/144*AL59)) | AN59: =COUNTIF(G59:J59,14) -> 0 | AO59: =IF(A59="","",IF($N$4="M",A59*B59*0.000011111*AN59,A59*B59/144*AN59)) | AP59: =COUNTIF(G59:J59,141) -> 0 | AQ59: =IF(A59="","",IF($N$4="M",A59*B59*0.000011111*AP59,A59*B59/144*AP59)) | AR59: =COUNTIF(G59:J59,15) -> 0 | AS59: =COUNTIF(G59:J59,16) -> 0 | AT59: =IF(A59="","",IF($N$4="M",A59*B59*0.000011111*AS59,A59*B59/144*AS59)) | AU59: =IF(D59=61,C59,0) -> 0 | AV59: =IF(D59=61,L59,0) -> 0 | AW59: =IF(A59="","",(C59-AU59)) | AX59: =IF(A59="","",(L59-AV59))
A60: 850 | B60: 400 | C60: 8.8 | F60: RE | K60: =IF($N$4="M",IF(A60="","",IF(D60=6,16,IF(A60<=$M$5,26,IF(A60<=$M$6,24,IF(A60<=$M$7,22,IF(A60<=$M$8,20,18)))))),IF(A60="","",IF(D60=6,16,IF(A60<=$P$5,26,IF(A60<=$P$6,24,IF(A60<=$P$7,22,IF(A60<=$P$8,20,18))))))) | L60: =IF($N$4="M",IF(A60="","",IF(K60=26,(A60+B60+Q60)*C60*0.02739,IF(K60=24,(A60+B60+Q60)*C60*0.02739,IF(K60=22,(A60+B60+Q60)*C60*0.0333,IF(K60=20,(A60+B60+Q60)*C60*0.0393,IF(K60=18,(A60+B60+Q60)*C60*0.0511,IF(K60=16,(A60+B60+Q60)*C60*0.0628))))))),IF(A60="","",IF(K60=26,(A60+B60+Q60)*C60*0.211,IF(K60=24,(A60+B60+Q60)*C60*0.211,IF(K60=22,(A60+B60+Q60)*C60*0.258,IF(K60=20,(A60+B60+Q60)*C60*0.304,IF(K60=18,(A60+B60+Q60)*C60*0.395,IF(K60=16,(A60+B60+Q60)*C60*0.487)))))))) | M60: =IF(D60=1,0.5,IF(D60=2,"1 F",IF(D60=21,"1 R",IF(D60=3,2,"")))) | N60: =IF(M60="","",IF($N$4="M",(A60+B60+Q60)*C60*0.022,(A60+B60+Q60)*C60*0.17)) | O60: =IF(D60=4,1,IF(D60=5,2,"")) | P60: =IF(O60="","",IF($N$4="M",IF(O60=1,(A60+B60+Q60)*C60*0.022*1.1,(A60+B60+Q60)*C60*0.022*1.15),IF(O60=1,(A60+B60+Q60)*C60*0.17*1.1,(A60+B60+Q60)*C60*0.17*1.15))) | Q60: =IF($N$4="M",IF(A60="","",IF(D60=1,50,IF(D60=2,100,IF(D60=21,100,IF(D60=3,200,0))))),IF(A60="","",IF(D60=1,2,IF(D60=2,4,IF(D60=21,4,IF(D60=3,8,0)))))) | R60: =COUNTIF(G60:J60,7) -> 0 | S60: =IF(A60="","",IF($N$4="M",A60*B60*0.000011111*R60*1.5,A60*B60/144*R60*1.5)) | T60: =COUNTIF(G60:J60,71) -> 0 | U60: =IF(A60="","",IF($N$4="M",A60*B60*0.000011111*T60*1.5,A60*B60/144*T60*1.5)) | V60: =COUNTIF(G60:J60,8) -> 0 | W60: =IF(A60="","",IF($N$4="M",(A60+B60)*2*0.0032808*V60,(A60+B60)*2*V60/12)) | X60: =COUNTIF(G60:J60,81) -> 0 | Y60: =IF(A60="","",IF($N$4="M",(A60+B60)*2*0.0032808*X60,(A60+B60)*2*X60/12)) | Z60: =COUNTIF(G60:J60,9) -> 0 | AA60: =COUNTIF(G60:J60,10) -> 0 | AB60: =IF(A60="","",IF($N$4="M",(A60+B60)*2*0.0032808*AA60,(A60+B60)*2*AA60/12)) | AC60: =COUNTIF(G60:J60,100) -> 0 | AE60: =COUNTIF(G60:J60,11) -> 0 | AF60: =IF(A60="","",IF($N$4="M",A60*B60*0.000011111*AE60,A60*B60/144*AE60)) | AG60: =COUNTIF(G60:J60,111) -> 0 | AH60: =IF(A60="","",IF($N$4="M",A60*B60*0.000011111*AG60,A60*B60/144*AG60)) | AI60: =COUNTIF(G60:J60,12) -> 0 | AJ60: =IF(A60="","",IF($N$4="M",A60*B60*0.000011111*AI60,A60*B60/144*AI60)) | AK60: =COUNTIF(G60:J60,13) -> 0 | AL60: =COUNTIF(G60:J60,131) -> 0 | AM60: =IF(A60="","",IF($N$4="M",A60*B60*0.000011111*AL60,A60*B60/144*AL60)) | AN60: =COUNTIF(G60:J60,14) -> 0 | AO60: =IF(A60="","",IF($N$4="M",A60*B60*0.000011111*AN60,A60*B60/144*AN60)) | AP60: =COUNTIF(G60:J60,141) -> 0 | AQ60: =IF(A60="","",IF($N$4="M",A60*B60*0.000011111*AP60,A60*B60/144*AP60)) | AR60: =COUNTIF(G60:J60,15) -> 0 | AS60: =COUNTIF(G60:J60,16) -> 0 | AT60: =IF(A60="","",IF($N$4="M",A60*B60*0.000011111*AS60,A60*B60/144*AS60)) | AU60: =IF(D60=61,C60,0) -> 0 | AV60: =IF(D60=61,L60,0) -> 0 | AW60: =IF(A60="","",(C60-AU60)) | AX60: =IF(A60="","",(L60-AV60))
A61: 900 | B61: 500 | C61: 2.9 | D61: 6 | E61: HP | F61: RE | G61: 21 | H61: 81 | I61: 71 | K61: =IF($N$4="M",IF(A61="","",IF(D61=6,16,IF(A61<=$M$5,26,IF(A61<=$M$6,24,IF(A61<=$M$7,22,IF(A61<=$M$8,20,18)))))),IF(A61="","",IF(D61=6,16,IF(A61<=$P$5,26,IF(A61<=$P$6,24,IF(A61<=$P$7,22,IF(A61<=$P$8,20,18))))))) | L61: =IF($N$4="M",IF(A61="","",IF(K61=26,(A61+B61+Q61)*C61*0.02739,IF(K61=24,(A61+B61+Q61)*C61*0.02739,IF(K61=22,(A61+B61+Q61)*C61*0.0333,IF(K61=20,(A61+B61+Q61)*C61*0.0393,IF(K61=18,(A61+B61+Q61)*C61*0.0511,IF(K61=16,(A61+B61+Q61)*C61*0.0628))))))),IF(A61="","",IF(K61=26,(A61+B61+Q61)*C61*0.211,IF(K61=24,(A61+B61+Q61)*C61*0.211,IF(K61=22,(A61+B61+Q61)*C61*0.258,IF(K61=20,(A61+B61+Q61)*C61*0.304,IF(K61=18,(A61+B61+Q61)*C61*0.395,IF(K61=16,(A61+B61+Q61)*C61*0.487)))))))) | M61: =IF(D61=1,0.5,IF(D61=2,"1 F",IF(D61=21,"1 R",IF(D61=3,2,"")))) | N61: =IF(M61="","",IF($N$4="M",(A61+B61+Q61)*C61*0.022,(A61+B61+Q61)*C61*0.17)) | O61: =IF(D61=4,1,IF(D61=5,2,"")) | P61: =IF(O61="","",IF($N$4="M",IF(O61=1,(A61+B61+Q61)*C61*0.022*1.1,(A61+B61+Q61)*C61*0.022*1.15),IF(O61=1,(A61+B61+Q61)*C61*0.17*1.1,(A61+B61+Q61)*C61*0.17*1.15))) | Q61: =IF($N$4="M",IF(A61="","",IF(D61=1,50,IF(D61=2,100,IF(D61=21,100,IF(D61=3,200,0))))),IF(A61="","",IF(D61=1,2,IF(D61=2,4,IF(D61=21,4,IF(D61=3,8,0)))))) | R61: =COUNTIF(G61:J61,7) -> 0 | S61: =IF(A61="","",IF($N$4="M",A61*B61*0.000011111*R61*1.5,A61*B61/144*R61*1.5)) | T61: =COUNTIF(G61:J61,71) -> 0 | U61: =IF(A61="","",IF($N$4="M",A61*B61*0.000011111*T61*1.5,A61*B61/144*T61*1.5)) | V61: =COUNTIF(G61:J61,8) -> 0 | W61: =IF(A61="","",IF($N$4="M",(A61+B61)*2*0.0032808*V61,(A61+B61)*2*V61/12)) | X61: =COUNTIF(G61:J61,81) -> 0 | Y61: =IF(A61="","",IF($N$4="M",(A61+B61)*2*0.0032808*X61,(A61+B61)*2*X61/12)) | Z61: =COUNTIF(G61:J61,9) -> 0 | AA61: =COUNTIF(G61:J61,10) -> 0 | AB61: =IF(A61="","",IF($N$4="M",(A61+B61)*2*0.0032808*AA61,(A61+B61)*2*AA61/12)) | AC61: =COUNTIF(G61:J61,100) -> 0 | AE61: =COUNTIF(G61:J61,11) -> 0 | AF61: =IF(A61="","",IF($N$4="M",A61*B61*0.000011111*AE61,A61*B61/144*AE61)) | AG61: =COUNTIF(G61:J61,111) -> 0 | AH61: =IF(A61="","",IF($N$4="M",A61*B61*0.000011111*AG61,A61*B61/144*AG61)) | AI61: =COUNTIF(G61:J61,12) -> 0 | AJ61: =IF(A61="","",IF($N$4="M",A61*B61*0.000011111*AI61,A61*B61/144*AI61)) | AK61: =COUNTIF(G61:J61,13) -> 0 | AL61: =COUNTIF(G61:J61,131) -> 0 | AM61: =IF(A61="","",IF($N$4="M",A61*B61*0.000011111*AL61,A61*B61/144*AL61)) | AN61: =COUNTIF(G61:J61,14) -> 0 | AO61: =IF(A61="","",IF($N$4="M",A61*B61*0.000011111*AN61,A61*B61/144*AN61)) | AP61: =COUNTIF(G61:J61,141) -> 0 | AQ61: =IF(A61="","",IF($N$4="M",A61*B61*0.000011111*AP61,A61*B61/144*AP61)) | AR61: =COUNTIF(G61:J61,15) -> 0 | AS61: =COUNTIF(G61:J61,16) -> 0 | AT61: =IF(A61="","",IF($N$4="M",A61*B61*0.000011111*AS61,A61*B61/144*AS61)) | AU61: =IF(D61=61,C61,0) -> 0 | AV61: =IF(D61=61,L61,0) -> 0 | AW61: =IF(A61="","",(C61-AU61)) | AX61: =IF(A61="","",(L61-AV61))
A62: 1200 | B62: 400 | C62: 2.5 | D62: 6 | E62: HP | F62: RE | G62: 71 | K62: =IF($N$4="M",IF(A62="","",IF(D62=6,16,IF(A62<=$M$5,26,IF(A62<=$M$6,24,IF(A62<=$M$7,22,IF(A62<=$M$8,20,18)))))),IF(A62="","",IF(D62=6,16,IF(A62<=$P$5,26,IF(A62<=$P$6,24,IF(A62<=$P$7,22,IF(A62<=$P$8,20,18))))))) | L62: =IF($N$4="M",IF(A62="","",IF(K62=26,(A62+B62+Q62)*C62*0.02739,IF(K62=24,(A62+B62+Q62)*C62*0.02739,IF(K62=22,(A62+B62+Q62)*C62*0.0333,IF(K62=20,(A62+B62+Q62)*C62*0.0393,IF(K62=18,(A62+B62+Q62)*C62*0.0511,IF(K62=16,(A62+B62+Q62)*C62*0.0628))))))),IF(A62="","",IF(K62=26,(A62+B62+Q62)*C62*0.211,IF(K62=24,(A62+B62+Q62)*C62*0.211,IF(K62=22,(A62+B62+Q62)*C62*0.258,IF(K62=20,(A62+B62+Q62)*C62*0.304,IF(K62=18,(A62+B62+Q62)*C62*0.395,IF(K62=16,(A62+B62+Q62)*C62*0.487)))))))) | M62: =IF(D62=1,0.5,IF(D62=2,"1 F",IF(D62=21,"1 R",IF(D62=3,2,"")))) | N62: =IF(M62="","",IF($N$4="M",(A62+B62+Q62)*C62*0.022,(A62+B62+Q62)*C62*0.17)) | O62: =IF(D62=4,1,IF(D62=5,2,"")) | P62: =IF(O62="","",IF($N$4="M",IF(O62=1,(A62+B62+Q62)*C62*0.022*1.1,(A62+B62+Q62)*C62*0.022*1.15),IF(O62=1,(A62+B62+Q62)*C62*0.17*1.1,(A62+B62+Q62)*C62*0.17*1.15))) | Q62: =IF($N$4="M",IF(A62="","",IF(D62=1,50,IF(D62=2,100,IF(D62=21,100,IF(D62=3,200,0))))),IF(A62="","",IF(D62=1,2,IF(D62=2,4,IF(D62=21,4,IF(D62=3,8,0)))))) | R62: =COUNTIF(G62:J62,7) -> 0 | S62: =IF(A62="","",IF($N$4="M",A62*B62*0.000011111*R62*1.5,A62*B62/144*R62*1.5)) | T62: =COUNTIF(G62:J62,71) -> 0 | U62: =IF(A62="","",IF($N$4="M",A62*B62*0.000011111*T62*1.5,A62*B62/144*T62*1.5)) | V62: =COUNTIF(G62:J62,8) -> 0 | W62: =IF(A62="","",IF($N$4="M",(A62+B62)*2*0.0032808*V62,(A62+B62)*2*V62/12)) | X62: =COUNTIF(G62:J62,81) -> 0 | Y62: =IF(A62="","",IF($N$4="M",(A62+B62)*2*0.0032808*X62,(A62+B62)*2*X62/12)) | Z62: =COUNTIF(G62:J62,9) -> 0 | AA62: =COUNTIF(G62:J62,10) -> 0 | AB62: =IF(A62="","",IF($N$4="M",(A62+B62)*2*0.0032808*AA62,(A62+B62)*2*AA62/12)) | AC62: =COUNTIF(G62:J62,100) -> 0 | AE62: =COUNTIF(G62:J62,11) -> 0 | AF62: =IF(A62="","",IF($N$4="M",A62*B62*0.000011111*AE62,A62*B62/144*AE62)) | AG62: =COUNTIF(G62:J62,111) -> 0 | AH62: =IF(A62="","",IF($N$4="M",A62*B62*0.000011111*AG62,A62*B62/144*AG62)) | AI62: =COUNTIF(G62:J62,12) -> 0 | AJ62: =IF(A62="","",IF($N$4="M",A62*B62*0.000011111*AI62,A62*B62/144*AI62)) | AK62: =COUNTIF(G62:J62,13) -> 0 | AL62: =COUNTIF(G62:J62,131) -> 0 | AM62: =IF(A62="","",IF($N$4="M",A62*B62*0.000011111*AL62,A62*B62/144*AL62)) | AN62: =COUNTIF(G62:J62,14) -> 0 | AO62: =IF(A62="","",IF($N$4="M",A62*B62*0.000011111*AN62,A62*B62/144*AN62)) | AP62: =COUNTIF(G62:J62,141) -> 0 | AQ62: =IF(A62="","",IF($N$4="M",A62*B62*0.000011111*AP62,A62*B62/144*AP62)) | AR62: =COUNTIF(G62:J62,15) -> 0 | AS62: =COUNTIF(G62:J62,16) -> 0 | AT62: =IF(A62="","",IF($N$4="M",A62*B62*0.000011111*AS62,A62*B62/144*AS62)) | AU62: =IF(D62=61,C62,0) -> 0 | AV62: =IF(D62=61,L62,0) -> 0 | AW62: =IF(A62="","",(C62-AU62)) | AX62: =IF(A62="","",(L62-AV62))
A63: 1500 | B63: 500 | C63: 0.5 | D63: 6 | E63: HP | F63: RE | K63: =IF($N$4="M",IF(A63="","",IF(D63=6,16,IF(A63<=$M$5,26,IF(A63<=$M$6,24,IF(A63<=$M$7,22,IF(A63<=$M$8,20,18)))))),IF(A63="","",IF(D63=6,16,IF(A63<=$P$5,26,IF(A63<=$P$6,24,IF(A63<=$P$7,22,IF(A63<=$P$8,20,18))))))) | L63: =IF($N$4="M",IF(A63="","",IF(K63=26,(A63+B63+Q63)*C63*0.02739,IF(K63=24,(A63+B63+Q63)*C63*0.02739,IF(K63=22,(A63+B63+Q63)*C63*0.0333,IF(K63=20,(A63+B63+Q63)*C63*0.0393,IF(K63=18,(A63+B63+Q63)*C63*0.0511,IF(K63=16,(A63+B63+Q63)*C63*0.0628))))))),IF(A63="","",IF(K63=26,(A63+B63+Q63)*C63*0.211,IF(K63=24,(A63+B63+Q63)*C63*0.211,IF(K63=22,(A63+B63+Q63)*C63*0.258,IF(K63=20,(A63+B63+Q63)*C63*0.304,IF(K63=18,(A63+B63+Q63)*C63*0.395,IF(K63=16,(A63+B63+Q63)*C63*0.487)))))))) | M63: =IF(D63=1,0.5,IF(D63=2,"1 F",IF(D63=21,"1 R",IF(D63=3,2,"")))) | N63: =IF(M63="","",IF($N$4="M",(A63+B63+Q63)*C63*0.022,(A63+B63+Q63)*C63*0.17)) | O63: =IF(D63=4,1,IF(D63=5,2,"")) | P63: =IF(O63="","",IF($N$4="M",IF(O63=1,(A63+B63+Q63)*C63*0.022*1.1,(A63+B63+Q63)*C63*0.022*1.15),IF(O63=1,(A63+B63+Q63)*C63*0.17*1.1,(A63+B63+Q63)*C63*0.17*1.15))) | Q63: =IF($N$4="M",IF(A63="","",IF(D63=1,50,IF(D63=2,100,IF(D63=21,100,IF(D63=3,200,0))))),IF(A63="","",IF(D63=1,2,IF(D63=2,4,IF(D63=21,4,IF(D63=3,8,0)))))) | R63: =COUNTIF(G63:J63,7) -> 0 | S63: =IF(A63="","",IF($N$4="M",A63*B63*0.000011111*R63*1.5,A63*B63/144*R63*1.5)) | T63: =COUNTIF(G63:J63,71) -> 0 | U63: =IF(A63="","",IF($N$4="M",A63*B63*0.000011111*T63*1.5,A63*B63/144*T63*1.5)) | V63: =COUNTIF(G63:J63,8) -> 0 | W63: =IF(A63="","",IF($N$4="M",(A63+B63)*2*0.0032808*V63,(A63+B63)*2*V63/12)) | X63: =COUNTIF(G63:J63,81) -> 0 | Y63: =IF(A63="","",IF($N$4="M",(A63+B63)*2*0.0032808*X63,(A63+B63)*2*X63/12)) | Z63: =COUNTIF(G63:J63,9) -> 0 | AA63: =COUNTIF(G63:J63,10) -> 0 | AB63: =IF(A63="","",IF($N$4="M",(A63+B63)*2*0.0032808*AA63,(A63+B63)*2*AA63/12)) | AC63: =COUNTIF(G63:J63,100) -> 0 | AE63: =COUNTIF(G63:J63,11) -> 0 | AF63: =IF(A63="","",IF($N$4="M",A63*B63*0.000011111*AE63,A63*B63/144*AE63)) | AG63: =COUNTIF(G63:J63,111) -> 0 | AH63: =IF(A63="","",IF($N$4="M",A63*B63*0.000011111*AG63,A63*B63/144*AG63)) | AI63: =COUNTIF(G63:J63,12) -> 0 | AJ63: =IF(A63="","",IF($N$4="M",A63*B63*0.000011111*AI63,A63*B63/144*AI63)) | AK63: =COUNTIF(G63:J63,13) -> 0 | AL63: =COUNTIF(G63:J63,131) -> 0 | AM63: =IF(A63="","",IF($N$4="M",A63*B63*0.000011111*AL63,A63*B63/144*AL63)) | AN63: =COUNTIF(G63:J63,14) -> 0 | AO63: =IF(A63="","",IF($N$4="M",A63*B63*0.000011111*AN63,A63*B63/144*AN63)) | AP63: =COUNTIF(G63:J63,141) -> 0 | AQ63: =IF(A63="","",IF($N$4="M",A63*B63*0.000011111*AP63,A63*B63/144*AP63)) | AR63: =COUNTIF(G63:J63,15) -> 0 | AS63: =COUNTIF(G63:J63,16) -> 0 | AT63: =IF(A63="","",IF($N$4="M",A63*B63*0.000011111*AS63,A63*B63/144*AS63)) | AU63: =IF(D63=61,C63,0) -> 0 | AV63: =IF(D63=61,L63,0) -> 0 | AW63: =IF(A63="","",(C63-AU63)) | AX63: =IF(A63="","",(L63-AV63))
A64: 150 | B64: 150 | C64: 12.8 | F64: HA | G64: 7 | H64: 13 | K64: =IF($N$4="M",IF(A64="","",IF(D64=6,16,IF(A64<=$M$5,26,IF(A64<=$M$6,24,IF(A64<=$M$7,22,IF(A64<=$M$8,20,18)))))),IF(A64="","",IF(D64=6,16,IF(A64<=$P$5,26,IF(A64<=$P$6,24,IF(A64<=$P$7,22,IF(A64<=$P$8,20,18))))))) | L64: =IF($N$4="M",IF(A64="","",IF(K64=26,(A64+B64+Q64)*C64*0.02739,IF(K64=24,(A64+B64+Q64)*C64*0.02739,IF(K64=22,(A64+B64+Q64)*C64*0.0333,IF(K64=20,(A64+B64+Q64)*C64*0.0393,IF(K64=18,(A64+B64+Q64)*C64*0.0511,IF(K64=16,(A64+B64+Q64)*C64*0.0628))))))),IF(A64="","",IF(K64=26,(A64+B64+Q64)*C64*0.211,IF(K64=24,(A64+B64+Q64)*C64*0.211,IF(K64=22,(A64+B64+Q64)*C64*0.258,IF(K64=20,(A64+B64+Q64)*C64*0.304,IF(K64=18,(A64+B64+Q64)*C64*0.395,IF(K64=16,(A64+B64+Q64)*C64*0.487)))))))) | M64: =IF(D64=1,0.5,IF(D64=2,"1 F",IF(D64=21,"1 R",IF(D64=3,2,"")))) | N64: =IF(M64="","",IF($N$4="M",(A64+B64+Q64)*C64*0.022,(A64+B64+Q64)*C64*0.17)) | O64: =IF(D64=4,1,IF(D64=5,2,"")) | P64: =IF(O64="","",IF($N$4="M",IF(O64=1,(A64+B64+Q64)*C64*0.022*1.1,(A64+B64+Q64)*C64*0.022*1.15),IF(O64=1,(A64+B64+Q64)*C64*0.17*1.1,(A64+B64+Q64)*C64*0.17*1.15))) | Q64: =IF($N$4="M",IF(A64="","",IF(D64=1,50,IF(D64=2,100,IF(D64=21,100,IF(D64=3,200,0))))),IF(A64="","",IF(D64=1,2,IF(D64=2,4,IF(D64=21,4,IF(D64=3,8,0)))))) | R64: =COUNTIF(G64:J64,7) -> 0 | S64: =IF(A64="","",IF($N$4="M",A64*B64*0.000011111*R64*1.5,A64*B64/144*R64*1.5)) | T64: =COUNTIF(G64:J64,71) -> 0 | U64: =IF(A64="","",IF($N$4="M",A64*B64*0.000011111*T64*1.5,A64*B64/144*T64*1.5)) | V64: =COUNTIF(G64:J64,8) -> 0 | W64: =IF(A64="","",IF($N$4="M",(A64+B64)*2*0.0032808*V64,(A64+B64)*2*V64/12)) | X64: =COUNTIF(G64:J64,81) -> 0 | Y64: =IF(A64="","",IF($N$4="M",(A64+B64)*2*0.0032808*X64,(A64+B64)*2*X64/12)) | Z64: =COUNTIF(G64:J64,9) -> 0 | AA64: =COUNTIF(G64:J64,10) -> 0 | AB64: =IF(A64="","",IF($N$4="M",(A64+B64)*2*0.0032808*AA64,(A64+B64)*2*AA64/12)) | AC64: =COUNTIF(G64:J64,100) -> 0 | AE64: =COUNTIF(G64:J64,11) -> 0 | AF64: =IF(A64="","",IF($N$4="M",A64*B64*0.000011111*AE64,A64*B64/144*AE64)) | AG64: =COUNTIF(G64:J64,111) -> 0 | AH64: =IF(A64="","",IF($N$4="M",A64*B64*0.000011111*AG64,A64*B64/144*AG64)) | AI64: =COUNTIF(G64:J64,12) -> 0 | AJ64: =IF(A64="","",IF($N$4="M",A64*B64*0.000011111*AI64,A64*B64/144*AI64)) | AK64: =COUNTIF(G64:J64,13) -> 0 | AL64: =COUNTIF(G64:J64,131) -> 0 | AM64: =IF(A64="","",IF($N$4="M",A64*B64*0.000011111*AL64,A64*B64/144*AL64)) | AN64: =COUNTIF(G64:J64,14) -> 0 | AO64: =IF(A64="","",IF($N$4="M",A64*B64*0.000011111*AN64,A64*B64/144*AN64)) | AP64: =COUNTIF(G64:J64,141) -> 0 | AQ64: =IF(A64="","",IF($N$4="M",A64*B64*0.000011111*AP64,A64*B64/144*AP64)) | AR64: =COUNTIF(G64:J64,15) -> 0 | AS64: =COUNTIF(G64:J64,16) -> 0 | AT64: =IF(A64="","",IF($N$4="M",A64*B64*0.000011111*AS64,A64*B64/144*AS64)) | AU64: =IF(D64=61,C64,0) -> 0 | AV64: =IF(D64=61,L64,0) -> 0 | AW64: =IF(A64="","",(C64-AU64)) | AX64: =IF(A64="","",(L64-AV64))
A65: 2000 | B65: 300 | C65: 0.3 | F65: RE | K65: =IF($N$4="M",IF(A65="","",IF(D65=6,16,IF(A65<=$M$5,26,IF(A65<=$M$6,24,IF(A65<=$M$7,22,IF(A65<=$M$8,20,18)))))),IF(A65="","",IF(D65=6,16,IF(A65<=$P$5,26,IF(A65<=$P$6,24,IF(A65<=$P$7,22,IF(A65<=$P$8,20,18))))))) | L65: =IF($N$4="M",IF(A65="","",IF(K65=26,(A65+B65+Q65)*C65*0.02739,IF(K65=24,(A65+B65+Q65)*C65*0.02739,IF(K65=22,(A65+B65+Q65)*C65*0.0333,IF(K65=20,(A65+B65+Q65)*C65*0.0393,IF(K65=18,(A65+B65+Q65)*C65*0.0511,IF(K65=16,(A65+B65+Q65)*C65*0.0628))))))),IF(A65="","",IF(K65=26,(A65+B65+Q65)*C65*0.211,IF(K65=24,(A65+B65+Q65)*C65*0.211,IF(K65=22,(A65+B65+Q65)*C65*0.258,IF(K65=20,(A65+B65+Q65)*C65*0.304,IF(K65=18,(A65+B65+Q65)*C65*0.395,IF(K65=16,(A65+B65+Q65)*C65*0.487)))))))) | M65: =IF(D65=1,0.5,IF(D65=2,"1 F",IF(D65=21,"1 R",IF(D65=3,2,"")))) | N65: =IF(M65="","",IF($N$4="M",(A65+B65+Q65)*C65*0.022,(A65+B65+Q65)*C65*0.17)) | O65: =IF(D65=4,1,IF(D65=5,2,"")) | P65: =IF(O65="","",IF($N$4="M",IF(O65=1,(A65+B65+Q65)*C65*0.022*1.1,(A65+B65+Q65)*C65*0.022*1.15),IF(O65=1,(A65+B65+Q65)*C65*0.17*1.1,(A65+B65+Q65)*C65*0.17*1.15))) | Q65: =IF($N$4="M",IF(A65="","",IF(D65=1,50,IF(D65=2,100,IF(D65=21,100,IF(D65=3,200,0))))),IF(A65="","",IF(D65=1,2,IF(D65=2,4,IF(D65=21,4,IF(D65=3,8,0)))))) | R65: =COUNTIF(G65:J65,7) -> 0 | S65: =IF(A65="","",IF($N$4="M",A65*B65*0.000011111*R65*1.5,A65*B65/144*R65*1.5)) | T65: =COUNTIF(G65:J65,71) -> 0 | U65: =IF(A65="","",IF($N$4="M",A65*B65*0.000011111*T65*1.5,A65*B65/144*T65*1.5)) | V65: =COUNTIF(G65:J65,8) -> 0 | W65: =IF(A65="","",IF($N$4="M",(A65+B65)*2*0.0032808*V65,(A65+B65)*2*V65/12)) | X65: =COUNTIF(G65:J65,81) -> 0 | Y65: =IF(A65="","",IF($N$4="M",(A65+B65)*2*0.0032808*X65,(A65+B65)*2*X65/12)) | Z65: =COUNTIF(G65:J65,9) -> 0 | AA65: =COUNTIF(G65:J65,10) -> 0 | AB65: =IF(A65="","",IF($N$4="M",(A65+B65)*2*0.0032808*AA65,(A65+B65)*2*AA65/12)) | AC65: =COUNTIF(G65:J65,100) -> 0 | AE65: =COUNTIF(G65:J65,11) -> 0 | AF65: =IF(A65="","",IF($N$4="M",A65*B65*0.000011111*AE65,A65*B65/144*AE65)) | AG65: =COUNTIF(G65:J65,111) -> 0 | AH65: =IF(A65="","",IF($N$4="M",A65*B65*0.000011111*AG65,A65*B65/144*AG65)) | AI65: =COUNTIF(G65:J65,12) -> 0 | AJ65: =IF(A65="","",IF($N$4="M",A65*B65*0.000011111*AI65,A65*B65/144*AI65)) | AK65: =COUNTIF(G65:J65,13) -> 0 | AL65: =COUNTIF(G65:J65,131) -> 0 | AM65: =IF(A65="","",IF($N$4="M",A65*B65*0.000011111*AL65,A65*B65/144*AL65)) | AN65: =COUNTIF(G65:J65,14) -> 0 | AO65: =IF(A65="","",IF($N$4="M",A65*B65*0.000011111*AN65,A65*B65/144*AN65)) | AP65: =COUNTIF(G65:J65,141) -> 0 | AQ65: =IF(A65="","",IF($N$4="M",A65*B65*0.000011111*AP65,A65*B65/144*AP65)) | AR65: =COUNTIF(G65:J65,15) -> 0 | AS65: =COUNTIF(G65:J65,16) -> 0 | AT65: =IF(A65="","",IF($N$4="M",A65*B65*0.000011111*AS65,A65*B65/144*AS65)) | AU65: =IF(D65=61,C65,0) -> 0 | AV65: =IF(D65=61,L65,0) -> 0 | AW65: =IF(A65="","",(C65-AU65)) | AX65: =IF(A65="","",(L65-AV65))
A66: 2000 | B66: 500 | C66: 0.7 | D66: 6 | E66: HP | F66: RE | K66: =IF($N$4="M",IF(A66="","",IF(D66=6,16,IF(A66<=$M$5,26,IF(A66<=$M$6,24,IF(A66<=$M$7,22,IF(A66<=$M$8,20,18)))))),IF(A66="","",IF(D66=6,16,IF(A66<=$P$5,26,IF(A66<=$P$6,24,IF(A66<=$P$7,22,IF(A66<=$P$8,20,18))))))) | L66: =IF($N$4="M",IF(A66="","",IF(K66=26,(A66+B66+Q66)*C66*0.02739,IF(K66=24,(A66+B66+Q66)*C66*0.02739,IF(K66=22,(A66+B66+Q66)*C66*0.0333,IF(K66=20,(A66+B66+Q66)*C66*0.0393,IF(K66=18,(A66+B66+Q66)*C66*0.0511,IF(K66=16,(A66+B66+Q66)*C66*0.0628))))))),IF(A66="","",IF(K66=26,(A66+B66+Q66)*C66*0.211,IF(K66=24,(A66+B66+Q66)*C66*0.211,IF(K66=22,(A66+B66+Q66)*C66*0.258,IF(K66=20,(A66+B66+Q66)*C66*0.304,IF(K66=18,(A66+B66+Q66)*C66*0.395,IF(K66=16,(A66+B66+Q66)*C66*0.487)))))))) | M66: =IF(D66=1,0.5,IF(D66=2,"1 F",IF(D66=21,"1 R",IF(D66=3,2,"")))) | N66: =IF(M66="","",IF($N$4="M",(A66+B66+Q66)*C66*0.022,(A66+B66+Q66)*C66*0.17)) | O66: =IF(D66=4,1,IF(D66=5,2,"")) | P66: =IF(O66="","",IF($N$4="M",IF(O66=1,(A66+B66+Q66)*C66*0.022*1.1,(A66+B66+Q66)*C66*0.022*1.15),IF(O66=1,(A66+B66+Q66)*C66*0.17*1.1,(A66+B66+Q66)*C66*0.17*1.15))) | Q66: =IF($N$4="M",IF(A66="","",IF(D66=1,50,IF(D66=2,100,IF(D66=21,100,IF(D66=3,200,0))))),IF(A66="","",IF(D66=1,2,IF(D66=2,4,IF(D66=21,4,IF(D66=3,8,0)))))) | R66: =COUNTIF(G66:J66,7) -> 0 | S66: =IF(A66="","",IF($N$4="M",A66*B66*0.000011111*R66*1.5,A66*B66/144*R66*1.5)) | T66: =COUNTIF(G66:J66,71) -> 0 | U66: =IF(A66="","",IF($N$4="M",A66*B66*0.000011111*T66*1.5,A66*B66/144*T66*1.5)) | V66: =COUNTIF(G66:J66,8) -> 0 | W66: =IF(A66="","",IF($N$4="M",(A66+B66)*2*0.0032808*V66,(A66+B66)*2*V66/12)) | X66: =COUNTIF(G66:J66,81) -> 0 | Y66: =IF(A66="","",IF($N$4="M",(A66+B66)*2*0.0032808*X66,(A66+B66)*2*X66/12)) | Z66: =COUNTIF(G66:J66,9) -> 0 | AA66: =COUNTIF(G66:J66,10) -> 0 | AB66: =IF(A66="","",IF($N$4="M",(A66+B66)*2*0.0032808*AA66,(A66+B66)*2*AA66/12)) | AC66: =COUNTIF(G66:J66,100) -> 0 | AE66: =COUNTIF(G66:J66,11) -> 0 | AF66: =IF(A66="","",IF($N$4="M",A66*B66*0.000011111*AE66,A66*B66/144*AE66)) | AG66: =COUNTIF(G66:J66,111) -> 0 | AH66: =IF(A66="","",IF($N$4="M",A66*B66*0.000011111*AG66,A66*B66/144*AG66)) | AI66: =COUNTIF(G66:J66,12) -> 0 | AJ66: =IF(A66="","",IF($N$4="M",A66*B66*0.000011111*AI66,A66*B66/144*AI66)) | AK66: =COUNTIF(G66:J66,13) -> 0 | AL66: =COUNTIF(G66:J66,131) -> 0 | AM66: =IF(A66="","",IF($N$4="M",A66*B66*0.000011111*AL66,A66*B66/144*AL66)) | AN66: =COUNTIF(G66:J66,14) -> 0 | AO66: =IF(A66="","",IF($N$4="M",A66*B66*0.000011111*AN66,A66*B66/144*AN66)) | AP66: =COUNTIF(G66:J66,141) -> 0 | AQ66: =IF(A66="","",IF($N$4="M",A66*B66*0.000011111*AP66,A66*B66/144*AP66)) | AR66: =COUNTIF(G66:J66,15) -> 0 | AS66: =COUNTIF(G66:J66,16) -> 0 | AT66: =IF(A66="","",IF($N$4="M",A66*B66*0.000011111*AS66,A66*B66/144*AS66)) | AU66: =IF(D66=61,C66,0) -> 0 | AV66: =IF(D66=61,L66,0) -> 0 | AW66: =IF(A66="","",(C66-AU66)) | AX66: =IF(A66="","",(L66-AV66))
A67: 200 | B67: 150 | C67: 11.2 | F67: HA | K67: =IF($N$4="M",IF(A67="","",IF(D67=6,16,IF(A67<=$M$5,26,IF(A67<=$M$6,24,IF(A67<=$M$7,22,IF(A67<=$M$8,20,18)))))),IF(A67="","",IF(D67=6,16,IF(A67<=$P$5,26,IF(A67<=$P$6,24,IF(A67<=$P$7,22,IF(A67<=$P$8,20,18))))))) | L67: =IF($N$4="M",IF(A67="","",IF(K67=26,(A67+B67+Q67)*C67*0.02739,IF(K67=24,(A67+B67+Q67)*C67*0.02739,IF(K67=22,(A67+B67+Q67)*C67*0.0333,IF(K67=20,(A67+B67+Q67)*C67*0.0393,IF(K67=18,(A67+B67+Q67)*C67*0.0511,IF(K67=16,(A67+B67+Q67)*C67*0.0628))))))),IF(A67="","",IF(K67=26,(A67+B67+Q67)*C67*0.211,IF(K67=24,(A67+B67+Q67)*C67*0.211,IF(K67=22,(A67+B67+Q67)*C67*0.258,IF(K67=20,(A67+B67+Q67)*C67*0.304,IF(K67=18,(A67+B67+Q67)*C67*0.395,IF(K67=16,(A67+B67+Q67)*C67*0.487)))))))) | M67: =IF(D67=1,0.5,IF(D67=2,"1 F",IF(D67=21,"1 R",IF(D67=3,2,"")))) | N67: =IF(M67="","",IF($N$4="M",(A67+B67+Q67)*C67*0.022,(A67+B67+Q67)*C67*0.17)) | O67: =IF(D67=4,1,IF(D67=5,2,"")) | P67: =IF(O67="","",IF($N$4="M",IF(O67=1,(A67+B67+Q67)*C67*0.022*1.1,(A67+B67+Q67)*C67*0.022*1.15),IF(O67=1,(A67+B67+Q67)*C67*0.17*1.1,(A67+B67+Q67)*C67*0.17*1.15))) | Q67: =IF($N$4="M",IF(A67="","",IF(D67=1,50,IF(D67=2,100,IF(D67=21,100,IF(D67=3,200,0))))),IF(A67="","",IF(D67=1,2,IF(D67=2,4,IF(D67=21,4,IF(D67=3,8,0)))))) | R67: =COUNTIF(G67:J67,7) -> 0 | S67: =IF(A67="","",IF($N$4="M",A67*B67*0.000011111*R67*1.5,A67*B67/144*R67*1.5)) | T67: =COUNTIF(G67:J67,71) -> 0 | U67: =IF(A67="","",IF($N$4="M",A67*B67*0.000011111*T67*1.5,A67*B67/144*T67*1.5)) | V67: =COUNTIF(G67:J67,8) -> 0 | W67: =IF(A67="","",IF($N$4="M",(A67+B67)*2*0.0032808*V67,(A67+B67)*2*V67/12)) | X67: =COUNTIF(G67:J67,81) -> 0 | Y67: =IF(A67="","",IF($N$4="M",(A67+B67)*2*0.0032808*X67,(A67+B67)*2*X67/12)) | Z67: =COUNTIF(G67:J67,9) -> 0 | AA67: =COUNTIF(G67:J67,10) -> 0 | AB67: =IF(A67="","",IF($N$4="M",(A67+B67)*2*0.0032808*AA67,(A67+B67)*2*AA67/12)) | AC67: =COUNTIF(G67:J67,100) -> 0 | AE67: =COUNTIF(G67:J67,11) -> 0 | AF67: =IF(A67="","",IF($N$4="M",A67*B67*0.000011111*AE67,A67*B67/144*AE67)) | AG67: =COUNTIF(G67:J67,111) -> 0 | AH67: =IF(A67="","",IF($N$4="M",A67*B67*0.000011111*AG67,A67*B67/144*AG67)) | AI67: =COUNTIF(G67:J67,12) -> 0 | AJ67: =IF(A67="","",IF($N$4="M",A67*B67*0.000011111*AI67,A67*B67/144*AI67)) | AK67: =COUNTIF(G67:J67,13) -> 0 | AL67: =COUNTIF(G67:J67,131) -> 0 | AM67: =IF(A67="","",IF($N$4="M",A67*B67*0.000011111*AL67,A67*B67/144*AL67)) | AN67: =COUNTIF(G67:J67,14) -> 0 | AO67: =IF(A67="","",IF($N$4="M",A67*B67*0.000011111*AN67,A67*B67/144*AN67)) | AP67: =COUNTIF(G67:J67,141) -> 0 | AQ67: =IF(A67="","",IF($N$4="M",A67*B67*0.000011111*AP67,A67*B67/144*AP67)) | AR67: =COUNTIF(G67:J67,15) -> 0 | AS67: =COUNTIF(G67:J67,16) -> 0 | AT67: =IF(A67="","",IF($N$4="M",A67*B67*0.000011111*AS67,A67*B67/144*AS67)) | AU67: =IF(D67=61,C67,0) -> 0 | AV67: =IF(D67=61,L67,0) -> 0 | AW67: =IF(A67="","",(C67-AU67)) | AX67: =IF(A67="","",(L67-AV67))
A68: 200 | B68: 200 | C68: 0.2 | F68: HA | K68: =IF($N$4="M",IF(A68="","",IF(D68=6,16,IF(A68<=$M$5,26,IF(A68<=$M$6,24,IF(A68<=$M$7,22,IF(A68<=$M$8,20,18)))))),IF(A68="","",IF(D68=6,16,IF(A68<=$P$5,26,IF(A68<=$P$6,24,IF(A68<=$P$7,22,IF(A68<=$P$8,20,18))))))) | L68: =IF($N$4="M",IF(A68="","",IF(K68=26,(A68+B68+Q68)*C68*0.02739,IF(K68=24,(A68+B68+Q68)*C68*0.02739,IF(K68=22,(A68+B68+Q68)*C68*0.0333,IF(K68=20,(A68+B68+Q68)*C68*0.0393,IF(K68=18,(A68+B68+Q68)*C68*0.0511,IF(K68=16,(A68+B68+Q68)*C68*0.0628))))))),IF(A68="","",IF(K68=26,(A68+B68+Q68)*C68*0.211,IF(K68=24,(A68+B68+Q68)*C68*0.211,IF(K68=22,(A68+B68+Q68)*C68*0.258,IF(K68=20,(A68+B68+Q68)*C68*0.304,IF(K68=18,(A68+B68+Q68)*C68*0.395,IF(K68=16,(A68+B68+Q68)*C68*0.487)))))))) | M68: =IF(D68=1,0.5,IF(D68=2,"1 F",IF(D68=21,"1 R",IF(D68=3,2,"")))) | N68: =IF(M68="","",IF($N$4="M",(A68+B68+Q68)*C68*0.022,(A68+B68+Q68)*C68*0.17)) | O68: =IF(D68=4,1,IF(D68=5,2,"")) | P68: =IF(O68="","",IF($N$4="M",IF(O68=1,(A68+B68+Q68)*C68*0.022*1.1,(A68+B68+Q68)*C68*0.022*1.15),IF(O68=1,(A68+B68+Q68)*C68*0.17*1.1,(A68+B68+Q68)*C68*0.17*1.15))) | Q68: =IF($N$4="M",IF(A68="","",IF(D68=1,50,IF(D68=2,100,IF(D68=21,100,IF(D68=3,200,0))))),IF(A68="","",IF(D68=1,2,IF(D68=2,4,IF(D68=21,4,IF(D68=3,8,0)))))) | R68: =COUNTIF(G68:J68,7) -> 0 | S68: =IF(A68="","",IF($N$4="M",A68*B68*0.000011111*R68*1.5,A68*B68/144*R68*1.5)) | T68: =COUNTIF(G68:J68,71) -> 0 | U68: =IF(A68="","",IF($N$4="M",A68*B68*0.000011111*T68*1.5,A68*B68/144*T68*1.5)) | V68: =COUNTIF(G68:J68,8) -> 0 | W68: =IF(A68="","",IF($N$4="M",(A68+B68)*2*0.0032808*V68,(A68+B68)*2*V68/12)) | X68: =COUNTIF(G68:J68,81) -> 0 | Y68: =IF(A68="","",IF($N$4="M",(A68+B68)*2*0.0032808*X68,(A68+B68)*2*X68/12)) | Z68: =COUNTIF(G68:J68,9) -> 0 | AA68: =COUNTIF(G68:J68,10) -> 0 | AB68: =IF(A68="","",IF($N$4="M",(A68+B68)*2*0.0032808*AA68,(A68+B68)*2*AA68/12)) | AC68: =COUNTIF(G68:J68,100) -> 0 | AE68: =COUNTIF(G68:J68,11) -> 0 | AF68: =IF(A68="","",IF($N$4="M",A68*B68*0.000011111*AE68,A68*B68/144*AE68)) | AG68: =COUNTIF(G68:J68,111) -> 0 | AH68: =IF(A68="","",IF($N$4="M",A68*B68*0.000011111*AG68,A68*B68/144*AG68)) | AI68: =COUNTIF(G68:J68,12) -> 0 | AJ68: =IF(A68="","",IF($N$4="M",A68*B68*0.000011111*AI68,A68*B68/144*AI68)) | AK68: =COUNTIF(G68:J68,13) -> 0 | AL68: =COUNTIF(G68:J68,131) -> 0 | AM68: =IF(A68="","",IF($N$4="M",A68*B68*0.000011111*AL68,A68*B68/144*AL68)) | AN68: =COUNTIF(G68:J68,14) -> 0 | AO68: =IF(A68="","",IF($N$4="M",A68*B68*0.000011111*AN68,A68*B68/144*AN68)) | AP68: =COUNTIF(G68:J68,141) -> 0 | AQ68: =IF(A68="","",IF($N$4="M",A68*B68*0.000011111*AP68,A68*B68/144*AP68)) | AR68: =COUNTIF(G68:J68,15) -> 0 | AS68: =COUNTIF(G68:J68,16) -> 0 | AT68: =IF(A68="","",IF($N$4="M",A68*B68*0.000011111*AS68,A68*B68/144*AS68)) | AU68: =IF(D68=61,C68,0) -> 0 | AV68: =IF(D68=61,L68,0) -> 0 | AW68: =IF(A68="","",(C68-AU68)) | AX68: =IF(A68="","",(L68-AV68))
A69: 2025 | B69: 500 | C69: 0.5 | D69: 6 | E69: HP | F69: RE | K69: =IF($N$4="M",IF(A69="","",IF(D69=6,16,IF(A69<=$M$5,26,IF(A69<=$M$6,24,IF(A69<=$M$7,22,IF(A69<=$M$8,20,18)))))),IF(A69="","",IF(D69=6,16,IF(A69<=$P$5,26,IF(A69<=$P$6,24,IF(A69<=$P$7,22,IF(A69<=$P$8,20,18))))))) | L69: =IF($N$4="M",IF(A69="","",IF(K69=26,(A69+B69+Q69)*C69*0.02739,IF(K69=24,(A69+B69+Q69)*C69*0.02739,IF(K69=22,(A69+B69+Q69)*C69*0.0333,IF(K69=20,(A69+B69+Q69)*C69*0.0393,IF(K69=18,(A69+B69+Q69)*C69*0.0511,IF(K69=16,(A69+B69+Q69)*C69*0.0628))))))),IF(A69="","",IF(K69=26,(A69+B69+Q69)*C69*0.211,IF(K69=24,(A69+B69+Q69)*C69*0.211,IF(K69=22,(A69+B69+Q69)*C69*0.258,IF(K69=20,(A69+B69+Q69)*C69*0.304,IF(K69=18,(A69+B69+Q69)*C69*0.395,IF(K69=16,(A69+B69+Q69)*C69*0.487)))))))) | M69: =IF(D69=1,0.5,IF(D69=2,"1 F",IF(D69=21,"1 R",IF(D69=3,2,"")))) | N69: =IF(M69="","",IF($N$4="M",(A69+B69+Q69)*C69*0.022,(A69+B69+Q69)*C69*0.17)) | O69: =IF(D69=4,1,IF(D69=5,2,"")) | P69: =IF(O69="","",IF($N$4="M",IF(O69=1,(A69+B69+Q69)*C69*0.022*1.1,(A69+B69+Q69)*C69*0.022*1.15),IF(O69=1,(A69+B69+Q69)*C69*0.17*1.1,(A69+B69+Q69)*C69*0.17*1.15))) | Q69: =IF($N$4="M",IF(A69="","",IF(D69=1,50,IF(D69=2,100,IF(D69=21,100,IF(D69=3,200,0))))),IF(A69="","",IF(D69=1,2,IF(D69=2,4,IF(D69=21,4,IF(D69=3,8,0)))))) | R69: =COUNTIF(G69:J69,7) -> 0 | S69: =IF(A69="","",IF($N$4="M",A69*B69*0.000011111*R69*1.5,A69*B69/144*R69*1.5)) | T69: =COUNTIF(G69:J69,71) -> 0 | U69: =IF(A69="","",IF($N$4="M",A69*B69*0.000011111*T69*1.5,A69*B69/144*T69*1.5)) | V69: =COUNTIF(G69:J69,8) -> 0 | W69: =IF(A69="","",IF($N$4="M",(A69+B69)*2*0.0032808*V69,(A69+B69)*2*V69/12)) | X69: =COUNTIF(G69:J69,81) -> 0 | Y69: =IF(A69="","",IF($N$4="M",(A69+B69)*2*0.0032808*X69,(A69+B69)*2*X69/12)) | Z69: =COUNTIF(G69:J69,9) -> 0 | AA69: =COUNTIF(G69:J69,10) -> 0 | AB69: =IF(A69="","",IF($N$4="M",(A69+B69)*2*0.0032808*AA69,(A69+B69)*2*AA69/12)) | AC69: =COUNTIF(G69:J69,100) -> 0 | AE69: =COUNTIF(G69:J69,11) -> 0 | AF69: =IF(A69="","",IF($N$4="M",A69*B69*0.000011111*AE69,A69*B69/144*AE69)) | AG69: =COUNTIF(G69:J69,111) -> 0 | AH69: =IF(A69="","",IF($N$4="M",A69*B69*0.000011111*AG69,A69*B69/144*AG69)) | AI69: =COUNTIF(G69:J69,12) -> 0 | AJ69: =IF(A69="","",IF($N$4="M",A69*B69*0.000011111*AI69,A69*B69/144*AI69)) | AK69: =COUNTIF(G69:J69,13) -> 0 | AL69: =COUNTIF(G69:J69,131) -> 0 | AM69: =IF(A69="","",IF($N$4="M",A69*B69*0.000011111*AL69,A69*B69/144*AL69)) | AN69: =COUNTIF(G69:J69,14) -> 0 | AO69: =IF(A69="","",IF($N$4="M",A69*B69*0.000011111*AN69,A69*B69/144*AN69)) | AP69: =COUNTIF(G69:J69,141) -> 0 | AQ69: =IF(A69="","",IF($N$4="M",A69*B69*0.000011111*AP69,A69*B69/144*AP69)) | AR69: =COUNTIF(G69:J69,15) -> 0 | AS69: =COUNTIF(G69:J69,16) -> 0 | AT69: =IF(A69="","",IF($N$4="M",A69*B69*0.000011111*AS69,A69*B69/144*AS69)) | AU69: =IF(D69=61,C69,0) -> 0 | AV69: =IF(D69=61,L69,0) -> 0 | AW69: =IF(A69="","",(C69-AU69)) | AX69: =IF(A69="","",(L69-AV69))
A70: 300 | B70: 200 | C70: 7.3 | F70: HA | K70: =IF($N$4="M",IF(A70="","",IF(D70=6,16,IF(A70<=$M$5,26,IF(A70<=$M$6,24,IF(A70<=$M$7,22,IF(A70<=$M$8,20,18)))))),IF(A70="","",IF(D70=6,16,IF(A70<=$P$5,26,IF(A70<=$P$6,24,IF(A70<=$P$7,22,IF(A70<=$P$8,20,18))))))) | L70: =IF($N$4="M",IF(A70="","",IF(K70=26,(A70+B70+Q70)*C70*0.02739,IF(K70=24,(A70+B70+Q70)*C70*0.02739,IF(K70=22,(A70+B70+Q70)*C70*0.0333,IF(K70=20,(A70+B70+Q70)*C70*0.0393,IF(K70=18,(A70+B70+Q70)*C70*0.0511,IF(K70=16,(A70+B70+Q70)*C70*0.0628))))))),IF(A70="","",IF(K70=26,(A70+B70+Q70)*C70*0.211,IF(K70=24,(A70+B70+Q70)*C70*0.211,IF(K70=22,(A70+B70+Q70)*C70*0.258,IF(K70=20,(A70+B70+Q70)*C70*0.304,IF(K70=18,(A70+B70+Q70)*C70*0.395,IF(K70=16,(A70+B70+Q70)*C70*0.487)))))))) | M70: =IF(D70=1,0.5,IF(D70=2,"1 F",IF(D70=21,"1 R",IF(D70=3,2,"")))) | N70: =IF(M70="","",IF($N$4="M",(A70+B70+Q70)*C70*0.022,(A70+B70+Q70)*C70*0.17)) | O70: =IF(D70=4,1,IF(D70=5,2,"")) | P70: =IF(O70="","",IF($N$4="M",IF(O70=1,(A70+B70+Q70)*C70*0.022*1.1,(A70+B70+Q70)*C70*0.022*1.15),IF(O70=1,(A70+B70+Q70)*C70*0.17*1.1,(A70+B70+Q70)*C70*0.17*1.15))) | Q70: =IF($N$4="M",IF(A70="","",IF(D70=1,50,IF(D70=2,100,IF(D70=21,100,IF(D70=3,200,0))))),IF(A70="","",IF(D70=1,2,IF(D70=2,4,IF(D70=21,4,IF(D70=3,8,0)))))) | R70: =COUNTIF(G70:J70,7) -> 0 | S70: =IF(A70="","",IF($N$4="M",A70*B70*0.000011111*R70*1.5,A70*B70/144*R70*1.5)) | T70: =COUNTIF(G70:J70,71) -> 0 | U70: =IF(A70="","",IF($N$4="M",A70*B70*0.000011111*T70*1.5,A70*B70/144*T70*1.5)) | V70: =COUNTIF(G70:J70,8) -> 0 | W70: =IF(A70="","",IF($N$4="M",(A70+B70)*2*0.0032808*V70,(A70+B70)*2*V70/12)) | X70: =COUNTIF(G70:J70,81) -> 0 | Y70: =IF(A70="","",IF($N$4="M",(A70+B70)*2*0.0032808*X70,(A70+B70)*2*X70/12)) | Z70: =COUNTIF(G70:J70,9) -> 0 | AA70: =COUNTIF(G70:J70,10) -> 0 | AB70: =IF(A70="","",IF($N$4="M",(A70+B70)*2*0.0032808*AA70,(A70+B70)*2*AA70/12)) | AC70: =COUNTIF(G70:J70,100) -> 0 | AE70: =COUNTIF(G70:J70,11) -> 0 | AF70: =IF(A70="","",IF($N$4="M",A70*B70*0.000011111*AE70,A70*B70/144*AE70)) | AG70: =COUNTIF(G70:J70,111) -> 0 | AH70: =IF(A70="","",IF($N$4="M",A70*B70*0.000011111*AG70,A70*B70/144*AG70)) | AI70: =COUNTIF(G70:J70,12) -> 0 | AJ70: =IF(A70="","",IF($N$4="M",A70*B70*0.000011111*AI70,A70*B70/144*AI70)) | AK70: =COUNTIF(G70:J70,13) -> 0 | AL70: =COUNTIF(G70:J70,131) -> 0 | AM70: =IF(A70="","",IF($N$4="M",A70*B70*0.000011111*AL70,A70*B70/144*AL70)) | AN70: =COUNTIF(G70:J70,14) -> 0 | AO70: =IF(A70="","",IF($N$4="M",A70*B70*0.000011111*AN70,A70*B70/144*AN70)) | AP70: =COUNTIF(G70:J70,141) -> 0 | AQ70: =IF(A70="","",IF($N$4="M",A70*B70*0.000011111*AP70,A70*B70/144*AP70)) | AR70: =COUNTIF(G70:J70,15) -> 0 | AS70: =COUNTIF(G70:J70,16) -> 0 | AT70: =IF(A70="","",IF($N$4="M",A70*B70*0.000011111*AS70,A70*B70/144*AS70)) | AU70: =IF(D70=61,C70,0) -> 0 | AV70: =IF(D70=61,L70,0) -> 0 | AW70: =IF(A70="","",(C70-AU70)) | AX70: =IF(A70="","",(L70-AV70))
A71: 300 | B71: 250 | C71: 7.6 | F71: HA | G71: 7 | K71: =IF($N$4="M",IF(A71="","",IF(D71=6,16,IF(A71<=$M$5,26,IF(A71<=$M$6,24,IF(A71<=$M$7,22,IF(A71<=$M$8,20,18)))))),IF(A71="","",IF(D71=6,16,IF(A71<=$P$5,26,IF(A71<=$P$6,24,IF(A71<=$P$7,22,IF(A71<=$P$8,20,18))))))) | L71: =IF($N$4="M",IF(A71="","",IF(K71=26,(A71+B71+Q71)*C71*0.02739,IF(K71=24,(A71+B71+Q71)*C71*0.02739,IF(K71=22,(A71+B71+Q71)*C71*0.0333,IF(K71=20,(A71+B71+Q71)*C71*0.0393,IF(K71=18,(A71+B71+Q71)*C71*0.0511,IF(K71=16,(A71+B71+Q71)*C71*0.0628))))))),IF(A71="","",IF(K71=26,(A71+B71+Q71)*C71*0.211,IF(K71=24,(A71+B71+Q71)*C71*0.211,IF(K71=22,(A71+B71+Q71)*C71*0.258,IF(K71=20,(A71+B71+Q71)*C71*0.304,IF(K71=18,(A71+B71+Q71)*C71*0.395,IF(K71=16,(A71+B71+Q71)*C71*0.487)))))))) | M71: =IF(D71=1,0.5,IF(D71=2,"1 F",IF(D71=21,"1 R",IF(D71=3,2,"")))) | N71: =IF(M71="","",IF($N$4="M",(A71+B71+Q71)*C71*0.022,(A71+B71+Q71)*C71*0.17)) | O71: =IF(D71=4,1,IF(D71=5,2,"")) | P71: =IF(O71="","",IF($N$4="M",IF(O71=1,(A71+B71+Q71)*C71*0.022*1.1,(A71+B71+Q71)*C71*0.022*1.15),IF(O71=1,(A71+B71+Q71)*C71*0.17*1.1,(A71+B71+Q71)*C71*0.17*1.15))) | Q71: =IF($N$4="M",IF(A71="","",IF(D71=1,50,IF(D71=2,100,IF(D71=21,100,IF(D71=3,200,0))))),IF(A71="","",IF(D71=1,2,IF(D71=2,4,IF(D71=21,4,IF(D71=3,8,0)))))) | R71: =COUNTIF(G71:J71,7) -> 0 | S71: =IF(A71="","",IF($N$4="M",A71*B71*0.000011111*R71*1.5,A71*B71/144*R71*1.5)) | T71: =COUNTIF(G71:J71,71) -> 0 | U71: =IF(A71="","",IF($N$4="M",A71*B71*0.000011111*T71*1.5,A71*B71/144*T71*1.5)) | V71: =COUNTIF(G71:J71,8) -> 0 | W71: =IF(A71="","",IF($N$4="M",(A71+B71)*2*0.0032808*V71,(A71+B71)*2*V71/12)) | X71: =COUNTIF(G71:J71,81) -> 0 | Y71: =IF(A71="","",IF($N$4="M",(A71+B71)*2*0.0032808*X71,(A71+B71)*2*X71/12)) | Z71: =COUNTIF(G71:J71,9) -> 0 | AA71: =COUNTIF(G71:J71,10) -> 0 | AB71: =IF(A71="","",IF($N$4="M",(A71+B71)*2*0.0032808*AA71,(A71+B71)*2*AA71/12)) | AC71: =COUNTIF(G71:J71,100) -> 0 | AE71: =COUNTIF(G71:J71,11) -> 0 | AF71: =IF(A71="","",IF($N$4="M",A71*B71*0.000011111*AE71,A71*B71/144*AE71)) | AG71: =COUNTIF(G71:J71,111) -> 0 | AH71: =IF(A71="","",IF($N$4="M",A71*B71*0.000011111*AG71,A71*B71/144*AG71)) | AI71: =COUNTIF(G71:J71,12) -> 0 | AJ71: =IF(A71="","",IF($N$4="M",A71*B71*0.000011111*AI71,A71*B71/144*AI71)) | AK71: =COUNTIF(G71:J71,13) -> 0 | AL71: =COUNTIF(G71:J71,131) -> 0 | AM71: =IF(A71="","",IF($N$4="M",A71*B71*0.000011111*AL71,A71*B71/144*AL71)) | AN71: =COUNTIF(G71:J71,14) -> 0 | AO71: =IF(A71="","",IF($N$4="M",A71*B71*0.000011111*AN71,A71*B71/144*AN71)) | AP71: =COUNTIF(G71:J71,141) -> 0 | AQ71: =IF(A71="","",IF($N$4="M",A71*B71*0.000011111*AP71,A71*B71/144*AP71)) | AR71: =COUNTIF(G71:J71,15) -> 0 | AS71: =COUNTIF(G71:J71,16) -> 0 | AT71: =IF(A71="","",IF($N$4="M",A71*B71*0.000011111*AS71,A71*B71/144*AS71)) | AU71: =IF(D71=61,C71,0) -> 0 | AV71: =IF(D71=61,L71,0) -> 0 | AW71: =IF(A71="","",(C71-AU71)) | AX71: =IF(A71="","",(L71-AV71))
A72: 300 | B72: 300 | C72: 4.6 | F72: HA | K72: =IF($N$4="M",IF(A72="","",IF(D72=6,16,IF(A72<=$M$5,26,IF(A72<=$M$6,24,IF(A72<=$M$7,22,IF(A72<=$M$8,20,18)))))),IF(A72="","",IF(D72=6,16,IF(A72<=$P$5,26,IF(A72<=$P$6,24,IF(A72<=$P$7,22,IF(A72<=$P$8,20,18))))))) | L72: =IF($N$4="M",IF(A72="","",IF(K72=26,(A72+B72+Q72)*C72*0.02739,IF(K72=24,(A72+B72+Q72)*C72*0.02739,IF(K72=22,(A72+B72+Q72)*C72*0.0333,IF(K72=20,(A72+B72+Q72)*C72*0.0393,IF(K72=18,(A72+B72+Q72)*C72*0.0511,IF(K72=16,(A72+B72+Q72)*C72*0.0628))))))),IF(A72="","",IF(K72=26,(A72+B72+Q72)*C72*0.211,IF(K72=24,(A72+B72+Q72)*C72*0.211,IF(K72=22,(A72+B72+Q72)*C72*0.258,IF(K72=20,(A72+B72+Q72)*C72*0.304,IF(K72=18,(A72+B72+Q72)*C72*0.395,IF(K72=16,(A72+B72+Q72)*C72*0.487)))))))) | M72: =IF(D72=1,0.5,IF(D72=2,"1 F",IF(D72=21,"1 R",IF(D72=3,2,"")))) | N72: =IF(M72="","",IF($N$4="M",(A72+B72+Q72)*C72*0.022,(A72+B72+Q72)*C72*0.17)) | O72: =IF(D72=4,1,IF(D72=5,2,"")) | P72: =IF(O72="","",IF($N$4="M",IF(O72=1,(A72+B72+Q72)*C72*0.022*1.1,(A72+B72+Q72)*C72*0.022*1.15),IF(O72=1,(A72+B72+Q72)*C72*0.17*1.1,(A72+B72+Q72)*C72*0.17*1.15))) | Q72: =IF($N$4="M",IF(A72="","",IF(D72=1,50,IF(D72=2,100,IF(D72=21,100,IF(D72=3,200,0))))),IF(A72="","",IF(D72=1,2,IF(D72=2,4,IF(D72=21,4,IF(D72=3,8,0)))))) | R72: =COUNTIF(G72:J72,7) -> 0 | S72: =IF(A72="","",IF($N$4="M",A72*B72*0.000011111*R72*1.5,A72*B72/144*R72*1.5)) | T72: =COUNTIF(G72:J72,71) -> 0 | U72: =IF(A72="","",IF($N$4="M",A72*B72*0.000011111*T72*1.5,A72*B72/144*T72*1.5)) | V72: =COUNTIF(G72:J72,8) -> 0 | W72: =IF(A72="","",IF($N$4="M",(A72+B72)*2*0.0032808*V72,(A72+B72)*2*V72/12)) | X72: =COUNTIF(G72:J72,81) -> 0 | Y72: =IF(A72="","",IF($N$4="M",(A72+B72)*2*0.0032808*X72,(A72+B72)*2*X72/12)) | Z72: =COUNTIF(G72:J72,9) -> 0 | AA72: =COUNTIF(G72:J72,10) -> 0 | AB72: =IF(A72="","",IF($N$4="M",(A72+B72)*2*0.0032808*AA72,(A72+B72)*2*AA72/12)) | AC72: =COUNTIF(G72:J72,100) -> 0 | AE72: =COUNTIF(G72:J72,11) -> 0 | AF72: =IF(A72="","",IF($N$4="M",A72*B72*0.000011111*AE72,A72*B72/144*AE72)) | AG72: =COUNTIF(G72:J72,111) -> 0 | AH72: =IF(A72="","",IF($N$4="M",A72*B72*0.000011111*AG72,A72*B72/144*AG72)) | AI72: =COUNTIF(G72:J72,12) -> 0 | AJ72: =IF(A72="","",IF($N$4="M",A72*B72*0.000011111*AI72,A72*B72/144*AI72)) | AK72: =COUNTIF(G72:J72,13) -> 0 | AL72: =COUNTIF(G72:J72,131) -> 0 | AM72: =IF(A72="","",IF($N$4="M",A72*B72*0.000011111*AL72,A72*B72/144*AL72)) | AN72: =COUNTIF(G72:J72,14) -> 0 | AO72: =IF(A72="","",IF($N$4="M",A72*B72*0.000011111*AN72,A72*B72/144*AN72)) | AP72: =COUNTIF(G72:J72,141) -> 0 | AQ72: =IF(A72="","",IF($N$4="M",A72*B72*0.000011111*AP72,A72*B72/144*AP72)) | AR72: =COUNTIF(G72:J72,15) -> 0 | AS72: =COUNTIF(G72:J72,16) -> 0 | AT72: =IF(A72="","",IF($N$4="M",A72*B72*0.000011111*AS72,A72*B72/144*AS72)) | AU72: =IF(D72=61,C72,0) -> 0 | AV72: =IF(D72=61,L72,0) -> 0 | AW72: =IF(A72="","",(C72-AU72)) | AX72: =IF(A72="","",(L72-AV72))
A73: 350 | B73: 200 | C73: 9.1 | F73: HA | G73: 13 | H73: 13 | K73: =IF($N$4="M",IF(A73="","",IF(D73=6,16,IF(A73<=$M$5,26,IF(A73<=$M$6,24,IF(A73<=$M$7,22,IF(A73<=$M$8,20,18)))))),IF(A73="","",IF(D73=6,16,IF(A73<=$P$5,26,IF(A73<=$P$6,24,IF(A73<=$P$7,22,IF(A73<=$P$8,20,18))))))) | L73: =IF($N$4="M",IF(A73="","",IF(K73=26,(A73+B73+Q73)*C73*0.02739,IF(K73=24,(A73+B73+Q73)*C73*0.02739,IF(K73=22,(A73+B73+Q73)*C73*0.0333,IF(K73=20,(A73+B73+Q73)*C73*0.0393,IF(K73=18,(A73+B73+Q73)*C73*0.0511,IF(K73=16,(A73+B73+Q73)*C73*0.0628))))))),IF(A73="","",IF(K73=26,(A73+B73+Q73)*C73*0.211,IF(K73=24,(A73+B73+Q73)*C73*0.211,IF(K73=22,(A73+B73+Q73)*C73*0.258,IF(K73=20,(A73+B73+Q73)*C73*0.304,IF(K73=18,(A73+B73+Q73)*C73*0.395,IF(K73=16,(A73+B73+Q73)*C73*0.487)))))))) | M73: =IF(D73=1,0.5,IF(D73=2,"1 F",IF(D73=21,"1 R",IF(D73=3,2,"")))) | N73: =IF(M73="","",IF($N$4="M",(A73+B73+Q73)*C73*0.022,(A73+B73+Q73)*C73*0.17)) | O73: =IF(D73=4,1,IF(D73=5,2,"")) | P73: =IF(O73="","",IF($N$4="M",IF(O73=1,(A73+B73+Q73)*C73*0.022*1.1,(A73+B73+Q73)*C73*0.022*1.15),IF(O73=1,(A73+B73+Q73)*C73*0.17*1.1,(A73+B73+Q73)*C73*0.17*1.15))) | Q73: =IF($N$4="M",IF(A73="","",IF(D73=1,50,IF(D73=2,100,IF(D73=21,100,IF(D73=3,200,0))))),IF(A73="","",IF(D73=1,2,IF(D73=2,4,IF(D73=21,4,IF(D73=3,8,0)))))) | R73: =COUNTIF(G73:J73,7) -> 0 | S73: =IF(A73="","",IF($N$4="M",A73*B73*0.000011111*R73*1.5,A73*B73/144*R73*1.5)) | T73: =COUNTIF(G73:J73,71) -> 0 | U73: =IF(A73="","",IF($N$4="M",A73*B73*0.000011111*T73*1.5,A73*B73/144*T73*1.5)) | V73: =COUNTIF(G73:J73,8) -> 0 | W73: =IF(A73="","",IF($N$4="M",(A73+B73)*2*0.0032808*V73,(A73+B73)*2*V73/12)) | X73: =COUNTIF(G73:J73,81) -> 0 | Y73: =IF(A73="","",IF($N$4="M",(A73+B73)*2*0.0032808*X73,(A73+B73)*2*X73/12)) | Z73: =COUNTIF(G73:J73,9) -> 0 | AA73: =COUNTIF(G73:J73,10) -> 0 | AB73: =IF(A73="","",IF($N$4="M",(A73+B73)*2*0.0032808*AA73,(A73+B73)*2*AA73/12)) | AC73: =COUNTIF(G73:J73,100) -> 0 | AE73: =COUNTIF(G73:J73,11) -> 0 | AF73: =IF(A73="","",IF($N$4="M",A73*B73*0.000011111*AE73,A73*B73/144*AE73)) | AG73: =COUNTIF(G73:J73,111) -> 0 | AH73: =IF(A73="","",IF($N$4="M",A73*B73*0.000011111*AG73,A73*B73/144*AG73)) | AI73: =COUNTIF(G73:J73,12) -> 0 | AJ73: =IF(A73="","",IF($N$4="M",A73*B73*0.000011111*AI73,A73*B73/144*AI73)) | AK73: =COUNTIF(G73:J73,13) -> 0 | AL73: =COUNTIF(G73:J73,131) -> 0 | AM73: =IF(A73="","",IF($N$4="M",A73*B73*0.000011111*AL73,A73*B73/144*AL73)) | AN73: =COUNTIF(G73:J73,14) -> 0 | AO73: =IF(A73="","",IF($N$4="M",A73*B73*0.000011111*AN73,A73*B73/144*AN73)) | AP73: =COUNTIF(G73:J73,141) -> 0 | AQ73: =IF(A73="","",IF($N$4="M",A73*B73*0.000011111*AP73,A73*B73/144*AP73)) | AR73: =COUNTIF(G73:J73,15) -> 0 | AS73: =COUNTIF(G73:J73,16) -> 0 | AT73: =IF(A73="","",IF($N$4="M",A73*B73*0.000011111*AS73,A73*B73/144*AS73)) | AU73: =IF(D73=61,C73,0) -> 0 | AV73: =IF(D73=61,L73,0) -> 0 | AW73: =IF(A73="","",(C73-AU73)) | AX73: =IF(A73="","",(L73-AV73))
A74: 350 | B74: 300 | C74: 47 | F74: HA | G74: 7 | K74: =IF($N$4="M",IF(A74="","",IF(D74=6,16,IF(A74<=$M$5,26,IF(A74<=$M$6,24,IF(A74<=$M$7,22,IF(A74<=$M$8,20,18)))))),IF(A74="","",IF(D74=6,16,IF(A74<=$P$5,26,IF(A74<=$P$6,24,IF(A74<=$P$7,22,IF(A74<=$P$8,20,18))))))) | L74: =IF($N$4="M",IF(A74="","",IF(K74=26,(A74+B74+Q74)*C74*0.02739,IF(K74=24,(A74+B74+Q74)*C74*0.02739,IF(K74=22,(A74+B74+Q74)*C74*0.0333,IF(K74=20,(A74+B74+Q74)*C74*0.0393,IF(K74=18,(A74+B74+Q74)*C74*0.0511,IF(K74=16,(A74+B74+Q74)*C74*0.0628))))))),IF(A74="","",IF(K74=26,(A74+B74+Q74)*C74*0.211,IF(K74=24,(A74+B74+Q74)*C74*0.211,IF(K74=22,(A74+B74+Q74)*C74*0.258,IF(K74=20,(A74+B74+Q74)*C74*0.304,IF(K74=18,(A74+B74+Q74)*C74*0.395,IF(K74=16,(A74+B74+Q74)*C74*0.487)))))))) | M74: =IF(D74=1,0.5,IF(D74=2,"1 F",IF(D74=21,"1 R",IF(D74=3,2,"")))) | N74: =IF(M74="","",IF($N$4="M",(A74+B74+Q74)*C74*0.022,(A74+B74+Q74)*C74*0.17)) | O74: =IF(D74=4,1,IF(D74=5,2,"")) | P74: =IF(O74="","",IF($N$4="M",IF(O74=1,(A74+B74+Q74)*C74*0.022*1.1,(A74+B74+Q74)*C74*0.022*1.15),IF(O74=1,(A74+B74+Q74)*C74*0.17*1.1,(A74+B74+Q74)*C74*0.17*1.15))) | Q74: =IF($N$4="M",IF(A74="","",IF(D74=1,50,IF(D74=2,100,IF(D74=21,100,IF(D74=3,200,0))))),IF(A74="","",IF(D74=1,2,IF(D74=2,4,IF(D74=21,4,IF(D74=3,8,0)))))) | R74: =COUNTIF(G74:J74,7) -> 0 | S74: =IF(A74="","",IF($N$4="M",A74*B74*0.000011111*R74*1.5,A74*B74/144*R74*1.5)) | T74: =COUNTIF(G74:J74,71) -> 0 | U74: =IF(A74="","",IF($N$4="M",A74*B74*0.000011111*T74*1.5,A74*B74/144*T74*1.5)) | V74: =COUNTIF(G74:J74,8) -> 0 | W74: =IF(A74="","",IF($N$4="M",(A74+B74)*2*0.0032808*V74,(A74+B74)*2*V74/12)) | X74: =COUNTIF(G74:J74,81) -> 0 | Y74: =IF(A74="","",IF($N$4="M",(A74+B74)*2*0.0032808*X74,(A74+B74)*2*X74/12)) | Z74: =COUNTIF(G74:J74,9) -> 0 | AA74: =COUNTIF(G74:J74,10) -> 0 | AB74: =IF(A74="","",IF($N$4="M",(A74+B74)*2*0.0032808*AA74,(A74+B74)*2*AA74/12)) | AC74: =COUNTIF(G74:J74,100) -> 0 | AE74: =COUNTIF(G74:J74,11) -> 0 | AF74: =IF(A74="","",IF($N$4="M",A74*B74*0.000011111*AE74,A74*B74/144*AE74)) | AG74: =COUNTIF(G74:J74,111) -> 0 | AH74: =IF(A74="","",IF($N$4="M",A74*B74*0.000011111*AG74,A74*B74/144*AG74)) | AI74: =COUNTIF(G74:J74,12) -> 0 | AJ74: =IF(A74="","",IF($N$4="M",A74*B74*0.000011111*AI74,A74*B74/144*AI74)) | AK74: =COUNTIF(G74:J74,13) -> 0 | AL74: =COUNTIF(G74:J74,131) -> 0 | AM74: =IF(A74="","",IF($N$4="M",A74*B74*0.000011111*AL74,A74*B74/144*AL74)) | AN74: =COUNTIF(G74:J74,14) -> 0 | AO74: =IF(A74="","",IF($N$4="M",A74*B74*0.000011111*AN74,A74*B74/144*AN74)) | AP74: =COUNTIF(G74:J74,141) -> 0 | AQ74: =IF(A74="","",IF($N$4="M",A74*B74*0.000011111*AP74,A74*B74/144*AP74)) | AR74: =COUNTIF(G74:J74,15) -> 0 | AS74: =COUNTIF(G74:J74,16) -> 0 | AT74: =IF(A74="","",IF($N$4="M",A74*B74*0.000011111*AS74,A74*B74/144*AS74)) | AU74: =IF(D74=61,C74,0) -> 0 | AV74: =IF(D74=61,L74,0) -> 0 | AW74: =IF(A74="","",(C74-AU74)) | AX74: =IF(A74="","",(L74-AV74))
A75: 350 | B75: 350 | C75: 0.4 | F75: HA | K75: =IF($N$4="M",IF(A75="","",IF(D75=6,16,IF(A75<=$M$5,26,IF(A75<=$M$6,24,IF(A75<=$M$7,22,IF(A75<=$M$8,20,18)))))),IF(A75="","",IF(D75=6,16,IF(A75<=$P$5,26,IF(A75<=$P$6,24,IF(A75<=$P$7,22,IF(A75<=$P$8,20,18))))))) | L75: =IF($N$4="M",IF(A75="","",IF(K75=26,(A75+B75+Q75)*C75*0.02739,IF(K75=24,(A75+B75+Q75)*C75*0.02739,IF(K75=22,(A75+B75+Q75)*C75*0.0333,IF(K75=20,(A75+B75+Q75)*C75*0.0393,IF(K75=18,(A75+B75+Q75)*C75*0.0511,IF(K75=16,(A75+B75+Q75)*C75*0.0628))))))),IF(A75="","",IF(K75=26,(A75+B75+Q75)*C75*0.211,IF(K75=24,(A75+B75+Q75)*C75*0.211,IF(K75=22,(A75+B75+Q75)*C75*0.258,IF(K75=20,(A75+B75+Q75)*C75*0.304,IF(K75=18,(A75+B75+Q75)*C75*0.395,IF(K75=16,(A75+B75+Q75)*C75*0.487)))))))) | M75: =IF(D75=1,0.5,IF(D75=2,"1 F",IF(D75=21,"1 R",IF(D75=3,2,"")))) | N75: =IF(M75="","",IF($N$4="M",(A75+B75+Q75)*C75*0.022,(A75+B75+Q75)*C75*0.17)) | O75: =IF(D75=4,1,IF(D75=5,2,"")) | P75: =IF(O75="","",IF($N$4="M",IF(O75=1,(A75+B75+Q75)*C75*0.022*1.1,(A75+B75+Q75)*C75*0.022*1.15),IF(O75=1,(A75+B75+Q75)*C75*0.17*1.1,(A75+B75+Q75)*C75*0.17*1.15))) | Q75: =IF($N$4="M",IF(A75="","",IF(D75=1,50,IF(D75=2,100,IF(D75=21,100,IF(D75=3,200,0))))),IF(A75="","",IF(D75=1,2,IF(D75=2,4,IF(D75=21,4,IF(D75=3,8,0)))))) | R75: =COUNTIF(G75:J75,7) -> 0 | S75: =IF(A75="","",IF($N$4="M",A75*B75*0.000011111*R75*1.5,A75*B75/144*R75*1.5)) | T75: =COUNTIF(G75:J75,71) -> 0 | U75: =IF(A75="","",IF($N$4="M",A75*B75*0.000011111*T75*1.5,A75*B75/144*T75*1.5)) | V75: =COUNTIF(G75:J75,8) -> 0 | W75: =IF(A75="","",IF($N$4="M",(A75+B75)*2*0.0032808*V75,(A75+B75)*2*V75/12)) | X75: =COUNTIF(G75:J75,81) -> 0 | Y75: =IF(A75="","",IF($N$4="M",(A75+B75)*2*0.0032808*X75,(A75+B75)*2*X75/12)) | Z75: =COUNTIF(G75:J75,9) -> 0 | AA75: =COUNTIF(G75:J75,10) -> 0 | AB75: =IF(A75="","",IF($N$4="M",(A75+B75)*2*0.0032808*AA75,(A75+B75)*2*AA75/12)) | AC75: =COUNTIF(G75:J75,100) -> 0 | AE75: =COUNTIF(G75:J75,11) -> 0 | AF75: =IF(A75="","",IF($N$4="M",A75*B75*0.000011111*AE75,A75*B75/144*AE75)) | AG75: =COUNTIF(G75:J75,111) -> 0 | AH75: =IF(A75="","",IF($N$4="M",A75*B75*0.000011111*AG75,A75*B75/144*AG75)) | AI75: =COUNTIF(G75:J75,12) -> 0 | AJ75: =IF(A75="","",IF($N$4="M",A75*B75*0.000011111*AI75,A75*B75/144*AI75)) | AK75: =COUNTIF(G75:J75,13) -> 0 | AL75: =COUNTIF(G75:J75,131) -> 0 | AM75: =IF(A75="","",IF($N$4="M",A75*B75*0.000011111*AL75,A75*B75/144*AL75)) | AN75: =COUNTIF(G75:J75,14) -> 0 | AO75: =IF(A75="","",IF($N$4="M",A75*B75*0.000011111*AN75,A75*B75/144*AN75)) | AP75: =COUNTIF(G75:J75,141) -> 0 | AQ75: =IF(A75="","",IF($N$4="M",A75*B75*0.000011111*AP75,A75*B75/144*AP75)) | AR75: =COUNTIF(G75:J75,15) -> 0 | AS75: =COUNTIF(G75:J75,16) -> 0 | AT75: =IF(A75="","",IF($N$4="M",A75*B75*0.000011111*AS75,A75*B75/144*AS75)) | AU75: =IF(D75=61,C75,0) -> 0 | AV75: =IF(D75=61,L75,0) -> 0 | AW75: =IF(A75="","",(C75-AU75)) | AX75: =IF(A75="","",(L75-AV75))
A76: 400 | B76: 200 | C76: 10.7 | F76: HA | K76: =IF($N$4="M",IF(A76="","",IF(D76=6,16,IF(A76<=$M$5,26,IF(A76<=$M$6,24,IF(A76<=$M$7,22,IF(A76<=$M$8,20,18)))))),IF(A76="","",IF(D76=6,16,IF(A76<=$P$5,26,IF(A76<=$P$6,24,IF(A76<=$P$7,22,IF(A76<=$P$8,20,18))))))) | L76: =IF($N$4="M",IF(A76="","",IF(K76=26,(A76+B76+Q76)*C76*0.02739,IF(K76=24,(A76+B76+Q76)*C76*0.02739,IF(K76=22,(A76+B76+Q76)*C76*0.0333,IF(K76=20,(A76+B76+Q76)*C76*0.0393,IF(K76=18,(A76+B76+Q76)*C76*0.0511,IF(K76=16,(A76+B76+Q76)*C76*0.0628))))))),IF(A76="","",IF(K76=26,(A76+B76+Q76)*C76*0.211,IF(K76=24,(A76+B76+Q76)*C76*0.211,IF(K76=22,(A76+B76+Q76)*C76*0.258,IF(K76=20,(A76+B76+Q76)*C76*0.304,IF(K76=18,(A76+B76+Q76)*C76*0.395,IF(K76=16,(A76+B76+Q76)*C76*0.487)))))))) | M76: =IF(D76=1,0.5,IF(D76=2,"1 F",IF(D76=21,"1 R",IF(D76=3,2,"")))) | N76: =IF(M76="","",IF($N$4="M",(A76+B76+Q76)*C76*0.022,(A76+B76+Q76)*C76*0.17)) | O76: =IF(D76=4,1,IF(D76=5,2,"")) | P76: =IF(O76="","",IF($N$4="M",IF(O76=1,(A76+B76+Q76)*C76*0.022*1.1,(A76+B76+Q76)*C76*0.022*1.15),IF(O76=1,(A76+B76+Q76)*C76*0.17*1.1,(A76+B76+Q76)*C76*0.17*1.15))) | Q76: =IF($N$4="M",IF(A76="","",IF(D76=1,50,IF(D76=2,100,IF(D76=21,100,IF(D76=3,200,0))))),IF(A76="","",IF(D76=1,2,IF(D76=2,4,IF(D76=21,4,IF(D76=3,8,0)))))) | R76: =COUNTIF(G76:J76,7) -> 0 | S76: =IF(A76="","",IF($N$4="M",A76*B76*0.000011111*R76*1.5,A76*B76/144*R76*1.5)) | T76: =COUNTIF(G76:J76,71) -> 0 | U76: =IF(A76="","",IF($N$4="M",A76*B76*0.000011111*T76*1.5,A76*B76/144*T76*1.5)) | V76: =COUNTIF(G76:J76,8) -> 0 | W76: =IF(A76="","",IF($N$4="M",(A76+B76)*2*0.0032808*V76,(A76+B76)*2*V76/12)) | X76: =COUNTIF(G76:J76,81) -> 0 | Y76: =IF(A76="","",IF($N$4="M",(A76+B76)*2*0.0032808*X76,(A76+B76)*2*X76/12)) | Z76: =COUNTIF(G76:J76,9) -> 0 | AA76: =COUNTIF(G76:J76,10) -> 0 | AB76: =IF(A76="","",IF($N$4="M",(A76+B76)*2*0.0032808*AA76,(A76+B76)*2*AA76/12)) | AC76: =COUNTIF(G76:J76,100) -> 0 | AE76: =COUNTIF(G76:J76,11) -> 0 | AF76: =IF(A76="","",IF($N$4="M",A76*B76*0.000011111*AE76,A76*B76/144*AE76)) | AG76: =COUNTIF(G76:J76,111) -> 0 | AH76: =IF(A76="","",IF($N$4="M",A76*B76*0.000011111*AG76,A76*B76/144*AG76)) | AI76: =COUNTIF(G76:J76,12) -> 0 | AJ76: =IF(A76="","",IF($N$4="M",A76*B76*0.000011111*AI76,A76*B76/144*AI76)) | AK76: =COUNTIF(G76:J76,13) -> 0 | AL76: =COUNTIF(G76:J76,131) -> 0 | AM76: =IF(A76="","",IF($N$4="M",A76*B76*0.000011111*AL76,A76*B76/144*AL76)) | AN76: =COUNTIF(G76:J76,14) -> 0 | AO76: =IF(A76="","",IF($N$4="M",A76*B76*0.000011111*AN76,A76*B76/144*AN76)) | AP76: =COUNTIF(G76:J76,141) -> 0 | AQ76: =IF(A76="","",IF($N$4="M",A76*B76*0.000011111*AP76,A76*B76/144*AP76)) | AR76: =COUNTIF(G76:J76,15) -> 0 | AS76: =COUNTIF(G76:J76,16) -> 0 | AT76: =IF(A76="","",IF($N$4="M",A76*B76*0.000011111*AS76,A76*B76/144*AS76)) | AU76: =IF(D76=61,C76,0) -> 0 | AV76: =IF(D76=61,L76,0) -> 0 | AW76: =IF(A76="","",(C76-AU76)) | AX76: =IF(A76="","",(L76-AV76))
A77: 400 | B77: 200 | C77: 2.4 | F77: HA | G77: 21 | K77: =IF($N$4="M",IF(A77="","",IF(D77=6,16,IF(A77<=$M$5,26,IF(A77<=$M$6,24,IF(A77<=$M$7,22,IF(A77<=$M$8,20,18)))))),IF(A77="","",IF(D77=6,16,IF(A77<=$P$5,26,IF(A77<=$P$6,24,IF(A77<=$P$7,22,IF(A77<=$P$8,20,18))))))) | L77: =IF($N$4="M",IF(A77="","",IF(K77=26,(A77+B77+Q77)*C77*0.02739,IF(K77=24,(A77+B77+Q77)*C77*0.02739,IF(K77=22,(A77+B77+Q77)*C77*0.0333,IF(K77=20,(A77+B77+Q77)*C77*0.0393,IF(K77=18,(A77+B77+Q77)*C77*0.0511,IF(K77=16,(A77+B77+Q77)*C77*0.0628))))))),IF(A77="","",IF(K77=26,(A77+B77+Q77)*C77*0.211,IF(K77=24,(A77+B77+Q77)*C77*0.211,IF(K77=22,(A77+B77+Q77)*C77*0.258,IF(K77=20,(A77+B77+Q77)*C77*0.304,IF(K77=18,(A77+B77+Q77)*C77*0.395,IF(K77=16,(A77+B77+Q77)*C77*0.487)))))))) | M77: =IF(D77=1,0.5,IF(D77=2,"1 F",IF(D77=21,"1 R",IF(D77=3,2,"")))) | N77: =IF(M77="","",IF($N$4="M",(A77+B77+Q77)*C77*0.022,(A77+B77+Q77)*C77*0.17)) | O77: =IF(D77=4,1,IF(D77=5,2,"")) | P77: =IF(O77="","",IF($N$4="M",IF(O77=1,(A77+B77+Q77)*C77*0.022*1.1,(A77+B77+Q77)*C77*0.022*1.15),IF(O77=1,(A77+B77+Q77)*C77*0.17*1.1,(A77+B77+Q77)*C77*0.17*1.15))) | Q77: =IF($N$4="M",IF(A77="","",IF(D77=1,50,IF(D77=2,100,IF(D77=21,100,IF(D77=3,200,0))))),IF(A77="","",IF(D77=1,2,IF(D77=2,4,IF(D77=21,4,IF(D77=3,8,0)))))) | R77: =COUNTIF(G77:J77,7) -> 0 | S77: =IF(A77="","",IF($N$4="M",A77*B77*0.000011111*R77*1.5,A77*B77/144*R77*1.5)) | T77: =COUNTIF(G77:J77,71) -> 0 | U77: =IF(A77="","",IF($N$4="M",A77*B77*0.000011111*T77*1.5,A77*B77/144*T77*1.5)) | V77: =COUNTIF(G77:J77,8) -> 0 | W77: =IF(A77="","",IF($N$4="M",(A77+B77)*2*0.0032808*V77,(A77+B77)*2*V77/12)) | X77: =COUNTIF(G77:J77,81) -> 0 | Y77: =IF(A77="","",IF($N$4="M",(A77+B77)*2*0.0032808*X77,(A77+B77)*2*X77/12)) | Z77: =COUNTIF(G77:J77,9) -> 0 | AA77: =COUNTIF(G77:J77,10) -> 0 | AB77: =IF(A77="","",IF($N$4="M",(A77+B77)*2*0.0032808*AA77,(A77+B77)*2*AA77/12)) | AC77: =COUNTIF(G77:J77,100) -> 0 | AE77: =COUNTIF(G77:J77,11) -> 0 | AF77: =IF(A77="","",IF($N$4="M",A77*B77*0.000011111*AE77,A77*B77/144*AE77)) | AG77: =COUNTIF(G77:J77,111) -> 0 | AH77: =IF(A77="","",IF($N$4="M",A77*B77*0.000011111*AG77,A77*B77/144*AG77)) | AI77: =COUNTIF(G77:J77,12) -> 0 | AJ77: =IF(A77="","",IF($N$4="M",A77*B77*0.000011111*AI77,A77*B77/144*AI77)) | AK77: =COUNTIF(G77:J77,13) -> 0 | AL77: =COUNTIF(G77:J77,131) -> 0 | AM77: =IF(A77="","",IF($N$4="M",A77*B77*0.000011111*AL77,A77*B77/144*AL77)) | AN77: =COUNTIF(G77:J77,14) -> 0 | AO77: =IF(A77="","",IF($N$4="M",A77*B77*0.000011111*AN77,A77*B77/144*AN77)) | AP77: =COUNTIF(G77:J77,141) -> 0 | AQ77: =IF(A77="","",IF($N$4="M",A77*B77*0.000011111*AP77,A77*B77/144*AP77)) | AR77: =COUNTIF(G77:J77,15) -> 0 | AS77: =COUNTIF(G77:J77,16) -> 0 | AT77: =IF(A77="","",IF($N$4="M",A77*B77*0.000011111*AS77,A77*B77/144*AS77)) | AU77: =IF(D77=61,C77,0) -> 0 | AV77: =IF(D77=61,L77,0) -> 0 | AW77: =IF(A77="","",(C77-AU77)) | AX77: =IF(A77="","",(L77-AV77))
A78: 400 | B78: 250 | C78: 41.1 | F78: HA | G78: 7 | H78: 13 | K78: =IF($N$4="M",IF(A78="","",IF(D78=6,16,IF(A78<=$M$5,26,IF(A78<=$M$6,24,IF(A78<=$M$7,22,IF(A78<=$M$8,20,18)))))),IF(A78="","",IF(D78=6,16,IF(A78<=$P$5,26,IF(A78<=$P$6,24,IF(A78<=$P$7,22,IF(A78<=$P$8,20,18))))))) | L78: =IF($N$4="M",IF(A78="","",IF(K78=26,(A78+B78+Q78)*C78*0.02739,IF(K78=24,(A78+B78+Q78)*C78*0.02739,IF(K78=22,(A78+B78+Q78)*C78*0.0333,IF(K78=20,(A78+B78+Q78)*C78*0.0393,IF(K78=18,(A78+B78+Q78)*C78*0.0511,IF(K78=16,(A78+B78+Q78)*C78*0.0628))))))),IF(A78="","",IF(K78=26,(A78+B78+Q78)*C78*0.211,IF(K78=24,(A78+B78+Q78)*C78*0.211,IF(K78=22,(A78+B78+Q78)*C78*0.258,IF(K78=20,(A78+B78+Q78)*C78*0.304,IF(K78=18,(A78+B78+Q78)*C78*0.395,IF(K78=16,(A78+B78+Q78)*C78*0.487)))))))) | M78: =IF(D78=1,0.5,IF(D78=2,"1 F",IF(D78=21,"1 R",IF(D78=3,2,"")))) | N78: =IF(M78="","",IF($N$4="M",(A78+B78+Q78)*C78*0.022,(A78+B78+Q78)*C78*0.17)) | O78: =IF(D78=4,1,IF(D78=5,2,"")) | P78: =IF(O78="","",IF($N$4="M",IF(O78=1,(A78+B78+Q78)*C78*0.022*1.1,(A78+B78+Q78)*C78*0.022*1.15),IF(O78=1,(A78+B78+Q78)*C78*0.17*1.1,(A78+B78+Q78)*C78*0.17*1.15))) | Q78: =IF($N$4="M",IF(A78="","",IF(D78=1,50,IF(D78=2,100,IF(D78=21,100,IF(D78=3,200,0))))),IF(A78="","",IF(D78=1,2,IF(D78=2,4,IF(D78=21,4,IF(D78=3,8,0)))))) | R78: =COUNTIF(G78:J78,7) -> 0 | S78: =IF(A78="","",IF($N$4="M",A78*B78*0.000011111*R78*1.5,A78*B78/144*R78*1.5)) | T78: =COUNTIF(G78:J78,71) -> 0 | U78: =IF(A78="","",IF($N$4="M",A78*B78*0.000011111*T78*1.5,A78*B78/144*T78*1.5)) | V78: =COUNTIF(G78:J78,8) -> 0 | W78: =IF(A78="","",IF($N$4="M",(A78+B78)*2*0.0032808*V78,(A78+B78)*2*V78/12)) | X78: =COUNTIF(G78:J78,81) -> 0 | Y78: =IF(A78="","",IF($N$4="M",(A78+B78)*2*0.0032808*X78,(A78+B78)*2*X78/12)) | Z78: =COUNTIF(G78:J78,9) -> 0 | AA78: =COUNTIF(G78:J78,10) -> 0 | AB78: =IF(A78="","",IF($N$4="M",(A78+B78)*2*0.0032808*AA78,(A78+B78)*2*AA78/12)) | AC78: =COUNTIF(G78:J78,100) -> 0 | AE78: =COUNTIF(G78:J78,11) -> 0 | AF78: =IF(A78="","",IF($N$4="M",A78*B78*0.000011111*AE78,A78*B78/144*AE78)) | AG78: =COUNTIF(G78:J78,111) -> 0 | AH78: =IF(A78="","",IF($N$4="M",A78*B78*0.000011111*AG78,A78*B78/144*AG78)) | AI78: =COUNTIF(G78:J78,12) -> 0 | AJ78: =IF(A78="","",IF($N$4="M",A78*B78*0.000011111*AI78,A78*B78/144*AI78)) | AK78: =COUNTIF(G78:J78,13) -> 0 | AL78: =COUNTIF(G78:J78,131) -> 0 | AM78: =IF(A78="","",IF($N$4="M",A78*B78*0.000011111*AL78,A78*B78/144*AL78)) | AN78: =COUNTIF(G78:J78,14) -> 0 | AO78: =IF(A78="","",IF($N$4="M",A78*B78*0.000011111*AN78,A78*B78/144*AN78)) | AP78: =COUNTIF(G78:J78,141) -> 0 | AQ78: =IF(A78="","",IF($N$4="M",A78*B78*0.000011111*AP78,A78*B78/144*AP78)) | AR78: =COUNTIF(G78:J78,15) -> 0 | AS78: =COUNTIF(G78:J78,16) -> 0 | AT78: =IF(A78="","",IF($N$4="M",A78*B78*0.000011111*AS78,A78*B78/144*AS78)) | AU78: =IF(D78=61,C78,0) -> 0 | AV78: =IF(D78=61,L78,0) -> 0 | AW78: =IF(A78="","",(C78-AU78)) | AX78: =IF(A78="","",(L78-AV78))
